Workbook

Sheet ENERO
B2: Cobranza Total 2025 | D2: =SUM(S2+S3+S4+S5+S6+S7+S8+S9+S10+S11+S12+D5+S13) -> 623596.23 | E2: Saldos 2024 | S2: =G214 -> 45163.987
E3: Enero`25 | S3: =H214 -> 0
B4: COBRANZA ENERO 2025 | E4: Febrero´25 | S4: =I214 -> 0
B5: Enero'2025 | D5: =S214+T214+U214 -> 578432.24 | E5: Marzo'25 | S5: =J214 -> 0
B6: Recuperación del 01 al 05 | D6: =SUM(V214:Z214) -> 7187 | E6: Abril´25 | S6: =K214 -> 0
B7: Recuperación del 06 al 12 | D7: =SUM(AA214:AG214) -> 155765.9 | E7: Mayo´25 | S7: =L214 -> 0
B8: Recuperación del 13 al 19 | D8: =SUM(AH214:AN214) -> 258118.96 | E8: Junio´25 | S8: =M214 -> 0
B9: Recuperación del 20 al 26 | D9: =SUM(AO214:AU214) -> 92161.09 | E9: Julio´25 | S9: =N214 -> 0
B10: Recuperación del 27 al 31 | D10: =SUM(AV214:AZ214) -> 55053.97 | E10: Agosto'25 | S10: =O214 -> 0
E11: Septiembre'25 | S11: =P214 -> 0
E12: Octubre'25 | S12: =Q214 -> 0
B13: Total Recuperado | D13: =SUM(D6:D11) -> 568286.92 | E13: Noviembre'25 | S13: =R214 -> 0
B14: Por Recuperar | D14: =D2-D13 -> 55309.31 | E14: Total de Arrastre: | S14: =SUM(S2:S13) -> 45163.987
A16: NO. | B16: CLIENTE | C16: DATOS FISCALES | D16: CONTACTO | E16: UNI | F16: VENTA | G16: ATRASO | S16: IMPORTE ENE´2025 | T16: SERV. EXTRAS | U16: DES % | V16: 1 | W16: 2 | X16: 3 | Y16: 4 | Z16: 5 | AA16: 6 | AB16: 7 | AC16: 8 | AD16: 9 | AE16: 10 | AF16: 11 | AG16: 12 | AH16: 13 | AI16: 14 | AJ16: 15 | AK16: 16 | AL16: 17 | AM16: 18 | AN16: 19 | AO16: 20 | AP16: 21 | AQ16: 22 | AR16: 23 | AS16: 24 | AT16: 25 | AU16: 26 | AV16: 27 | AW16: 28 | AX16: 29 | AY16: 30 | AZ16: 31 | BA16: SALDOS PENDIENTES | BB16: COMENTARIOS | BC16: ESTATUS PROMESA DE PAGO
G17: 2024 | H17: ENE | I17: FEB | J17: MAR | K17: ABR | L17: MAY | M17: JUN | N17: JUL | O17: AGO | P17: SEP | Q17: OCT | R17: NOV | V17: M | W17: J | X17: V | Y17: S | Z17: D | AA17: L | AB17: M | AC17: M | AD17: J | AE17: V | AF17: S | AG17: D | AH17: L | AI17: M | AJ17: M | AK17: J | AL17: V | AM17: S | AN17: D | AO17: L | AP17: M | AQ17: M | AR17: J | AS17: V | AT17: S | AU17: D | AV17: L | AW17: M | AX17: M | AY17: J | AZ17: V
A18: 1 | B18: ADRIANA ORANDAY DAVILA - RODRIGO ALANIS | D18: Rodrigo Alanis - 81 2861 1509 Email:adrianaoranday@gmail.com alanis_rodrigo@hotmail.com | E18: 1 | F18: JOSE LUIS | G18: =[1]DICIEMBRE!$BA$91 -> 290 | S18: =(250*0.16+250)*E18 -> 290 | BA18: =SUM(G18+S18+T18-U18-V18-W18-X18-Y18-Z18-AA18-AB18-AC18-AD18-AE18-AF18-AG18-AH18-AI18-AJ18-AK18-AL18-AM18-AN18-AO18-AP18-AQ18-AR18-AS18-AT18-AU18-AV18-AW18-AX18-AY18-AZ18) -> 580
A19: 2 | B19: ALIMENTOS REGIOMONTANOS PERCAM - ALIMENTOS GRUPER | C19: Nombre de la Empresa: ALIMENTOS GUPER S.A. DE C.V. Contacto: Nancy Paola Perales Teléfono: 811 801 4266 Email: alimentosgupersacv@gmail.com | D19: Alejandro Garcia - 81 2034 3938 Nancy Paola Perales - 8118014266 Alimentosregiopercam@gmail.com alimentosgupersacv@gmail.com | E19: 20 | F19: DANIEL ESTRADA | G19: =[1]DICIEMBRE!$BA$21 -> -0.3952 | S19: =(300*0.16+300)*E19 -> 6960 | T19: =1500*0.16+1500 -> 1740 | AH19: 8700 | BA19: =SUM(G19+S19+T19-U19-V19-W19-X19-Y19-Z19-AA19-AB19-AC19-AD19-AE19-AF19-AG19-AH19-AI19-AJ19-AK19-AL19-AM19-AN19-AO19-AP19-AQ19-AR19-AS19-AT19-AU19-AV19-AW19-AX19-AY19-AZ19) -> -0.3952 | BB19: COB. ENE'25: 1 REVISION Y 2 RE-INST.
A20: 3 | B20: AUTO EXPRESS GERAL 21 S.A. DE C.V. - LUIS GERARDO BOLAÑOS GARCIA | C20: Nombre de la Empresa: LUIS GERARDO BOLAÑOS GARCIA RFC. BOGL8702094H5 CFDI: Gastos en general Forma de Pago: Transferencia Teléfono: 811 027 0226 Contacto: Luis Gerardo Bolaños García Email: luismty0902@gmail.com; | D20: Luis Gerardo Bolaños García - 811 027 0226 Email:expressgeral19@gmail.com luismty0902@gmail.com | E20: 5 | F20: JOSE LUIS | G20: =[1]DICIEMBRE!$BA$75 -> 3190.0028 | S20: =(280*0.16+280)*E20 -> 1624 | T20: =450*0.16+450 -> 522 | AW20: 5336 | BA20: =SUM(G20+S20+T20-U20-V20-W20-X20-Y20-Z20-AA20-AB20-AC20-AD20-AE20-AF20-AG20-AH20-AI20-AJ20-AK20-AL20-AM20-AN20-AO20-AP20-AQ20-AR20-AS20-AT20-AU20-AV20-AW20-AX20-AY20-AZ20) -> 0.0028 | BB20: COB. ENE'25: 1 REVISION
A21: 4 | B21: AUTOEXPRESS MATA | C21: Nombre de la Empresa: AUTOEXPRESS MATA S.A. DE C.V. RFC. AMA040520BZ2 CFDI : Forma de Pago: Transferencia Teléfono: 81 1029 1017 Contacto: Edgar Garza Email: | D21: COMODATO Edgar Garza - 81 1029 1017 | E21: 3 | F21: JOSE LUIS | G21: =[1]DICIEMBRE!$BA$23 -> -0.0032 | S21: =(299*0.16+299)*E21 -> 1040.52 | AJ21: 1040.52 | BA21: =SUM(G21+S21+T21-U21-V21-W21-X21-Y21-Z21-AA21-AB21-AC21-AD21-AE21-AF21-AG21-AH21-AI21-AJ21-AK21-AL21-AM21-AN21-AO21-AP21-AQ21-AR21-AS21-AT21-AU21-AV21-AW21-AX21-AY21-AZ21) -> -0.0032
A22: 5 | B22: AUTOREDES EL BAJIO | D22: COMODATO Mane Troncoso -833 192 6706 Email:admontubored@hotmail.com | E22: 10 | F22: JOSE LUIS | G22: =[1]DICIEMBRE!$BA$24 -> -0.3952 | S22: =(270*0.16+270)*E22 -> 3132 | AA22: 3132 | BA22: =SUM(G22+S22+T22-U22-V22-W22-X22-Y22-Z22-AA22-AB22-AC22-AD22-AE22-AF22-AG22-AH22-AI22-AJ22-AK22-AL22-AM22-AN22-AO22-AP22-AQ22-AR22-AS22-AT22-AU22-AV22-AW22-AX22-AY22-AZ22) -> -0.3952
A23: 6 | B23: BAWOMA CONTROL TOTAL S.A. DE C.V. - FUMIGAZ | C23: Nombre de la Empresa: BAWOMA CONTROL TOTAL S.A. DE C.V. RFC.: BCT100310834 CFDI: Gastos en General Forma de Pago: Transferencia Teléfono: 81 1811 0645 Contacto: Manuel Rico Email: supervisorfumigaz@outlook.com | D23: COMODATO Manuel Rico - 81 1811 0645 Email:supervisorfumigaz@outlook.com | E23: 2 | F23: JOSE LUIS | G23: =[1]DICIEMBRE!$BA$48 -> 696 | S23: =(300*0.16+300)*1 -> 348 | AR23: 348 | BA23: =SUM(G23+S23+T23-U23-V23-W23-X23-Y23-Z23-AA23-AB23-AC23-AD23-AE23-AF23-AG23-AH23-AI23-AJ23-AK23-AL23-AM23-AN23-AO23-AP23-AQ23-AR23-AS23-AT23-AU23-AV23-AW23-AX23-AY23-AZ23) -> 696 | BB23: PDTE. 1 DES-INST. YA PAGADA
A24: 7 | B24: BE ONE SYSTEMS | D24: Lydia Colunga - 81 1176 3598 Edgar Valentin (Pagos) - 81 1970 7000 Email:edgar.valentin@beone.mx lydia@beone.mx | E24: 1 | F24: JOSE LUIS | G24: =[1]DICIEMBRE!$BA$25 -> 0 | S24: =250*0.16+250 -> 290 | AA24: 290 | BA24: =SUM(G24+S24+T24-U24-V24-W24-X24-Y24-Z24-AA24-AB24-AC24-AD24-AE24-AF24-AG24-AH24-AI24-AJ24-AK24-AL24-AM24-AN24-AO24-AP24-AQ24-AR24-AS24-AT24-AU24-AV24-AW24-AX24-AY24-AZ24) -> 0
A25: 8 | B25: BRANDO IVAN MARTINEZ GOVEA - JOSUE FERNANDEZ | D25: Josue Fernandez - 81 1977 0958 Email:jfhz@icloud.com | E25: 5 | F25: JOSE LUIS | G25: =[1]DICIEMBRE!$BA$64 -> 0.0068 | S25: =(250*0.16+250)*E25 -> 1450 | AA25: 1450 | BA25: =SUM(G25+S25+T25-U25-V25-W25-X25-Y25-Z25-AA25-AB25-AC25-AD25-AE25-AF25-AG25-AH25-AI25-AJ25-AK25-AL25-AM25-AN25-AO25-AP25-AQ25-AR25-AS25-AT25-AU25-AV25-AW25-AX25-AY25-AZ25) -> 0.0068
A26: 9 | B26: CARNES RIBHAUS | D26: COMODATO Tania Reyes - 81 1631 2529 Roberta Treviño - 81 1909 7008 Email:facturas@carnesribhaus.com.mx robertaribhaus@gmail.com | E26: 5 | F26: JOSE LUIS | G26: =[1]DICIEMBRE!$BA$27 -> 0.004 | S26: =(279*0.16+279)*E26 -> 1618.2 | AA26: 1618.2 | BA26: =SUM(G26+S26+T26-U26-V26-W26-X26-Y26-Z26-AA26-AB26-AC26-AD26-AE26-AF26-AG26-AH26-AI26-AJ26-AK26-AL26-AM26-AN26-AO26-AP26-AQ26-AR26-AS26-AT26-AU26-AV26-AW26-AX26-AY26-AZ26) -> 0.004
A27: 10 | B27: CARPACK, S.A. DE C.V. | C27: Nombre de la Empresa: CARPACK S.A. DE C.V. RFC.: CAR070302UU2 CFDI: Gastos en General Forma de Pago: TransferenciaTeléfono: 811 277 9070 Contacto: Kelly Mayorga Email: compras@carpack.com.mx; antonioespinosa@carpack.com.mx; elizabeth@carpack.com.mx; | D27: COMODATO Kelly Mayorga - 8112779070 Elizabeth Campos - 8116635976 8181919205 Ext. 107 Email:antonioespinosa@carpack.com.mx; elizabeth@carpack.com.mx; compras@carpack.com.mx; pagos@carpack.com.mx | E27: 5 | F27: JOSE LUIS | G27: =[1]DICIEMBRE!$BA$28 -> 0.0028 | S27: =(280*0.16+280)*E27 -> 1624 | T27: =500*0.16+500 -> 580 | U27: 324.8 | AJ27: 1879.2 | BA27: =SUM(G27+S27+T27-U27-V27-W27-X27-Y27-Z27-AA27-AB27-AC27-AD27-AE27-AF27-AG27-AH27-AI27-AJ27-AK27-AL27-AM27-AN27-AO27-AP27-AQ27-AR27-AS27-AT27-AU27-AV27-AW27-AX27-AY27-AZ27) -> 0.0028 | BB27: COB. ENE'25: 1 DES-INST. Y REBAJE DE 1 MENS. POR BAJA Y PAGADA EN DIC'24
A28: 11 | B28: COMERCIALIZADORA AGROPECUARIA ICK -JORGE ADRIAN RIVERA | C28: Nombre de la Empresa: COMERCIALIZADORA AGROPECUARIA ICK S.A. DE C.V. RFC.: CAI220330VD7 CFDI: Gastos en general Teléfono: 81 2860 1814 Contacto: Adrian Rivera Email: adrian.rmoxica75@gmail.com | D28: COMODATO Adrian Rivera - 81 2860 1814 Email:adrian.rmoxica75@gmail.com | E28: 4 | F28: JOSE LUIS | G28: =[1]DICIEMBRE!$BA$20 -> 0 | S28: =(300*0.16+300)*E28 -> 1392 | AB28: 1392 | BA28: =SUM(G28+S28+T28-U28-V28-W28-X28-Y28-Z28-AA28-AB28-AC28-AD28-AE28-AF28-AG28-AH28-AI28-AJ28-AK28-AL28-AM28-AN28-AO28-AP28-AQ28-AR28-AS28-AT28-AU28-AV28-AW28-AX28-AY28-AZ28) -> 0
A29: 12 | B29: COMERCIALIZADORA FUERZA CEMENTERA | D29: Candy - 81 2634 9644 candymoreno@forzadelnorte.com | E29: 5 | F29: JOSE LUIS | G29: =[1]DICIEMBRE!$BA$31 -> -3480 | S29: =(300*0.16+300)*E29 -> 1740 | BA29: =SUM(G29+S29+T29-U29-V29-W29-X29-Y29-Z29-AA29-AB29-AC29-AD29-AE29-AF29-AG29-AH29-AI29-AJ29-AK29-AL29-AM29-AN29-AO29-AP29-AQ29-AR29-AS29-AT29-AU29-AV29-AW29-AX29-AY29-AZ29) -> -1740 | BB29: PAGO 3 MESES COBRAR HASTA MARZO 2025
A30: 13 | B30: COMERCIALIZADORA Y LOGISTICA SIFAL - ARTURO SIFUENTES | D30: Arturo Sifuentes - 811 521 3582 Silvia Neri Salazar - 811 044 7961 Email: silvia-neri@hotmail.com; ventas@acertrans.com.mx; logisticasifal@hotmail.com; | E30: 5 | F30: JOSE LUIS | G30: =[1]DICIEMBRE!$BA$18 -> -128 | S30: =(350*0.16+350)*E30 -> 2030 | AS30: 2030 | BA30: =SUM(G30+S30+T30-U30-V30-W30-X30-Y30-Z30-AA30-AB30-AC30-AD30-AE30-AF30-AG30-AH30-AI30-AJ30-AK30-AL30-AM30-AN30-AO30-AP30-AQ30-AR30-AS30-AT30-AU30-AV30-AW30-AX30-AY30-AZ30) -> -128
A31: 14 | B31: COMPAÑÍA MADERERA CUAUHTEMOC | D31: COMODATO Daniel Cardenas - 81 2634 0402 Email:recepcionfacturas@ciamaderera.com | E31: 5 | F31: JOSE LUIS | G31: =[1]DICIEMBRE!$BA$77 -> 0.0012 | S31: =(250*0.16+250)*4+(300*0.16+300)*1 -> 1508 | AA31: 1508 | BA31: =SUM(G31+S31+T31-U31-V31-W31-X31-Y31-Z31-AA31-AB31-AC31-AD31-AE31-AF31-AG31-AH31-AI31-AJ31-AK31-AL31-AM31-AN31-AO31-AP31-AQ31-AR31-AS31-AT31-AU31-AV31-AW31-AX31-AY31-AZ31) -> 0.0012
A32: 15 | B32: CONTINENTAL PARABELLUM - GRUPO SAR | D32: Alan Rodriguez finanzas.gposar@gmail.com | E32: 6 | F32: MARIO ULISES | G32: =[1]DICIEMBRE!$BA$32 -> 0 | S32: =(279*0.16+279)*E32 -> 1941.84 | T32: =1658.1*0.16+1658.1 -> 1923.396 | AB32: 3865.24 | BA32: =SUM(G32+S32+T32-U32-V32-W32-X32-Y32-Z32-AA32-AB32-AC32-AD32-AE32-AF32-AG32-AH32-AI32-AJ32-AK32-AL32-AM32-AN32-AO32-AP32-AQ32-AR32-AS32-AT32-AU32-AV32-AW32-AX32-AY32-AZ32) -> -0.004 | BB32: COB. ENE'25: 1 EQP. E INST. NUEVA Y 1 MENS. PROP. 17 DIAS
A33: 16 | B33: DAXS INDUSTRIAL - JOSE HUMBERTO VILLA | D33: Humberto Villa - 81 1487 4381 Email:daxsind@hotmail.com | E33: 2 | G33: =[1]DICIEMBRE!$BA$61 -> 2598.4 | BA33: =SUM(G33+S33+T33-U33-V33-W33-X33-Y33-Z33-AA33-AB33-AC33-AD33-AE33-AF33-AG33-AH33-AI33-AJ33-AK33-AL33-AM33-AN33-AO33-AP33-AQ33-AR33-AS33-AT33-AU33-AV33-AW33-AX33-AY33-AZ33) -> 2598.4 | BB33: BAJA
A34: 17 | B34: DISTRIBUIDORA FERRELECTRICA Y MATERIALES EXPRESS - DEX MATERIALES | D34: Aleyda - 81 3402 1812 Rolando Ziragem 811 077 1470 812 597 2700 / 812 332 3606 oficina@dexmateriales.com; rzgc@hotmail.com; rolando@dexmateriales.com; | E34: 9 | F34: JOSE LUIS | G34: =[1]DICIEMBRE!$BA$34 -> 0 | S34: 0 | BA34: =SUM(G34+S34+T34-U34-V34-W34-X34-Y34-Z34-AA34-AB34-AC34-AD34-AE34-AF34-AG34-AH34-AI34-AJ34-AK34-AL34-AM34-AN34-AO34-AP34-AQ34-AR34-AS34-AT34-AU34-AV34-AW34-AX34-AY34-AZ34) -> 0 | BB34: PAGARA 6 MENS. COBRAR HASTA EL MES DE MARZO 2025 CAMBIA A ESQUEMA DE MENSUALIDAD 06-SEPTIEMBRE-2024 Y DA DE BAJA 3 UNIDADES Y SE SEPARA CUENTA A COMERCIALIZADORA FUERZA CEMENTERA
A35: 18 | B35: EDGAR ALBERTO CORTEZ TREVIÑO | D35: Edgar Cortez - 81 8185 6454 | E35: 1 | F35: JOSE LUIS | G35: =[1]DICIEMBRE!$BA$35 -> 0 | S35: =(250*0.16+250)*E35 -> 290 | AE35: 290 | BA35: =SUM(G35+S35+T35-U35-V35-W35-X35-Y35-Z35-AA35-AB35-AC35-AD35-AE35-AF35-AG35-AH35-AI35-AJ35-AK35-AL35-AM35-AN35-AO35-AP35-AQ35-AR35-AS35-AT35-AU35-AV35-AW35-AX35-AY35-AZ35) -> 0
A36: 19 | B36: ELIZABETH RENTERIA REVILLA | C36: Nombre de la Empresa: ELIZABETH RENTERÍA REVILLA RFC. RERE760807SX9 CFDI: Gastos en general Forma de Pago: TransferenciaTeléfono: 811 810 0155 Contacto: Elizabeth Rentería Email: e.lic@live.com.mx | D36: Elizabeth Renteria - 811 810 0155 Email:e.lic@live.com.mx | E36: 2 | F36: JOSE LUIS | G36: =[1]DICIEMBRE!$BA$37 -> 0 | S36: =(250*0.16+250)*E36 -> 580 | T36: =1850*0.16+1850 -> 2146 | AE36: =290+2436 -> 2726 | BA36: =SUM(G36+S36+T36-U36-V36-W36-X36-Y36-Z36-AA36-AB36-AC36-AD36-AE36-AF36-AG36-AH36-AI36-AJ36-AK36-AL36-AM36-AN36-AO36-AP36-AQ36-AR36-AS36-AT36-AU36-AV36-AW36-AX36-AY36-AZ36) -> 0 | BB36: COB. ENE'25: 1 EQP. E INST. NUEVA COBRAR EN FEB 1 MENS. PROP. 20 DIAS
A37: 20 | B37: ENDER INDUSTRIAL (EMMANUEL VAZQUEZ - SINERGIX ) | C37: Nombre de la Empresa: ENDER INDUSTRIAL S.A. DE C.V. RFC.: SIS1703089V6 CFDI: Gastos en General. Forma de Pago: Transferencia Teléfono: 813 055 7409 / 81) 2141 0506 Contacto: Emmanuel Vázquez / Sonia Lugo Email: emmanuel@sinergix.net; sonia@sinergix.net; | D37: COMODATO Emmanuel Vazquez - 81 3055 7409 Sonia Lugo (pagos) - 81 2141 0506 Email:sandra@enderindustrial.com claudia@enderindustrial.com belen@enderindustrial.com facturas@enderindustrial.com; emmanuel@sinergix.net; | E37: 7 | F37: JOSE LUIS | G37: =[1]DICIEMBRE!$BA$38 -> -753.9924 | S37: =(350*0.16+350)*E37 -> 2842 | AE37: 2842 | BA37: =SUM(G37+S37+T37-U37-V37-W37-X37-Y37-Z37-AA37-AB37-AC37-AD37-AE37-AF37-AG37-AH37-AI37-AJ37-AK37-AL37-AM37-AN37-AO37-AP37-AQ37-AR37-AS37-AT37-AU37-AV37-AW37-AX37-AY37-AZ37) -> -753.9924
A38: 21 | B38: ENDO LASER MICROQUIRURGICO - INSTITUTO VIDAURRI DE OJOS (DANIELA MEDELLIN) | D38: Daniela Medellín - 81 1588 8485 Email:monitoreo@endolaser.com.mx | E38: 4 | F38: JOSE LUIS | G38: =[1]DICIEMBRE!$BA$59 -> 6.8212103e-13 | S38: =(249*0.16+249)*E38 -> 1155.36 | AE38: 1155.36 | BA38: =SUM(G38+S38+T38-U38-V38-W38-X38-Y38-Z38-AA38-AB38-AC38-AD38-AE38-AF38-AG38-AH38-AI38-AJ38-AK38-AL38-AM38-AN38-AO38-AP38-AQ38-AR38-AS38-AT38-AU38-AV38-AW38-AX38-AY38-AZ38) -> 9.094947e-13
A39: 22 | B39: EXTINTORES Y EQUIPOS MONTERREY (SERGIO GONZALEZ) | D39: COMODATO Sergio Gonzalez - 81 8654 2753 sergio.jr987@outlook.com | E39: 2 | F39: JOSE LUIS | G39: =[1]DICIEMBRE!$BA$41 -> 0 | S39: =(300*0.16+300)*2 -> 696 | AH39: 696 | BA39: =SUM(G39+S39+T39-U39-V39-W39-X39-Y39-Z39-AA39-AB39-AC39-AD39-AE39-AF39-AG39-AH39-AI39-AJ39-AK39-AL39-AM39-AN39-AO39-AP39-AQ39-AR39-AS39-AT39-AU39-AV39-AW39-AX39-AY39-AZ39) -> 0 | BB39: PDTE 1 INSTALACION YA PAGADA SOLO COBRAR PROP. CUANDO SE INSTALE
A40: 23 | B40: FERNANDO RAFAEL GONZALEZ MONTEMAYOR (SERVICIO DE PLATAFORMA) | C40: Nombre de la Empresa: GOMO SERVICES Contacto: FERNANDO DISATEL Email: frgm_76@hotmail.com Remisiones con IVA | D40: Fernando Disatel - 81 1799 2490 Email:frgm_76@hotmail.com | E40: 674 | F40: JOSE LUIS | G40: =[1]DICIEMBRE!$BA$42 -> 3220.026 | S40: =(38.8*0.16+38.8)*E40 -> 30335.392 | T40: =38.8*0.16+38.8 -> 45.008 | AO40: 30380.4 | BA40: =SUM(G40+S40+T40-U40-V40-W40-X40-Y40-Z40-AA40-AB40-AC40-AD40-AE40-AF40-AG40-AH40-AI40-AJ40-AK40-AL40-AM40-AN40-AO40-AP40-AQ40-AR40-AS40-AT40-AU40-AV40-AW40-AX40-AY40-AZ40) -> 3220.026 | BB40: COB. ENE'25: INGRESO DE 1 UNIDAD
A41: 24 | B41: FERNANDO REYES HERNANDES | D41: COMODATO Fernando Reyes - 81 1821 3781 Viridiana Flores - 81 1796 4130 arnol84reyeshdz@gmail.com | E41: 1 | F41: JOSE LUIS | G41: =[1]DICIEMBRE!$BA$43 -> 348 | S41: =(300*0.16+300)*E41 -> 348 | AB41: 696 | BA41: =SUM(G41+S41+T41-U41-V41-W41-X41-Y41-Z41-AA41-AB41-AC41-AD41-AE41-AF41-AG41-AH41-AI41-AJ41-AK41-AL41-AM41-AN41-AO41-AP41-AQ41-AR41-AS41-AT41-AU41-AV41-AW41-AX41-AY41-AZ41) -> 0
A42: 25 | B42: FINPAIS | C42: Nombre de la Empresa: FINPAIS S.A. DE C.V. RFC. FCO130429629 CFDI: Gastos en general Forma de Pago: TransferenciaTeléfono: 81 8208 7559 Contacto: Katty Email: administracion@finpais.com.mx | D42: COMODATO Katty - 81 8208 7559 Email:administracion@finpais.com.mx | E42: 7 | F42: JOSE LUIS | G42: =[1]DICIEMBRE!$BA$44 -> 2598.3956 | S42: =(320*0.16+320)*E42 -> 2598.4 | T42: =250*0.16+250 -> 290 | BA42: =SUM(G42+S42+T42-U42-V42-W42-X42-Y42-Z42-AA42-AB42-AC42-AD42-AE42-AF42-AG42-AH42-AI42-AJ42-AK42-AL42-AM42-AN42-AO42-AP42-AQ42-AR42-AS42-AT42-AU42-AV42-AW42-AX42-AY42-AZ42) -> 5486.7956 | BB42: COB. ENE'25: 1 VISITA EN FALSO Y 1 FACTURA PDTE.
A43: 26 | B43: FINXERT - FERNANDO VILLARREAL | D43: Fernando Villarreal - 81 2348 6430 | E43: 2 | G43: =[1]DICIEMBRE!$BA$45 -> 0 | S43: =(154.66*0.16+154.66)*E43 -> 358.8112 | T43: =2490*0.16+2490 -> 2888.4 | AB43: 358.81 | AL43: 2888.4 | BA43: =SUM(G43+S43+T43-U43-V43-W43-X43-Y43-Z43-AA43-AB43-AC43-AD43-AE43-AF43-AG43-AH43-AI43-AJ43-AK43-AL43-AM43-AN43-AO43-AP43-AQ43-AR43-AS43-AT43-AU43-AV43-AW43-AX43-AY43-AZ43) -> 0.0012 | BB43: COB. ENE'25: 1 EQP. E INST. NUEVAS 17-ENERO-25 COBRAR EN FEB MENS. PROP. 13 DIAS 2 MENS. PROP. 16 DIAS, COBRAR EN FEB. MENS. COMPL.
A44: 27 | B44: FLETES ESPECIALIZADOS AGL | D44: COMODATO Sr. Ariel - 81 1974 2676 fletesagl@gmail.com | E44: 14 | F44: JOSE LUIS | G44: =[1]DICIEMBRE!$BA$46 -> 9.094947e-13 | S44: =(300*0.16+300)*E44 -> 4872 | AE44: 4872 | BA44: =SUM(G44+S44+T44-U44-V44-W44-X44-Y44-Z44-AA44-AB44-AC44-AD44-AE44-AF44-AG44-AH44-AI44-AJ44-AK44-AL44-AM44-AN44-AO44-AP44-AQ44-AR44-AS44-AT44-AU44-AV44-AW44-AX44-AY44-AZ44) -> 9.094947e-13
A45: 28 | B45: FREIGHT HP-PACK MEXICO (DAVID FRANCISCO ARCOS) | D45: COMODATO Carlos Salinas - (201) 748 9020 David Francisco - 81 1033 1916 davidarcosfrancisco1991@gmail.com | E45: 20 | F45: JOSE LUIS | S45: =(279*0.16+279)*E45 -> 6472.8 | T45: =(549*0.16+549)*20 -> 12736.8 | AO45: 9604.8 | BA45: =SUM(G45+S45+T45-U45-V45-W45-X45-Y45-Z45-AA45-AB45-AC45-AD45-AE45-AF45-AG45-AH45-AI45-AJ45-AK45-AL45-AM45-AN45-AO45-AP45-AQ45-AR45-AS45-AT45-AU45-AV45-AW45-AX45-AY45-AZ45) -> 9604.8 | BB45: CLIENTE NUEVO 14-ENERO-2025 SALTILLO
A46: 29 | B46: GEORGINA MELISSA GOMEZ RODELA - PETROVACTOR | C46: Nombre de la Empresa: GEORGINA MELISSA GOMEZ RODELA RFC.: GORG8204295H5 CFDI: Gastos en General Forma de Pago: Transferencia Teléfono: 833 104 3672 Gisela Suarez - 81 1049 7882 Contacto: Griselda Suarez (Petrovactor) Email: griselda@petrovactor.com; facturagmgr@gmail.com; | D46: Georgina Gomez - 833 134 5812 Anahí Juarez - 833 104 3672 Email:facturagmgr@gmail.com; anaiwork7@gmail.com | E46: 14 | F46: JOSE LUIS | G46: =[1]DICIEMBRE!$BA$50 -> -0.0004 | S46: =(250*0.16+250)*E46 -> 4060 | AB46: 4060 | BA46: =SUM(G46+S46+T46-U46-V46-W46-X46-Y46-Z46-AA46-AB46-AC46-AD46-AE46-AF46-AG46-AH46-AI46-AJ46-AK46-AL46-AM46-AN46-AO46-AP46-AQ46-AR46-AS46-AT46-AU46-AV46-AW46-AX46-AY46-AZ46) -> -0.0004
A47: 30 | B47: GRUPO CASTOR ACERTIVA CONSTRUCCIONES, S.A. DE C.V. (CASTOR) | C47: Nombre de la Empresa: ACERTIVA CONTRUCCIONES S.A. DE C.V. RFC. ACO9605025G2 CFDI: Comunicaciones Satelitales Forma de Pago: Transferencia Teléfono: 818 347 7712 / 13 ext. 106 Contacto: Sr. Santos / Srta.(s) Janeth Villa / Karla Guerra / Fabiola García Email: fabiola.garcia@lsadministracion.com | D47: Srta. Janeth Villa 81 8347 7712 / 13 Ext. 106 Email:fabiola.garcia@lsadministracion.com; | E47: 1 | F47: JOSE LUIS | G47: =[1]DICIEMBRE!$BA$52 -> 0 | S47: 348 | AP47: 348 | BA47: =SUM(G47+S47+T47-U47-V47-W47-X47-Y47-Z47-AA47-AB47-AC47-AD47-AE47-AF47-AG47-AH47-AI47-AJ47-AK47-AL47-AM47-AN47-AO47-AP47-AQ47-AR47-AS47-AT47-AU47-AV47-AW47-AX47-AY47-AZ47) -> 0
A48: 31 | B48: GRUPO CASTOR ORGANIZACIÓN CASTOR AG, S.A. DE C.V. | C48: Nombre de la Empresa: ORGANIZACIÓN CASTOR S. A. DE C. V. RFC. OCA121001RX9 CFDI: Comunicaciones Satelitales Forma de Pago: Transferencia Teléfono: 818 347 7712 / 13 ext. 106 Contacto: Sr. Santos / Srta.(s) Janeth Villa / Karla Guerra / Fabiola García Email: fabiola.garcia@lsadministracion.com | D48: Srta. Janeth Villa 81 8347 7712 / 13 Ext. 106 Email:fabiola.garcia@lsadministracion.com; | E48: 2 | F48: JOSE LUIS | G48: =[1]DICIEMBRE!$BA$53 -> 0 | S48: 696 | AL48: 696 | BA48: =SUM(G48+S48+T48-U48-V48-W48-X48-Y48-Z48-AA48-AB48-AC48-AD48-AE48-AF48-AG48-AH48-AI48-AJ48-AK48-AL48-AM48-AN48-AO48-AP48-AQ48-AR48-AS48-AT48-AU48-AV48-AW48-AX48-AY48-AZ48) -> 0
A49: 32 | B49: GREGORY AJMEL MARTINEZ GARCIA (TEOURO TRANSPORTES) | D49: COMODATO Gregory Martínez García 81 1041 6798 greck_090@hotmail.com | E49: 3 | F49: JOSE LUIS | G49: =[1]DICIEMBRE!$BA$54 -> 0 | S49: =(300*0.16+300)*E49 -> 1044 | AB49: 1044 | BA49: =SUM(G49+S49+T49-U49-V49-W49-X49-Y49-Z49-AA49-AB49-AC49-AD49-AE49-AF49-AG49-AH49-AI49-AJ49-AK49-AL49-AM49-AN49-AO49-AP49-AQ49-AR49-AS49-AT49-AU49-AV49-AW49-AX49-AY49-AZ49) -> 0
A50: 33 | B50: GRUPO AMBIENTAL Y RESIDUOS INDUSTRIALES S.A. DE C. V. (GARISA) | C50: Nombre de la Empresa: GRUPO AMBIENTAL Y RESIDUOS INDUSTRIALES S.A. DE C.V. RFC.: GAR1503063C1 CFDI: Gastos en General. Forma de Pago: Transferencia Electrónica Contacto: Verónica Coronado Teléfono: 812 165 1133 / 8119575404 Email: garisav@hotmail.com | D50: Veronica Coronado- 812 165 1133 / 811 957 5404 Email:garisav@hotmail.com | E50: 3 | F50: JOSE LUIS | G50: =[1]DICIEMBRE!$BA$49 -> 0 | S50: =(300*0.16+300)*E50 -> 1044 | AL50: 1044 | BA50: =SUM(G50+S50+T50-U50-V50-W50-X50-Y50-Z50-AA50-AB50-AC50-AD50-AE50-AF50-AG50-AH50-AI50-AJ50-AK50-AL50-AM50-AN50-AO50-AP50-AQ50-AR50-AS50-AT50-AU50-AV50-AW50-AX50-AY50-AZ50) -> 0
A51: 34 | B51: GRUPO DIESEL HH | D51: Marisol Alvarado - 33 3486 8750 / Norma Navarro Oficina - 33 1401 2246 33 1654 3312 Email:azulitalia@live.com.mx | E51: 4 | F51: JOSE LUIS | G51: =[1]DICIEMBRE!$BA$56 -> 0 | S51: =(300*0.16+300)*E51 -> 1392 | AB51: 1392 | BA51: =SUM(G51+S51+T51-U51-V51-W51-X51-Y51-Z51-AA51-AB51-AC51-AD51-AE51-AF51-AG51-AH51-AI51-AJ51-AK51-AL51-AM51-AN51-AO51-AP51-AQ51-AR51-AS51-AT51-AU51-AV51-AW51-AX51-AY51-AZ51) -> 0
A52: 35 | B52: HACIENDO EQUIPO EN TU PROYECTO - EQUIPREST | C52: Nombre de la Empresa: HACIENDO EQUIPO EN TU PROYECTO S.A. DE C.V. RFC. EMO180713MC1 CFDI : Gastos en General C.P.: 64000 Regimen Fiscal: R SIMPLIFICADO DE CONFIANZA Forma de Pago: Transferencia Teléfono: 81 2002 4556 Contacto: Oscar Herrera Email:compras@equiprestmx.com 1er Factura: 1951 | D52: Karla - 81 2002 4556 Email:administracion@equiprestmx.com | E52: 3 | F52: JOSE LUIS | G52: =[1]DICIEMBRE!$BA$39 -> 9.094947e-13 | S52: =(250*0.16+250)*E52 -> 870 | AC52: 870 | BA52: =SUM(G52+S52+T52-U52-V52-W52-X52-Y52-Z52-AA52-AB52-AC52-AD52-AE52-AF52-AG52-AH52-AI52-AJ52-AK52-AL52-AM52-AN52-AO52-AP52-AQ52-AR52-AS52-AT52-AU52-AV52-AW52-AX52-AY52-AZ52) -> 9.094947e-13
A53: 36 | B53: HECTOR ALVEAR AGUILAR - KARLA ALVEAR | C53: Nombre de la Empresa: HECTOR ALVEAR AGUILAR RFC. AEAH940117AV1 CFDI : Gastos en General C.P.:67250 Regimen Fiscal: R DE LAS PERSONAS FISICAS CON ACTIVIDADES EMPRESARIALES Y PROFESIONALES Forma de Pago: Transferencia Teléfono: 81 8050 5722 Contacto: Karla Vear Email: Hec_alvear@hotmail.com 1er Factura: 2068 | D53: Karla Alvear - 81 1800 0233 Email:Hec_alvear@hotmail.com | E53: 1 | F53: JOSE LUIS | G53: =[1]DICIEMBRE!$BA$67 -> 0 | S53: =(300*0.16+300)*E53 -> 348 | AO53: 348 | BA53: =SUM(G53+S53+T53-U53-V53-W53-X53-Y53-Z53-AA53-AB53-AC53-AD53-AE53-AF53-AG53-AH53-AI53-AJ53-AK53-AL53-AM53-AN53-AO53-AP53-AQ53-AR53-AS53-AT53-AU53-AV53-AW53-AX53-AY53-AZ53) -> 0
A54: 37 | B54: INDUSTRIAL DE CARBON Y GRAFITO - CARBOGRAF | C54: Nombre de la Empresa: INDUSTRIAL DE CARBON Y GRAFITO, S.A. DE C.V. RFC: ICG 100106 UR0 CFDI: Gastos en general TEL: 16 42 2004 Contacto: Pablo Rodriguez Email: Elda@carbograf.com | D54: Daniela Cabello - 81 8273 6437 Email:julio.campos@carbograf.com marlene@carbograf.com | E54: 4 | F54: JOSE LUIS | G54: =[1]DICIEMBRE!$BA$26 -> 0.0032 | S54: =(349*0.16+349)*E54 -> 1619.36 | AR54: 1619.36 | BA54: =SUM(G54+S54+T54-U54-V54-W54-X54-Y54-Z54-AA54-AB54-AC54-AD54-AE54-AF54-AG54-AH54-AI54-AJ54-AK54-AL54-AM54-AN54-AO54-AP54-AQ54-AR54-AS54-AT54-AU54-AV54-AW54-AX54-AY54-AZ54) -> 0.0032
A55: 38 | B55: INDUSTRIAS PERSISTA LABORO S.A. DE C.V. (ERNESTO GOMEZ) | D55: COMODATO Ernesto Gómez - 81 2001 9256 ernesto.gomez@sanbox.com.mx | E55: 12 | F55: JOSE LUIS | G55: =[1]DICIEMBRE!$BA$58 -> 1525.0064 | S55: =(250*0.16+250)*E55 -> 3480 | AC55: 3480 | AH55: 1525.01 | BA55: =SUM(G55+S55+T55-U55-V55-W55-X55-Y55-Z55-AA55-AB55-AC55-AD55-AE55-AF55-AG55-AH55-AI55-AJ55-AK55-AL55-AM55-AN55-AO55-AP55-AQ55-AR55-AS55-AT55-AU55-AV55-AW55-AX55-AY55-AZ55) -> -0.0036
A56: 39 | B56: INVERSIONES QUINEXUS - PRESTACOCHE (FINANCIERA) | C56: Nombre de la Empresa: PRESTACOCHE Contacto: Rosy / Talía Carrizales Email: rosa.sr@quinexus.mx; talia.ci@quinexus.mx; Teléfono: 811 499 1431 / 812 147 3082 | D56: Rosy - 812 354 1373 Email:rosa.sr@quinexus.mx; | E56: 7 | F56: JOSE LUIS | G56: =[1]DICIEMBRE!$BA$85 -> 0.0048 | S56: =(220*0.16+220)*E56 -> 1786.4 | T56: =3900*0.16+3900 -> 4524 | AE56: 6310.4 | BA56: =SUM(G56+S56+T56-U56-V56-W56-X56-Y56-Z56-AA56-AB56-AC56-AD56-AE56-AF56-AG56-AH56-AI56-AJ56-AK56-AL56-AM56-AN56-AO56-AP56-AQ56-AR56-AS56-AT56-AU56-AV56-AW56-AX56-AY56-AZ56) -> 0.0048 | BB56: COB. ENE'25: 2 RE-INST. Y 4 DES-INST.
A57: 40 | B57: JAVIER ANGEL VELAZQUEZ SANCHEZ | C57: Nombre de la Empresa: JAVIER ANGEL VELAZQUEZ SANCHEZ RFC. VESJ4910026E3 CFDI: Comunicaciones satelitales Forma de Pago: Transferencia Teléfono: 812 032 0493 Contacto: Javier Ángel Velázquez Sánchez (FLETES ANGEL VELAZQUEZ) Email: fletesangelvelazquez@gmail.com | D57: Javier Velazquez - 812 032 0493 Email:fletesangelvelazquez@gmail.com | E57: 4 | F57: JOSE LUIS | G57: =[1]DICIEMBRE!$BA$60 -> -0.0048 | S57: =(330*0.16+330)*E57 -> 1531.2 | AA57: 1531.2 | BA57: =SUM(G57+S57+T57-U57-V57-W57-X57-Y57-Z57-AA57-AB57-AC57-AD57-AE57-AF57-AG57-AH57-AI57-AJ57-AK57-AL57-AM57-AN57-AO57-AP57-AQ57-AR57-AS57-AT57-AU57-AV57-AW57-AX57-AY57-AZ57) -> -0.0048
A58: 41 | B58: JESUS ALEJANDRO LOZANO LOZANO - TRANSPORTES TM | D58: ventas@autotransportes-jl.com administracion@autotransportes-jl.com | E58: 1 | F58: JOSE LUIS | G58: =[1]DICIEMBRE!$BA$100 -> 0 | S58: =300*0.16+300 -> 348 | AC58: 348 | BA58: =SUM(G58+S58+T58-U58-V58-W58-X58-Y58-Z58-AA58-AB58-AC58-AD58-AE58-AF58-AG58-AH58-AI58-AJ58-AK58-AL58-AM58-AN58-AO58-AP58-AQ58-AR58-AS58-AT58-AU58-AV58-AW58-AX58-AY58-AZ58) -> 0
A59: 42 | B59: JOSE ANGEL MENDEZ ARRIAGA - TRANSPORTES 2M | C59: Nombre de la Empresa: TRANSPORTES 2M Contacto: José Ángel Méndez Arriaga Teléfono: 812 600 8976 Email: jama_ca@hotmail.com | D59: Jose Angel Mendez Arriaga - 812 600 8976 Email:jama_ca@hotmail.com | E59: 4 | F59: JOSE LUIS | G59: =[1]DICIEMBRE!$BA$98 -> -6 | S59: =(300*0.16+300)*E59 -> 1392 | AB59: 1392 | BA59: =SUM(G59+S59+T59-U59-V59-W59-X59-Y59-Z59-AA59-AB59-AC59-AD59-AE59-AF59-AG59-AH59-AI59-AJ59-AK59-AL59-AM59-AN59-AO59-AP59-AQ59-AR59-AS59-AT59-AU59-AV59-AW59-AX59-AY59-AZ59) -> -6
A60: 43 | B60: JOSE MELQUIADES TOLEDO GARCIA DE LEON | D60: Jose Toledo - 81 1015 9453 Email:j.garcia@grupotranstech.com | E60: 2 | F60: JOSE LUIS | G60: =[1]DICIEMBRE!$BA$63 -> 2.2737368e-13 | S60: =(330*0.16+330)*E60 -> 765.6 | AC60: 765.6 | BA60: =SUM(G60+S60+T60-U60-V60-W60-X60-Y60-Z60-AA60-AB60-AC60-AD60-AE60-AF60-AG60-AH60-AI60-AJ60-AK60-AL60-AM60-AN60-AO60-AP60-AQ60-AR60-AS60-AT60-AU60-AV60-AW60-AX60-AY60-AZ60) -> 2.2737368e-13
A61: 44 | B61: JUAN ANTONIO DE JESUS GARCIA RAMIREZ - TRANSPORTES GARCÍA | C61: Nombre de la Empresa: JUAN ANTONIO DE JESUS GARCIA RAMIREZ RFC. GARJ810921FM4 CFDI : Por Definir Forma de Pago: Transferencia Teléfono: 811 155 2769 Contacto: Antonio García Email: antoniotransgar@hotmail.es | D61: COMODATO Antonio García - 81 1155 2769 Email:antoniotransgar@hotmail.es | E61: 14 | F61: JOSE LUIS | G61: =[1]DICIEMBRE!$BA$99 -> 0.004 | S61: =(289*0.16+289)*E61 -> 4693.36 | BA61: =SUM(G61+S61+T61-U61-V61-W61-X61-Y61-Z61-AA61-AB61-AC61-AD61-AE61-AF61-AG61-AH61-AI61-AJ61-AK61-AL61-AM61-AN61-AO61-AP61-AQ61-AR61-AS61-AT61-AU61-AV61-AW61-AX61-AY61-AZ61) -> 4693.364
A62: 45 | B62: JUAN HUMBERTO TAMEZ MARTINEZ - JOSE TAMEZ | D62: COMODATO Humberto Tamez - 82 6105 8660 Jose Tamez - 81 1066 5375 | E62: 1 | F62: JOSE LUIS | G62: =[1]DICIEMBRE!$BA$62 -> 0 | BA62: =SUM(G62+S62+T62-U62-V62-W62-X62-Y62-Z62-AA62-AB62-AC62-AD62-AE62-AF62-AG62-AH62-AI62-AJ62-AK62-AL62-AM62-AN62-AO62-AP62-AQ62-AR62-AS62-AT62-AU62-AV62-AW62-AX62-AY62-AZ62) -> 0 | BB62: BAJA 23-ENERO-2025
A63: 46 | B63: JUAN JAVIER CABRIALES CEDILLO (TRANSPORTES RCD) | D63: Juan Cabriales - 81 2947 2650 Email:transportes.rcd.diaz@gmail.com | E63: 4 | F63: JOSE LUIS | G63: =[1]DICIEMBRE!$BA$65 -> -0.0004 | S63: =(300*0.16+300)*E63 -> 1392 | T63: =2020*0.16+2020 -> 2343.2 | AB63: 3735.2 | BA63: =SUM(G63+S63+T63-U63-V63-W63-X63-Y63-Z63-AA63-AB63-AC63-AD63-AE63-AF63-AG63-AH63-AI63-AJ63-AK63-AL63-AM63-AN63-AO63-AP63-AQ63-AR63-AS63-AT63-AU63-AV63-AW63-AX63-AY63-AZ63) -> -0.0004 | BB63: COB. ENE'25: 1 EQP. E INST. NUEVA Y 1 MENS. PROP. 17 DIAS
A64: 47 | B64: JUAN MEJIA HERNANDEZ | D64: Juan Mejia - 44 2160 1772 mejiahj@hotmail.com | E64: 1 | F64: JOSE LUIS | G64: =[1]DICIEMBRE!$BA$66 -> 0 | S64: =(200*0.16+200)*E64 -> 232 | AI64: 232 | BA64: =SUM(G64+S64+T64-U64-V64-W64-X64-Y64-Z64-AA64-AB64-AC64-AD64-AE64-AF64-AG64-AH64-AI64-AJ64-AK64-AL64-AM64-AN64-AO64-AP64-AQ64-AR64-AS64-AT64-AU64-AV64-AW64-AX64-AY64-AZ64) -> 0
A65: 48 | B65: K3 SOLUCIONES A LA INDUSTRIA ALIMENTICIA | D65: Susana Calvo - 81 1695 4703 proyectos3@serviciosk3.mx | E65: 1 | F65: JOSE LUIS | G65: =[1]DICIEMBRE!$BA$68 -> 0 | S65: =(300*0.16+300)*E65 -> 348 | AC65: 348 | BA65: =SUM(G65+S65+T65-U65-V65-W65-X65-Y65-Z65-AA65-AB65-AC65-AD65-AE65-AF65-AG65-AH65-AI65-AJ65-AK65-AL65-AM65-AN65-AO65-AP65-AQ65-AR65-AS65-AT65-AU65-AV65-AW65-AX65-AY65-AZ65) -> 0
A66: 49 | B66: KARLA ZEBETH CLEMENTINA PEÑA MACIAS (EDUARDO ALMAGUER) | D66: Eduardo Almaguer - 81 2920 4044 abelardoalmaguer1991@gmail.com | E66: 1 | F66: JOSE LUIS | G66: =[1]DICIEMBRE!$BA$69 -> 0 | S66: =(250*0.16+250)*E66 -> 290 | AH66: 290 | BA66: =SUM(G66+S66+T66-U66-V66-W66-X66-Y66-Z66-AA66-AB66-AC66-AD66-AE66-AF66-AG66-AH66-AI66-AJ66-AK66-AL66-AM66-AN66-AO66-AP66-AQ66-AR66-AS66-AT66-AU66-AV66-AW66-AX66-AY66-AZ66) -> 0
A67: 50 | B67: KROHNE DE MEXICO | C67: Nombre de la Empresa: KROHNE DE MEXICO RFC. KME091130LY6 CFDI : Gastos en General C.P.89110 Regimen Fiscal: R GENERAL DE LEY PERSONAS MORALES Forma de Pago: Transferencia Teléfono: (833) 217-3830 Contacto: Email: Pamela@KROHNEMEXICO.com 'erika@krohnemexico.com'; 'israel@krohnemexico.com'; 'maricela@krohnemexico.com' 1er Factura: 2070 | D67: (833) 217-3830 Ext. 101 Email:Pamela@KROHNEMEXICO.com 'erika@krohnemexico.com'; 'israel@krohnemexico.com'; 'maricela@krohnemexico.com' | E67: 19 | F67: JOSE LUIS | G67: =[1]DICIEMBRE!$BA$70 -> 0.002 | S67: =(249*0.16+249)*E67 -> 5487.96 | T67: =3299*0.16+3299 -> 3826.84 | AL67: 9314.8 | BA67: =SUM(G67+S67+T67-U67-V67-W67-X67-Y67-Z67-AA67-AB67-AC67-AD67-AE67-AF67-AG67-AH67-AI67-AJ67-AK67-AL67-AM67-AN67-AO67-AP67-AQ67-AR67-AS67-AT67-AU67-AV67-AW67-AX67-AY67-AZ67) -> 0.002 | BB67: COB. ENE'25: 2 DES-INST.
A68: 51 | B68: LACAR ENERGY LOGISTIC - CARLOS MORENO | D68: Aylin Villanueva - 81 1240 3361 | E68: 2 | F68: JOSE LUIS | G68: =[1]DICIEMBRE!$BA$71 -> 0 | S68: =(210*0.16+210)*E68 -> 487.2 | AD68: 487.2 | BA68: =SUM(G68+S68+T68-U68-V68-W68-X68-Y68-Z68-AA68-AB68-AC68-AD68-AE68-AF68-AG68-AH68-AI68-AJ68-AK68-AL68-AM68-AN68-AO68-AP68-AQ68-AR68-AS68-AT68-AU68-AV68-AW68-AX68-AY68-AZ68) -> 0 | BB68: COB. ENE'25: 2 MENS. PROP. 21 DIAS COBRAR EN FEB. MENS. COMPL.
A69: 52 | B69: LAMBI | C69: Nombre de la Empresa: LAMBI S.A. DE C.V. RFC. LAM9109013H1 CFDI : Gastos en General C.P.66062 Regimen Fiscal: R GENERAL DE LEY PERSONAS MORALES Forma de Pago: Transferencia Teléfono: 81 1908 0591 Contacto: Ericka Ortega Email: eortega@lambi.com.mx 1er Factura: 2008 | D69: Ericka Ortega (Compras) - 81 1908 0591 Email:trafico@lambi.com.mx jrojas@lambi.com.mx dquijas@lambi.com.mx | E69: 2 | F69: JOSE LUIS | G69: =[1]DICIEMBRE!$BA$72 -> -0.008 | S69: =(249*0.16+249)*E69 -> 577.68 | AR69: 577.68 | BA69: =SUM(G69+S69+T69-U69-V69-W69-X69-Y69-Z69-AA69-AB69-AC69-AD69-AE69-AF69-AG69-AH69-AI69-AJ69-AK69-AL69-AM69-AN69-AO69-AP69-AQ69-AR69-AS69-AT69-AU69-AV69-AW69-AX69-AY69-AZ69) -> -0.008
A70: 53 | B70: LEMURA VIVIENDA | C70: Nombre de la Empresa: LEMURA VIVIENDA S.A. DE C.V. RFC. LVI170630MEA CFDI: Gastos en general Forma de Pago: Transferencia Teléfono: 81 1624 4288 Contacto: Ignacio Gaxiola Email: igaxiola@lemura.com.mx | D70: Ignacio Gaxiola - 81 1624 4288 Email:igaxiola@lemura.com.mx | E70: 1 | F70: JOSE LUIS | G70: =[1]DICIEMBRE!$BA$73 -> -866.52 | S70: =(249*0.16+249)*E70 -> 288.84 | BA70: =SUM(G70+S70+T70-U70-V70-W70-X70-Y70-Z70-AA70-AB70-AC70-AD70-AE70-AF70-AG70-AH70-AI70-AJ70-AK70-AL70-AM70-AN70-AO70-AP70-AQ70-AR70-AS70-AT70-AU70-AV70-AW70-AX70-AY70-AZ70) -> -577.68 | BB70: PAGO 6 MENSUALIDADES ADELANTADAS COBRAR HASTA ABRIL 2025
A71: 54 | B71: LUIS ALBERTO DAVILA SALAZAR | C71: Nombre de la Empresa: LUIS ALBERTO DÁVILA SALAZAR RFC. DASL701219TM3 CFDI: Gastos en general Forma de Pago: Transferencia Teléfono: 813 074 5638 Contacto: Luis Dávila Email: luisdavila1970@gmail.com; luis.davila@alsglobal.com | D71: Luis Davila - 813 074 5638 Email:luisdavila1970@gmail.com | E71: 1 | F71: JOSE LUIS | G71: =[1]DICIEMBRE!$BA$74 -> 0 | S71: 348 | AL71: 348 | BA71: =SUM(G71+S71+T71-U71-V71-W71-X71-Y71-Z71-AA71-AB71-AC71-AD71-AE71-AF71-AG71-AH71-AI71-AJ71-AK71-AL71-AM71-AN71-AO71-AP71-AQ71-AR71-AS71-AT71-AU71-AV71-AW71-AX71-AY71-AZ71) -> 0
A72: 55 | B72: LUIS JAVIER GONZALEZ PEREZ | C72: Nombre de la Empresa: LUIS JAVIER GONZALEZ PEREZ RFC. GOPL9105308A6 CFDI: Gastos en general Forma de Pago: Transferencia Teléfono: 811 907 9148 Contacto: Luis Javier Gonzalez Email: ljgonzalez3591@gmail.com | D72: Luis Javier Gonzalez Perez - 811 907 9148 Email:ljgonzalez3591@gmail.com | E72: 1 | F72: JOSE LUIS | G72: =[1]DICIEMBRE!$BA$76 -> 0 | S72: =(300*0.16+300)*E72 -> 348 | AI72: 348 | BA72: =SUM(G72+S72+T72-U72-V72-W72-X72-Y72-Z72-AA72-AB72-AC72-AD72-AE72-AF72-AG72-AH72-AI72-AJ72-AK72-AL72-AM72-AN72-AO72-AP72-AQ72-AR72-AS72-AT72-AU72-AV72-AW72-AX72-AY72-AZ72) -> 0
A73: 56 | B73: MARINE DEL VALLE MENDOZA PEREZ - EDUARDO VENTURA MENDOZA | D73: Marine Mexico - 81 1994 9256 Eduardo Ventura - 81 3090 4628 Email:mendozael2003@yahoo.com | E73: 11 | F73: JOSE LUIS | G73: =[1]DICIEMBRE!$BA$36 -> 0.0012 | S73: =(250*0.16+250)*E73 -> 3190 | T73: =7558.32*0.16+7558.32 -> 8767.6512 | AA73: 11957.66 | BA73: =SUM(G73+S73+T73-U73-V73-W73-X73-Y73-Z73-AA73-AB73-AC73-AD73-AE73-AF73-AG73-AH73-AI73-AJ73-AK73-AL73-AM73-AN73-AO73-AP73-AQ73-AR73-AS73-AT73-AU73-AV73-AW73-AX73-AY73-AZ73) -> -0.0076 | BB73: COB. ENE'25: 4 EQP. E INST. NUEVAS Y 4 MENS. PROP.
A74: 57 | B74: MARIO ALBERTO CABALLERO GARZA | D74: Mario Caballero - 81 1213 3136 | E74: 3 | F74: JOSE LUIS | G74: =[1]DICIEMBRE!$BA$78 -> 0.0012 | S74: =(250*0.16+250)*E74 -> 870 | AB74: 870 | BA74: =SUM(G74+S74+T74-U74-V74-W74-X74-Y74-Z74-AA74-AB74-AC74-AD74-AE74-AF74-AG74-AH74-AI74-AJ74-AK74-AL74-AM74-AN74-AO74-AP74-AQ74-AR74-AS74-AT74-AU74-AV74-AW74-AX74-AY74-AZ74) -> 0.0012
A75: 58 | B75: MARMOL Y GRANITO RIO - GERARDO NIETO | D75: Gerardo Nieto - 81 1184 1231 Email:fizz98@hotmail.com consueloer@marmolemperador.com | E75: 5 | F75: JOSE LUIS | G75: =[1]DICIEMBRE!$BA$51 -> 0 | S75: =(300*0.16+300)*E75 -> 1740 | AD75: 1740 | BA75: =SUM(G75+S75+T75-U75-V75-W75-X75-Y75-Z75-AA75-AB75-AC75-AD75-AE75-AF75-AG75-AH75-AI75-AJ75-AK75-AL75-AM75-AN75-AO75-AP75-AQ75-AR75-AS75-AT75-AU75-AV75-AW75-AX75-AY75-AZ75) -> 0
A76: 59 | B76: MARTINEZ & DE LA ROSA CONSTRUCCIONES - ANTONIO MARTINEZ | D76: COMODATO Brenda Araujo - 81 3421 7089 Ing. Antonio Martínez -81 1537 7636 Email:facturas@myrconsa.mx catalinac@myrconsa.mx antoniomtz@myrconsa.mx | E76: 14 | F76: JOSE LUIS | G76: =[1]DICIEMBRE!$BA$22 -> -1.8189894e-12 | S76: =(279*0.16+279)*E76 -> 4530.96 | T76: =602.3*0.16+602.3 -> 698.668 | AC76: 5229.63 | BA76: =SUM(G76+S76+T76-U76-V76-W76-X76-Y76-Z76-AA76-AB76-AC76-AD76-AE76-AF76-AG76-AH76-AI76-AJ76-AK76-AL76-AM76-AN76-AO76-AP76-AQ76-AR76-AS76-AT76-AU76-AV76-AW76-AX76-AY76-AZ76) -> -0.002 | BB76: COB. ENE'25: 1 INST. NUEVA Y 1 MENS. PROP. 11 DIAS
A77: 60 | B77: MCJ CHILLER - EVERARDO NUNCIO CUELLAR | D77: COMODATO Everardo Nuncio - 81 1823 3384 Pagos Brenda Ocañas - 81 7654 2904/81 18 72 2728 Email:oficina@mcjchillerservice.com | E77: 8 | F77: JOSE LUIS | G77: =[1]DICIEMBRE!$BA$40 -> 0.0004 | S77: =(269*0.16+269)*E77 -> 2496.32 | AI77: 2496.32 | BA77: =SUM(G77+S77+T77-U77-V77-W77-X77-Y77-Z77-AA77-AB77-AC77-AD77-AE77-AF77-AG77-AH77-AI77-AJ77-AK77-AL77-AM77-AN77-AO77-AP77-AQ77-AR77-AS77-AT77-AU77-AV77-AW77-AX77-AY77-AZ77) -> 0.0004
A78: 61 | B78: MIGUEL EDUARDO CASAS ARIZMENDI - MIGUEL ANGEL CASAS | C78: Nombre de la Empresa: MIGUEL EDUARDO CASAS ARIZMENDI RFC.: CAAM980824PA1 CFDI: Por Definir Forma de Pago: TransferenciaTeléfono: 811 418 8880 Contacto: Nidia Arizmendi Email: mactransportacion@gmail.com | D78: COMODATO Miguel Angel Casas - 811 566 5492 Email:mactransportacion@gmail.com | E78: 15 | F78: JOSE LUIS | S78: =(289*0.16+289)*E78 -> 5028.6 | AE78: 5028.6 | BA78: =SUM(G78+S78+T78-U78-V78-W78-X78-Y78-Z78-AA78-AB78-AC78-AD78-AE78-AF78-AG78-AH78-AI78-AJ78-AK78-AL78-AM78-AN78-AO78-AP78-AQ78-AR78-AS78-AT78-AU78-AV78-AW78-AX78-AY78-AZ78) -> 0
A79: 62 | B79: MYA TRANSPORTES, S.A. DE C.V. (MOLIENDAS Y ALIMENTOS) | C79: Nombre de la Empresa: MYA TRANSPORTES S.A. DE C.V. RFC. MTR0705245M3 CFDI: Por definir Forma de Pago: Cheque Bancario Teléfono: 81 8351 8283 Contacto: Srta. Elizabeth Garza / Sr. (s) Eduardo Garza / Emeterio Vargas. Email: administracion@myatsa.com; evargas@moliendas.com; egarza@moliendas.com; garzacavazos@hotmail.com, | D79: COMODATO Elizabeth Garza - 81 8351 8283 ext.126 Eduardo Garza / Emeterio Vargas Email:administracion@myatsa.com; evargas@moliendas.com; egarza@moliendas.com; garzacavazos@hotmail.com | E79: 16 | F79: DANIEL ESTRADA | G79: =[1]DICIEMBRE!$BA$81 -> -0.0012 | S79: =(5250+300)*0.16+5250+300 -> 6438 | AY79: 6438 | BA79: =SUM(G79+S79+T79-U79-V79-W79-X79-Y79-Z79-AA79-AB79-AC79-AD79-AE79-AF79-AG79-AH79-AI79-AJ79-AK79-AL79-AM79-AN79-AO79-AP79-AQ79-AR79-AS79-AT79-AU79-AV79-AW79-AX79-AY79-AZ79) -> -0.0012
A80: 63 | B80: PABLO EMILIANO RODRIGUEZ DURAN | D80: COMODATO Pablo Rodriguez - 81 2010 3744 pablordzmasper@hotmail.com | E80: 2 | F80: JOSE LUIS | G80: =[1]DICIEMBRE!$BA$83 -> 0 | S80: =(300*0.16+300)*E80 -> 696 | T80: =759*0.16+759 -> 880.44 | AR80: 1576.44 | BA80: =SUM(G80+S80+T80-U80-V80-W80-X80-Y80-Z80-AA80-AB80-AC80-AD80-AE80-AF80-AG80-AH80-AI80-AJ80-AK80-AL80-AM80-AN80-AO80-AP80-AQ80-AR80-AS80-AT80-AU80-AV80-AW80-AX80-AY80-AZ80) -> 0 | BB80: COB. ENE'25: 1 INST. Y 1 MENS. PROP. 21 DIAS
A81: 64 | B81: PACKET CAR DE MONTERREY - PABLO ERNESTO CADENA ACEVEDO | C81: Nombre de la Empresa: PACKET CAR DE MONTERREY S.A. DE C.V. RFC. PCM200703M63 CFDI: Por definir Forma de Pago: Transferencia Teléfono: 811 722 2636 Contacto: Pablo Ernesto Cadena Acevedo Email: docrem@hotmail.com | D81: Pablo E. Cadena Acevedo - 811 722 2636 Email:docrem@hotmail.com | E81: 8 | F81: JOSE LUIS | G81: =[1]DICIEMBRE!$BA$82 -> 2784.0048 | S81: =(300*0.16+300)*E81 -> 2784 | AL81: 5568 | BA81: =SUM(G81+S81+T81-U81-V81-W81-X81-Y81-Z81-AA81-AB81-AC81-AD81-AE81-AF81-AG81-AH81-AI81-AJ81-AK81-AL81-AM81-AN81-AO81-AP81-AQ81-AR81-AS81-AT81-AU81-AV81-AW81-AX81-AY81-AZ81) -> 0.0048
A82: 65 | B82: PREFOM | D82: COMODATO Hugo Díaz - 81 1290 4608 admin@bloquerafbk.com | E82: 4 | F82: JOSE LUIS | G82: =[1]DICIEMBRE!$BA$84 -> 0 | S82: =(220*0.16+220)*E82 -> 1020.8 | AH82: 1020.8 | BA82: =SUM(G82+S82+T82-U82-V82-W82-X82-Y82-Z82-AA82-AB82-AC82-AD82-AE82-AF82-AG82-AH82-AI82-AJ82-AK82-AL82-AM82-AN82-AO82-AP82-AQ82-AR82-AS82-AT82-AU82-AV82-AW82-AX82-AY82-AZ82) -> 0
A83: 66 | B83: PROATAM - JOSE ANTONIO LOPEZ GARCIA (Saygar Constructora) | D83: Jose Antonio - 899 168 0313 Email: proatam.admon@gmail.com | E83: 4 | F83: JOSE LUIS | BA83: =SUM(G83+S83+T83-U83-V83-W83-X83-Y83-Z83-AA83-AB83-AC83-AD83-AE83-AF83-AG83-AH83-AI83-AJ83-AK83-AL83-AM83-AN83-AO83-AP83-AQ83-AR83-AS83-AT83-AU83-AV83-AW83-AX83-AY83-AZ83) -> 0 | BB83: BAJA 27-ENERO-2025
A84: 67 | B84: QUITAKILOS | D84: Myrian Guerra - 811 636 1249 81 8359 4400 Email:facturacion@quitakilos.com adriana@quitakilos.com | E84: 3 | F84: JOSE LUIS | G84: =[1]DICIEMBRE!$BA$87 -> -0.0044 | S84: =(250*0.16+250)*E84 -> 870 | AE84: 870 | BA84: =SUM(G84+S84+T84-U84-V84-W84-X84-Y84-Z84-AA84-AB84-AC84-AD84-AE84-AF84-AG84-AH84-AI84-AJ84-AK84-AL84-AM84-AN84-AO84-AP84-AQ84-AR84-AS84-AT84-AU84-AV84-AW84-AX84-AY84-AZ84) -> -0.0044
A85: 68 | B85: RAUL MURO RODRIGUEZ - EDGAR MURO | D85: COMODATO Edgar Muro - 81 2255 3176 transportesmuro@hotmail.com | E85: 3 | F85: JOSE LUIS | G85: =[1]DICIEMBRE!$BA$88 -> 4.5474735e-13 | S85: =(300*0.16+300)*E85 -> 1044 | AH85: 1044 | BA85: =SUM(G85+S85+T85-U85-V85-W85-X85-Y85-Z85-AA85-AB85-AC85-AD85-AE85-AF85-AG85-AH85-AI85-AJ85-AK85-AL85-AM85-AN85-AO85-AP85-AQ85-AR85-AS85-AT85-AU85-AV85-AW85-AX85-AY85-AZ85) -> 4.5474735e-13
A86: 69 | B86: RAYAS SERVICIOS Y DESARROLLOS INTEGRALES | D86: Cristel del Rio - 844 380 0154 Alfonso - 81 3643 2962 Email:alonsogaspar578@gmail.com | E86: 5 | F86: JOSE LUIS | G86: =[1]DICIEMBRE!$BA$89 -> 0 | S86: =(300*0.16+300)*E86 -> 1740 | AL86: 1740 | BA86: =SUM(G86+S86+T86-U86-V86-W86-X86-Y86-Z86-AA86-AB86-AC86-AD86-AE86-AF86-AG86-AH86-AI86-AJ86-AK86-AL86-AM86-AN86-AO86-AP86-AQ86-AR86-AS86-AT86-AU86-AV86-AW86-AX86-AY86-AZ86) -> 0
A87: 70 | B87: ROBERTO CARLOS AVILA GUZMAN | D87: COMODATO Roberto Avila - 81 8088 2340 fletes-avila@hotmail.com | E87: 8 | F87: JOSE LUIS | G87: =[1]DICIEMBRE!$BA$90 -> 0 | S87: =(300*0.16+300)*7 -> 2436 | T87: =1378*0.16+1378 -> 1598.48 | AD87: 4034.48 | BA87: =SUM(G87+S87+T87-U87-V87-W87-X87-Y87-Z87-AA87-AB87-AC87-AD87-AE87-AF87-AG87-AH87-AI87-AJ87-AK87-AL87-AM87-AN87-AO87-AP87-AQ87-AR87-AS87-AT87-AU87-AV87-AW87-AX87-AY87-AZ87) -> 0 | BB87: COB. ENE'25: 1 INST. NUEVA Y 1 MENS. PROP. DE 14 DIAS, SOLO SE LE COBRARON 7 MENS. PORQUE EL PAGO DE 1 UNIDAD YA ESTABA CUBIERTA
A88: 71 | B88: RODRIGO MORENO VILLARREAL | D88: COMODATO Rodrigo Moreno - 81 1410 4886 | E88: 3 | F88: JOSE LUIS | G88: =[1]DICIEMBRE!$BA$92 -> 0 | S88: =(300*0.16+300)*E88 -> 1044 | AE88: 1044 | BA88: =SUM(G88+S88+T88-U88-V88-W88-X88-Y88-Z88-AA88-AB88-AC88-AD88-AE88-AF88-AG88-AH88-AI88-AJ88-AK88-AL88-AM88-AN88-AO88-AP88-AQ88-AR88-AS88-AT88-AU88-AV88-AW88-AX88-AY88-AZ88) -> 0
A89: 72 | B89: SEI ARQUITECTOS - DANIELA OCHOA | D89: Contacto: Nohemi Montemayor Teléfono: 81 1495 0269 Email:daniela.ochoa@seiarquitectos.com claudia.martinez@seiarquitectos.com: | E89: 2 | F89: JOSE LUIS | G89: =[1]DICIEMBRE!$BA$33 -> 0.0012 | S89: =(250*0.16+250)*E89 -> 580 | AS89: 580 | BA89: =SUM(G89+S89+T89-U89-V89-W89-X89-Y89-Z89-AA89-AB89-AC89-AD89-AE89-AF89-AG89-AH89-AI89-AJ89-AK89-AL89-AM89-AN89-AO89-AP89-AQ89-AR89-AS89-AT89-AU89-AV89-AW89-AX89-AY89-AZ89) -> 0.0012
A90: 73 | B90: SERVICIO DE ALMACENAMIENTO Y TRANSPORTE RG II - CESAR RODRIGUEZ (GP MET LOGISTICS) | D90: Contacto: Cesar Rodriguez Teléfono: 81 3088 0606 Proveedores@cbrlogistics.com cesar.rdz@cbrlogistics.com | E90: 5 | F90: JOSE LUIS | G90: =[1]DICIEMBRE!$BA$29 -> 2900 | S90: =(250*0.16+250)*E90 -> 1450 | BA90: =SUM(G90+S90+T90-U90-V90-W90-X90-Y90-Z90-AA90-AB90-AC90-AD90-AE90-AF90-AG90-AH90-AI90-AJ90-AK90-AL90-AM90-AN90-AO90-AP90-AQ90-AR90-AS90-AT90-AU90-AV90-AW90-AX90-AY90-AZ90) -> 4350 | BB90: SE MIGRARA UNIDAD A CESAR RODRIGUEZ - ANTES GP MET LOGISTICS
A91: 74 | B91: SERVICIOS LOGISTICOS MARSEL - CLAUDIA LUNA GUTIERREZ TRANSMARSEL | C91: Nombre de la Empresa: CLAUDIA LUNA GUTIERREZ RFC. LUGC700301TKA CFDI: Comunicaciones satelitales Forma de Pago: Transferencia Teléfono: 811 155 5054 / 8183646871 Contacto: Sergio Leal / Jazmín Email: bazoon_300@hotmail.com; clg.lgc@hotmail.com; transportesmarsel@hotmail.com; | D91: Sergio Leal - 811 155 5054 Jazmín - 818 364 6871 Email:bazoon_300@hotmail.com; clg.lgc@hotmail.com; transportesmarsel@hotmail.com; | E91: 12 | F91: JOSE LUIS | G91: =[1]DICIEMBRE!$BA$30 -> 0 | S91: =(250*0.16+250)*E91 -> 3480 | AH91: 3480 | BA91: =SUM(G91+S91+T91-U91-V91-W91-X91-Y91-Z91-AA91-AB91-AC91-AD91-AE91-AF91-AG91-AH91-AI91-AJ91-AK91-AL91-AM91-AN91-AO91-AP91-AQ91-AR91-AS91-AT91-AU91-AV91-AW91-AX91-AY91-AZ91) -> 0
A92: 75 | B92: SH TRANSPORTACIONES DRP TRANSPORTES | C92: Nombre de la Empresa: DRP TRANSPORTES S. DE R. L. DE C.V. RFC.: DTR210720A25 CFDI : G03 Forma de Pago: Transferencia Teléfono: 81 1421 3083 Contacto: Francisco Sanchez Email: fsancheznoreste@hotmail.es | D92: Francisco Sanchez - 81 1421 3083 Email:fsancheznoreste@hotmail.es | E92: 11 | F92: JOSE LUIS | G92: =[1]DICIEMBRE!$BA$93 -> -0.0848 | S92: =(350*0.16+350)*E92 -> 4466 | T92: =1950*0.16+1950 -> 2262 | AJ92: 6728 | BA92: =SUM(G92+S92+T92-U92-V92-W92-X92-Y92-Z92-AA92-AB92-AC92-AD92-AE92-AF92-AG92-AH92-AI92-AJ92-AK92-AL92-AM92-AN92-AO92-AP92-AQ92-AR92-AS92-AT92-AU92-AV92-AW92-AX92-AY92-AZ92) -> -0.0848 | BB92: COB. ENE'25: 2 REVISIONES Y 1 INST. DE EQP. PORTATIL
A93: 76 | B93: SH TRANSPORTACIONES JUAN FRANCISCO SANCHEZ CONTRERAS | C93: Nombre de la Empresa: JUAN FRANCISCO SANCHEZ CONTRERAS RFC.: SACJ7811022UA CFDI : G03 Forma de Pago: Transferencia Teléfono: 81 1421 3083 Contacto: Francisco Sanchez Email: fsancheznoreste@hotmail.es | D93: Francisco Sanchez - 81 1421 3083 Email:fsancheznoreste@hotmail.es | E93: 3 | F93: JOSE LUIS | G93: =[1]DICIEMBRE!$BA$94 -> -0.0088 | S93: =(350*0.16+350)*E93 -> 1218 | AJ93: 1218 | BA93: =SUM(G93+S93+T93-U93-V93-W93-X93-Y93-Z93-AA93-AB93-AC93-AD93-AE93-AF93-AG93-AH93-AI93-AJ93-AK93-AL93-AM93-AN93-AO93-AP93-AQ93-AR93-AS93-AT93-AU93-AV93-AW93-AX93-AY93-AZ93) -> -0.0088
A94: 77 | B94: SILVIA NERI SALAZAR - ACERTRANS | C94: Nombre de la Empresa: SILVIA NERI SALAZAR RFC.: NESS6001221GA CFDI: Gastos en general Forma de Pago: Transferencia Teléfono: 811 521 3582 / 811 044 7961 Contacto: Arturo Sifuentes / Silvia Neri Salazar Email: ventas@acertrans.com.mx; logisticasifal@hotmail.com; Silvia-neri@hotmail.com; | D94: Arturo Sifuentes - 811 521 3582 Silvia Neri Salazar - 811 044 7961 Email: silvia-neri@hotmail.com; ventas@acertrans.com.mx; logisticasifal@hotmail.com; | E94: 5 | F94: JOSE LUIS | G94: =[1]DICIEMBRE!$BA$19 -> 0 | S94: =350*E94*0.16+350*E94 -> 2030 | AF94: 2030 | BA94: =SUM(G94+S94+T94-U94-V94-W94-X94-Y94-Z94-AA94-AB94-AC94-AD94-AE94-AF94-AG94-AH94-AI94-AJ94-AK94-AL94-AM94-AN94-AO94-AP94-AQ94-AR94-AS94-AT94-AU94-AV94-AW94-AX94-AY94-AZ94) -> 0
A95: 78 | B95: SINDUSA SERVICIOS INDUSTRIALES – PABLO MORALES | D95: Pablo Morales - 81 3529 5622 | E95: 1 | S95: =(249*0.16+249)*E95 -> 288.84 | T95: =1850*0.16+1850 -> 2146 | AD95: 2434.84 | BA95: =SUM(G95+S95+T95-U95-V95-W95-X95-Y95-Z95-AA95-AB95-AC95-AD95-AE95-AF95-AG95-AH95-AI95-AJ95-AK95-AL95-AM95-AN95-AO95-AP95-AQ95-AR95-AS95-AT95-AU95-AV95-AW95-AX95-AY95-AZ95) -> 0 | BB95: CLIENTE NUEVO 08-ENERO-2025
A96: 79 | B96: SITELECOM SERVICIOS DE INGENIERIA Y TELECOMUNICACIONES | D96: COMODATO Fermin Uribe Ramos - 7732188379 Alejandro - 77 1393 3704 eber.sannicolas@sitelecom.lat | E96: 9 | F96: JOSE LUIS | G96: =[1]DICIEMBRE!$BA$95 -> 4.5474735e-13 | S96: =(300*0.16+300)*E96 -> 3132 | AY96: 3132 | BA96: =SUM(G96+S96+T96-U96-V96-W96-X96-Y96-Z96-AA96-AB96-AC96-AD96-AE96-AF96-AG96-AH96-AI96-AJ96-AK96-AL96-AM96-AN96-AO96-AP96-AQ96-AR96-AS96-AT96-AU96-AV96-AW96-AX96-AY96-AZ96) -> 4.5474735e-13
A97: 80 | B97: TEGMESA S.A. DE C.V. - GRUAS TEGMESA | C97: Nombre de la Empresa: GRUAS TEGMESA S.A. DE C.V. RFC. GTE1602233N9 CFDI : Gastos en general Forma de Pago: Transferencia Teléfono: 81 1908 2914 Contacto: Julia Gonzalez Sosa Email: julia@construtecacero.com.mx | D97: COMODATO Raul Hernandez - 811 2422 086 Julia Graciela Gzz. Sosa - 811 9082 914 Email:gruastegmesa@construtecacero.com.mx julia@construtecacero.com.mx | E97: 13 | F97: JOSE LUIS | G97: =[1]DICIEMBRE!$BA$55 -> -0.0004 | S97: =(300*0.16+300)*E97 -> 4524 | AS97: 4524 | BA97: =SUM(G97+S97+T97-U97-V97-W97-X97-Y97-Z97-AA97-AB97-AC97-AD97-AE97-AF97-AG97-AH97-AI97-AJ97-AK97-AL97-AM97-AN97-AO97-AP97-AQ97-AR97-AS97-AT97-AU97-AV97-AW97-AX97-AY97-AZ97) -> -0.0004
A98: 81 | B98: TRACTO TRANSPORTES FRASAGA - ISMAEL ESCAREÑO | D98: Ismael Escareño - 81 3079 9137 | E98: 2 | F98: JOSE LUIS | G98: =[1]DICIEMBRE!$BA$97 -> 2909.6628 | S98: =(250*0.16+250)*E98 -> 580 | T98: =350*0.16+350 -> 406 | BA98: =SUM(G98+S98+T98-U98-V98-W98-X98-Y98-Z98-AA98-AB98-AC98-AD98-AE98-AF98-AG98-AH98-AI98-AJ98-AK98-AL98-AM98-AN98-AO98-AP98-AQ98-AR98-AS98-AT98-AU98-AV98-AW98-AX98-AY98-AZ98) -> 3895.6628 | BB98: COB. ENE'25: 1 REVISION Y 1 FACTURA PDTE.
A99: 82 | B99: TRANSPORTES BESERKER - ERNESTO GOMEZ | D99: COMODATO Ernesto Gómez - 81 2001 9256 ernesto.gomez@sanbox.com.mx | E99: 5 | F99: JOSE LUIS | S99: =(250*0.16+250)*E99 -> 1450 | T99: =(549*0.16+549)*5 -> 3184.2 | AI99: 4634.2 | BA99: =SUM(G99+S99+T99-U99-V99-W99-X99-Y99-Z99-AA99-AB99-AC99-AD99-AE99-AF99-AG99-AH99-AI99-AJ99-AK99-AL99-AM99-AN99-AO99-AP99-AQ99-AR99-AS99-AT99-AU99-AV99-AW99-AX99-AY99-AZ99) -> 9.094947e-13 | BB99: COB. ENE'25: 5 INST. NUEVAS, COBRAR EN FEB 21 DIAS
A100: 83 | B100: TRANSPORTE STA ELENA GRAL ZUAZUA NL CARGA Y PERSONAL - FRANCELIA | C100: Nombre de la Empresa: TRANSPORTES STA ELENA GRAL ZUAZUA NL CARGA Y PERSONAL S.A. DE C.V. RFC. TSE210312P9A CFDI: Gastos en General Forma de Pago: Transferencia Teléfono: 811 244 6019 Contacto: Argelio Arrambide Email: santaelenasadecv2021@gmail.com | D100: Argelio Arrambide - 8112446019 Email:santaelenasadecv2021@gmail.com | E100: 9 | F100: MARIO ULISES | G100: =[1]DICIEMBRE!$BA$47 -> 0.0028 | S100: =(275*0.16+275)*E100 -> 2871 | T100: =650*0.16+650 -> 754 | AR100: 3625 | BA100: =SUM(G100+S100+T100-U100-V100-W100-X100-Y100-Z100-AA100-AB100-AC100-AD100-AE100-AF100-AG100-AH100-AI100-AJ100-AK100-AL100-AM100-AN100-AO100-AP100-AQ100-AR100-AS100-AT100-AU100-AV100-AW100-AX100-AY100-AZ100) -> 0.0028 | BB100: COB. ENE'25: 1 REVISION
A101: 84 | B101: USA MACHINERY & RENTALS | D101: COMODATO Ramiro - 81 2319 4917 | E101: 5 | S101: =(299*0.16+299)*5 -> 1734.2 | T101: =(549*0.16+549)*E101 -> 3184.2 | AE101: 4918.4 | BA101: =SUM(G101+S101+T101-U101-V101-W101-X101-Y101-Z101-AA101-AB101-AC101-AD101-AE101-AF101-AG101-AH101-AI101-AJ101-AK101-AL101-AM101-AN101-AO101-AP101-AQ101-AR101-AS101-AT101-AU101-AV101-AW101-AX101-AY101-AZ101) -> 9.094947e-13 | BB101: CLIENTE NUEVO 11-ENERO-2024, PDTES. 2 INST. YA PAGADAS , COBRAR PROP. EN FEB.
A102: 85 | B102: YOHANA ALEIDA DE LEON SALINAS - TDL TRANSPORTES | C102: Nombre de la Empresa: TDL TRANSPORTES Contacto: Roberto Cervantes Teléfono: 811 910 8849 / 811 255 1586 Email: tdl.yohana@hotmail.com | D102: Roberto Cervantes - 811 910 8849 811 255 1586 tdl.yohana@hotmail.com | E102: 13 | F102: JOSE LUIS | G102: =[1]DICIEMBRE!$BA$96 -> 0 | S102: =(300*0.16+300)*E102 -> 4524 | AS102: 4524 | BA102: =SUM(G102+S102+T102-U102-V102-W102-X102-Y102-Z102-AA102-AB102-AC102-AD102-AE102-AF102-AG102-AH102-AI102-AJ102-AK102-AL102-AM102-AN102-AO102-AP102-AQ102-AR102-AS102-AT102-AU102-AV102-AW102-AX102-AY102-AZ102) -> 0
...

Sheet FEBRERO
B2: Cobranza Total 2025 | D2: =SUM(S2+S3+S4+S5+S6+S7+S8+S9+S10+S11+S12+S13+D5) -> 675018.29 | E2: Saldos 2024 | S2: =G213 -> 46667.546
E3: Enero`25 | S3: =H213-S2 -> 7113.248
B4: COBRANZA FEBRERO 2025 | E4: Febrero´25 | S4: =I213 -> 0
B5: Febrero'2025 | D5: =S213+T213+U213 -> 621237.49 | E5: Marzo'25 | S5: =J213 -> 0
B6: Recuperación del 01 al 02 | D6: =SUM(V213:W213) -> 15004.8 | E6: Abril´25 | S6: =K213 -> 0
B7: Recuperación del 03 al 09 | D7: =SUM(X213:AD213) -> 159634.97 | E7: Mayo´25 | S7: =L213 -> 0
B8: Recuperación del 10 al 16 | D8: =SUM(AE213:AK213) -> 168928.58 | E8: Junio´25 | S8: =M213 -> 0
B9: Recuperación del 17 al 23 | D9: =SUM(AL213:AR213) -> 193494.59 | E9: Julio´25 | S9: =N213 -> 0
B10: Recuperación del 24 al 28 | D10: =SUM(AS213:AW213) -> 76341.7 | E10: Agosto'25 | S10: =O213 -> 0
E11: Septiembre'25 | S11: =P213 -> 0
E12: Octubre'25 | S12: =Q213 -> 0
B13: Total Recuperado | D13: =SUM(D6:D11) -> 613404.64 | E13: Noviembre'25 | S13: =R213 -> 0
B14: Por Recuperar | D14: =D2-D13 -> 61613.647 | E14: Total de Arrastre: | S14: =SUM(S2:S13) -> 53780.794
A16: NO. | B16: CLIENTE | C16: DATOS FISCALES | D16: CONTACTO | E16: UNI | F16: VENTA | G16: ATRASO | S16: IMPORTE FEB´2025 | T16: SERV. EXTRAS | U16: DES % | V16: 1 | W16: 2 | X16: 3 | Y16: 4 | Z16: 5 | AA16: 6 | AB16: 7 | AC16: 8 | AD16: 9 | AE16: 10 | AF16: 11 | AG16: 12 | AH16: 13 | AI16: 14 | AJ16: 15 | AK16: 16 | AL16: 17 | AM16: 18 | AN16: 19 | AO16: 20 | AP16: 21 | AQ16: 22 | AR16: 23 | AS16: 24 | AT16: 25 | AU16: 26 | AV16: 27 | AW16: 28 | AX16: SALDOS PENDIENTES | AY16: COMENTARIOS | AZ16: ESTATUS PROMESA DE PAGO
G17: 2024 | H17: ENE | I17: FEB | J17: MAR | K17: ABR | L17: MAY | M17: JUN | N17: JUL | O17: AGO | P17: SEP | Q17: OCT | R17: NOV | V17: S | W17: D | X17: L | Y17: M | Z17: M | AA17: J | AB17: V | AC17: S | AD17: D | AE17: L | AF17: M | AG17: M | AH17: J | AI17: V | AJ17: S | AK17: D | AL17: L | AM17: M | AN17: M | AO17: J | AP17: V | AQ17: S | AR17: D | AS17: L | AT17: M | AU17: M | AV17: J | AW17: V
A18: 1 | B18: ADRIANA ORANDAY DAVILA - RODRIGO ALANIS | D18: Rodrigo Alanis - 81 2861 1509 Email:adrianaoranday@gmail.com alanis_rodrigo@hotmail.com | E18: 1 | F18: JOSE LUIS | G18: =[1]DICIEMBRE!$BA$91 -> 290 | H18: =ENERO!BA18 -> 580 | S18: =(250*0.16+250)*E18 -> 290 | AX18: =SUM(H18+S18+T18-U18-V18-W18-X18-Y18-Z18-AA18-AB18-AC18-AD18-AE18-AF18-AG18-AH18-AI18-AJ18-AK18-AL18-AM18-AN18-AO18-AP18-AQ18-AR18-AS18-AT18-AU18-AV18-AW18) -> 870
A19: 2 | B19: ALIMENTOS REGIOMONTANOS PERCAM - ALIMENTOS GRUPER | C19: Nombre de la Empresa: ALIMENTOS GUPER S.A. DE C.V. Contacto: Nancy Paola Perales Teléfono: 811 801 4266 Email: alimentosgupersacv@gmail.com | D19: Alejandro Garcia - 81 2034 3938 Nancy Paola Perales - 8118014266 Alimentosregiopercam@gmail.com alimentosgupersacv@gmail.com | E19: 18 | F19: DANIEL ESTRADA | G19: =[1]DICIEMBRE!$BA$21 -> -0.3952 | H19: =ENERO!BA19 -> -0.3952 | S19: =(300*0.16+300)*E19 -> 6264 | AB19: 6263.6 | AX19: =SUM(H19+S19+T19-U19-V19-W19-X19-Y19-Z19-AA19-AB19-AC19-AD19-AE19-AF19-AG19-AH19-AI19-AJ19-AK19-AL19-AM19-AN19-AO19-AP19-AQ19-AR19-AS19-AT19-AU19-AV19-AW19) -> 0.0048
A20: 3 | B20: AUTO EXPRESS GERAL 21 S.A. DE C.V. - LUIS GERARDO BOLAÑOS GARCIA | C20: Nombre de la Empresa: LUIS GERARDO BOLAÑOS GARCIA RFC. BOGL8702094H5 CFDI: Gastos en general Forma de Pago: Transferencia Teléfono: 811 027 0226 Contacto: Luis Gerardo Bolaños García Email: luismty0902@gmail.com; | D20: Luis Gerardo Bolaños García - 811 027 0226 Email:expressgeral19@gmail.com luismty0902@gmail.com | E20: 5 | F20: JOSE LUIS | G20: =[1]DICIEMBRE!$BA$75 -> 3190.0028 | H20: =ENERO!BA20 -> 0.0028 | S20: =(280*0.16+280)*E20 -> 1624 | Z20: 1624 | AX20: =SUM(H20+S20+T20-U20-V20-W20-X20-Y20-Z20-AA20-AB20-AC20-AD20-AE20-AF20-AG20-AH20-AI20-AJ20-AK20-AL20-AM20-AN20-AO20-AP20-AQ20-AR20-AS20-AT20-AU20-AV20-AW20) -> 0.0028
A21: 4 | B21: AUTOEXPRESS MATA | C21: Nombre de la Empresa: AUTOEXPRESS MATA S.A. DE C.V. RFC. AMA040520BZ2 CFDI : Forma de Pago: Transferencia Teléfono: 81 1029 1017 Contacto: Edgar Garza Email: | D21: COMODATO Edgar Garza - 81 1029 1017 | E21: 3 | F21: JOSE LUIS | G21: =[1]DICIEMBRE!$BA$23 -> -0.0032 | H21: =ENERO!BA21 -> -0.0032 | S21: =(299*0.16+299)*E21 -> 1040.52 | AM21: 1040.52 | AX21: =SUM(H21+S21+T21-U21-V21-W21-X21-Y21-Z21-AA21-AB21-AC21-AD21-AE21-AF21-AG21-AH21-AI21-AJ21-AK21-AL21-AM21-AN21-AO21-AP21-AQ21-AR21-AS21-AT21-AU21-AV21-AW21) -> -0.0032
A22: 5 | B22: AUTOREDES EL BAJIO | D22: COMODATO Mane Troncoso -833 192 6706 Email:admontubored@hotmail.com | E22: 10 | F22: JOSE LUIS | G22: =[1]DICIEMBRE!$BA$24 -> -0.3952 | H22: =ENERO!BA22 -> -0.3952 | S22: =(270*0.16+270)*E22 -> 3132 | AB22: 3131.6 | AX22: =SUM(H22+S22+T22-U22-V22-W22-X22-Y22-Z22-AA22-AB22-AC22-AD22-AE22-AF22-AG22-AH22-AI22-AJ22-AK22-AL22-AM22-AN22-AO22-AP22-AQ22-AR22-AS22-AT22-AU22-AV22-AW22) -> 0.0048
A23: 6 | B23: BAWOMA CONTROL TOTAL S.A. DE C.V. - FUMIGAZ | C23: Nombre de la Empresa: BAWOMA CONTROL TOTAL S.A. DE C.V. RFC.: BCT100310834 CFDI: Gastos en General Forma de Pago: Transferencia Teléfono: 81 1811 0645 Contacto: Manuel Rico Email: supervisorfumigaz@outlook.com | D23: COMODATO Manuel Rico - 81 1811 0645 Email:supervisorfumigaz@outlook.com | E23: 2 | F23: JOSE LUIS | G23: =[1]DICIEMBRE!$BA$48 -> 696 | H23: =ENERO!BA23 -> 696 | S23: =(300*0.16+300)*1 -> 348 | AU23: 1044 | AX23: =SUM(H23+S23+T23-U23-V23-W23-X23-Y23-Z23-AA23-AB23-AC23-AD23-AE23-AF23-AG23-AH23-AI23-AJ23-AK23-AL23-AM23-AN23-AO23-AP23-AQ23-AR23-AS23-AT23-AU23-AV23-AW23) -> 0 | AY23: PDTE. 1 DES-INST. YA PAGADA
A24: 7 | B24: BE ONE SYSTEMS | D24: Lydia Colunga - 81 1176 3598 Edgar Valentin (Pagos) - 81 1970 7000 Email:edgar.valentin@beone.mx lydia@beone.mx | E24: 1 | F24: JOSE LUIS | G24: =[1]DICIEMBRE!$BA$25 -> 0 | H24: =ENERO!BA24 -> 0 | S24: =250*0.16+250 -> 290 | Y24: 290 | AX24: =SUM(H24+S24+T24-U24-V24-W24-X24-Y24-Z24-AA24-AB24-AC24-AD24-AE24-AF24-AG24-AH24-AI24-AJ24-AK24-AL24-AM24-AN24-AO24-AP24-AQ24-AR24-AS24-AT24-AU24-AV24-AW24) -> 0
A25: 8 | B25: BRANDO IVAN MARTINEZ GOVEA - JOSUE FERNANDEZ | D25: Josue Fernandez - 81 1977 0958 Email:jfhz@icloud.com | E25: 5 | F25: JOSE LUIS | G25: =[1]DICIEMBRE!$BA$64 -> 0.0068 | H25: =ENERO!BA25 -> 0.0068 | S25: =(250*0.16+250)*E25 -> 1450 | AB25: 1450.01 | AX25: =SUM(H25+S25+T25-U25-V25-W25-X25-Y25-Z25-AA25-AB25-AC25-AD25-AE25-AF25-AG25-AH25-AI25-AJ25-AK25-AL25-AM25-AN25-AO25-AP25-AQ25-AR25-AS25-AT25-AU25-AV25-AW25) -> -0.0032
A26: 9 | B26: CARLOS JONATHAN MARTINEZ RIVERA | D26: Jonathan Rivera - 81 1696 5321 jonathanrivera22929@gmail.com | E26: 1 | F26: JOSE LUIS | G26: =[1]DICIEMBRE!$BA$134 -> 0 | H26: =ENERO!BA139 -> 48 | S26: =(300*0.16+300)*E26 -> 348 | Z26: 396 | AX26: =SUM(H26+S26+T26-U26-V26-W26-X26-Y26-Z26-AA26-AB26-AC26-AD26-AE26-AF26-AG26-AH26-AI26-AJ26-AK26-AL26-AM26-AN26-AO26-AP26-AQ26-AR26-AS26-AT26-AU26-AV26-AW26) -> 0 | AY26: CAMBIA A ESQUEMA DE FACTURACION 05-FEBRERO-2025
A27: 10 | B27: CARNES RIBHAUS | D27: COMODATO Tania Reyes - 81 1631 2529 Roberta Treviño - 81 1909 7008 Email:facturas@carnesribhaus.com.mx robertaribhaus@gmail.com | E27: 5 | F27: JOSE LUIS | G27: =[1]DICIEMBRE!$BA$27 -> 0.004 | H27: =ENERO!BA26 -> 0.004 | S27: =(279*0.16+279)*E27 -> 1618.2 | Z27: 1618.2 | AX27: =SUM(H27+S27+T27-U27-V27-W27-X27-Y27-Z27-AA27-AB27-AC27-AD27-AE27-AF27-AG27-AH27-AI27-AJ27-AK27-AL27-AM27-AN27-AO27-AP27-AQ27-AR27-AS27-AT27-AU27-AV27-AW27) -> 0.004
A28: 11 | B28: CARPACK, S.A. DE C.V. | C28: Nombre de la Empresa: CARPACK S.A. DE C.V. RFC.: CAR070302UU2 CFDI: Gastos en General Forma de Pago: TransferenciaTeléfono: 811 277 9070 Contacto: Kelly Mayorga Email: compras@carpack.com.mx; antonioespinosa@carpack.com.mx; elizabeth@carpack.com.mx; | D28: COMODATO Kelly Mayorga - 8112779070 Elizabeth Campos - 8116635976 8181919205 Ext. 107 Email:antonioespinosa@carpack.com.mx; elizabeth@carpack.com.mx; compras@carpack.com.mx; pagos@carpack.com.mx | E28: 5 | F28: JOSE LUIS | G28: =[1]DICIEMBRE!$BA$28 -> 0.0028 | H28: =ENERO!BA27 -> 0.0028 | S28: =(280*0.16+280)*E28 -> 1624 | Z28: 1624 | AX28: =SUM(H28+S28+T28-U28-V28-W28-X28-Y28-Z28-AA28-AB28-AC28-AD28-AE28-AF28-AG28-AH28-AI28-AJ28-AK28-AL28-AM28-AN28-AO28-AP28-AQ28-AR28-AS28-AT28-AU28-AV28-AW28) -> 0.0028
A29: 12 | B29: COMERCIALIZADORA AGROPECUARIA ICK -JORGE ADRIAN RIVERA | C29: Nombre de la Empresa: COMERCIALIZADORA AGROPECUARIA ICK S.A. DE C.V. RFC.: CAI220330VD7 CFDI: Gastos en general Teléfono: 81 2860 1814 Contacto: Adrian Rivera Email: adrian.rmoxica75@gmail.com | D29: COMODATO Adrian Rivera - 81 2860 1814 Email:adrian.rmoxica75@gmail.com | E29: 4 | F29: JOSE LUIS | G29: =[1]DICIEMBRE!$BA$20 -> 0 | H29: =ENERO!BA28 -> 0 | S29: =(300*0.16+300)*E29 -> 1392 | AB29: 1392 | AX29: =SUM(H29+S29+T29-U29-V29-W29-X29-Y29-Z29-AA29-AB29-AC29-AD29-AE29-AF29-AG29-AH29-AI29-AJ29-AK29-AL29-AM29-AN29-AO29-AP29-AQ29-AR29-AS29-AT29-AU29-AV29-AW29) -> 0
A30: 13 | B30: COMERCIALIZADORA FUERZA CEMENTERA | D30: Candy - 81 2634 9644 candymoreno@forzadelnorte.com | E30: 5 | F30: JOSE LUIS | G30: =[1]DICIEMBRE!$BA$31 -> -3480 | H30: =ENERO!BA29 -> -1740 | S30: =(300*0.16+300)*E30 -> 1740 | AX30: =SUM(H30+S30+T30-U30-V30-W30-X30-Y30-Z30-AA30-AB30-AC30-AD30-AE30-AF30-AG30-AH30-AI30-AJ30-AK30-AL30-AM30-AN30-AO30-AP30-AQ30-AR30-AS30-AT30-AU30-AV30-AW30) -> 0 | AY30: PAGO 3 MESES COBRAR HASTA MARZO 2025
A31: 14 | B31: COMERCIALIZADORA Y LOGISTICA SIFAL - ARTURO SIFUENTES | D31: Arturo Sifuentes - 811 521 3582 Email: silvia-neri@hotmail.com; ventas@acertrans.com.mx; logisticasifal@hotmail.com; | E31: 5 | F31: JOSE LUIS | G31: =[1]DICIEMBRE!$BA$18 -> -128 | H31: =ENERO!BA30 -> -128 | S31: =(350*0.16+350)*E31 -> 2030 | AO31: 2030 | AX31: =SUM(H31+S31+T31-U31-V31-W31-X31-Y31-Z31-AA31-AB31-AC31-AD31-AE31-AF31-AG31-AH31-AI31-AJ31-AK31-AL31-AM31-AN31-AO31-AP31-AQ31-AR31-AS31-AT31-AU31-AV31-AW31) -> -128
A32: 15 | B32: COMPAÑÍA MADERERA CUAUHTEMOC | D32: COMODATO Daniel Cardenas - 81 2634 0402 Email:recepcionfacturas@ciamaderera.com | E32: 5 | F32: JOSE LUIS | G32: =[1]DICIEMBRE!$BA$77 -> 0.0012 | H32: =ENERO!BA31 -> 0.0012 | S32: =(250*0.16+250)*4+(300*0.16+300)*1 -> 1508 | Y32: 1508 | AX32: =SUM(H32+S32+T32-U32-V32-W32-X32-Y32-Z32-AA32-AB32-AC32-AD32-AE32-AF32-AG32-AH32-AI32-AJ32-AK32-AL32-AM32-AN32-AO32-AP32-AQ32-AR32-AS32-AT32-AU32-AV32-AW32) -> 0.0012
A33: 16 | B33: CONTINENTAL PARABELLUM - GRUPO SAR | D33: Alan Rodriguez finanzas.gposar@gmail.com | E33: 6 | F33: MARIO ULISES | G33: =[1]DICIEMBRE!$BA$32 -> 0 | H33: =ENERO!BA32 -> -0.004 | S33: =(279*0.16+279)*E33 -> 1941.84 | AB33: 1941.84 | AX33: =SUM(H33+S33+T33-U33-V33-W33-X33-Y33-Z33-AA33-AB33-AC33-AD33-AE33-AF33-AG33-AH33-AI33-AJ33-AK33-AL33-AM33-AN33-AO33-AP33-AQ33-AR33-AS33-AT33-AU33-AV33-AW33) -> -0.004
A34: 17 | B34: DAXS INDUSTRIAL - JOSE HUMBERTO VILLA | D34: Humberto Villa - 81 1487 4381 Email:daxsind@hotmail.com | E34: 2 | G34: =[1]DICIEMBRE!$BA$61 -> 2598.4 | H34: =ENERO!BA33 -> 2598.4 | AX34: =SUM(H34+S34+T34-U34-V34-W34-X34-Y34-Z34-AA34-AB34-AC34-AD34-AE34-AF34-AG34-AH34-AI34-AJ34-AK34-AL34-AM34-AN34-AO34-AP34-AQ34-AR34-AS34-AT34-AU34-AV34-AW34) -> 2598.4 | AY34: BAJA
A35: 18 | B35: DISTRIBUIDORA FERRELECTRICA Y MATERIALES EXPRESS - DEX MATERIALES | D35: Aleyda - 81 3402 1812 Rolando Ziragem 811 077 1470 812 597 2700 / 812 332 3606 oficina@dexmateriales.com; rzgc@hotmail.com; rolando@dexmateriales.com; | E35: 9 | F35: JOSE LUIS | G35: =[1]DICIEMBRE!$BA$34 -> 0 | H35: =ENERO!BA34 -> 0 | S35: 0 | AX35: =SUM(H35+S35+T35-U35-V35-W35-X35-Y35-Z35-AA35-AB35-AC35-AD35-AE35-AF35-AG35-AH35-AI35-AJ35-AK35-AL35-AM35-AN35-AO35-AP35-AQ35-AR35-AS35-AT35-AU35-AV35-AW35) -> 0 | AY35: PAGARA 6 MENS. COBRAR HASTA EL MES DE MARZO 2025 CAMBIA A ESQUEMA DE MENSUALIDAD 06-SEPTIEMBRE-2024 Y DA DE BAJA 3 UNIDADES Y SE SEPARA CUENTA A COMERCIALIZADORA FUERZA CEMENTERA
A36: 19 | B36: EDGAR ALBERTO CORTEZ TREVIÑO | D36: Edgar Cortez - 81 8185 6454 | E36: 1 | F36: JOSE LUIS | G36: =[1]DICIEMBRE!$BA$35 -> 0 | H36: =ENERO!BA35 -> 0 | S36: =(250*0.16+250)*E36 -> 290 | AC36: 290 | AX36: =SUM(H36+S36+T36-U36-V36-W36-X36-Y36-Z36-AA36-AB36-AC36-AD36-AE36-AF36-AG36-AH36-AI36-AJ36-AK36-AL36-AM36-AN36-AO36-AP36-AQ36-AR36-AS36-AT36-AU36-AV36-AW36) -> 0
A37: 20 | B37: ELIZABETH RENTERIA REVILLA | C37: Nombre de la Empresa: ELIZABETH RENTERÍA REVILLA RFC. RERE760807SX9 CFDI: Gastos en general Forma de Pago: TransferenciaTeléfono: 811 810 0155 Contacto: Elizabeth Rentería Email: e.lic@live.com.mx | D37: Elizabeth Renteria - 811 810 0155 Email:e.lic@live.com.mx | E37: 2 | F37: JOSE LUIS | G37: =[1]DICIEMBRE!$BA$37 -> 0 | H37: =ENERO!BA36 -> 0 | S37: =(250*0.16+250)*1+(166.66*0.16+166.66) -> 483.3256 | AH37: 483.33 | AX37: =SUM(H37+S37+T37-U37-V37-W37-X37-Y37-Z37-AA37-AB37-AC37-AD37-AE37-AF37-AG37-AH37-AI37-AJ37-AK37-AL37-AM37-AN37-AO37-AP37-AQ37-AR37-AS37-AT37-AU37-AV37-AW37) -> -0.0044 | AY37: COB. FEB'25: 1 MENS. PROP. 20 DIAS COBRAR EN MARZO MENS. COMPL.
A38: 21 | B38: ENDER INDUSTRIAL (EMMANUEL VAZQUEZ - SINERGIX ) | C38: Nombre de la Empresa: ENDER INDUSTRIAL S.A. DE C.V. RFC.: SIS1703089V6 CFDI: Gastos en General. Forma de Pago: Transferencia Teléfono: 813 055 7409 / 81) 2141 0506 Contacto: Emmanuel Vázquez / Sonia Lugo Email: emmanuel@sinergix.net; sonia@sinergix.net; | D38: COMODATO Emmanuel Vazquez - 81 3055 7409 Sonia Lugo (pagos) - 81 2141 0506 Email:sandra@enderindustrial.com claudia@enderindustrial.com belen@enderindustrial.com facturas@enderindustrial.com; emmanuel@sinergix.net; | E38: 7 | F38: JOSE LUIS | G38: =[1]DICIEMBRE!$BA$38 -> -753.9924 | H38: =ENERO!BA37 -> -753.9924 | S38: =(350*0.16+350)*E38 -> 2842 | AA38: 2842 | AX38: =SUM(H38+S38+T38-U38-V38-W38-X38-Y38-Z38-AA38-AB38-AC38-AD38-AE38-AF38-AG38-AH38-AI38-AJ38-AK38-AL38-AM38-AN38-AO38-AP38-AQ38-AR38-AS38-AT38-AU38-AV38-AW38) -> -753.9924
A39: 22 | B39: ENDO LASER MICROQUIRURGICO - INSTITUTO VIDAURRI DE OJOS (DANIELA MEDELLIN) | D39: Daniela Medellín - 81 1588 8485 Email:monitoreo@endolaser.com.mx | E39: 4 | F39: JOSE LUIS | G39: =[1]DICIEMBRE!$BA$59 -> 6.8212103e-13 | H39: =ENERO!BA38 -> 9.094947e-13 | S39: =(249*0.16+249)*E39 -> 1155.36 | AI39: 1155.36 | AX39: =SUM(H39+S39+T39-U39-V39-W39-X39-Y39-Z39-AA39-AB39-AC39-AD39-AE39-AF39-AG39-AH39-AI39-AJ39-AK39-AL39-AM39-AN39-AO39-AP39-AQ39-AR39-AS39-AT39-AU39-AV39-AW39) -> 1.1368684e-12
A40: 23 | B40: EXTINTORES Y EQUIPOS MONTERREY (SERGIO GONZALEZ) | D40: COMODATO Gabriela - 81 2077 4512 Sergio Gonzalez - 81 8654 2753 sergio.jr987@outlook.com | E40: 2 | F40: JOSE LUIS | G40: =[1]DICIEMBRE!$BA$41 -> 0 | H40: =ENERO!BA39 -> 0 | S40: =(300*0.16+300)*2 -> 696 | AB40: 696 | AX40: =SUM(H40+S40+T40-U40-V40-W40-X40-Y40-Z40-AA40-AB40-AC40-AD40-AE40-AF40-AG40-AH40-AI40-AJ40-AK40-AL40-AM40-AN40-AO40-AP40-AQ40-AR40-AS40-AT40-AU40-AV40-AW40) -> 0 | AY40: PDTE 1 INSTALACION YA PAGADA SOLO COBRAR PROP. CUANDO SE INSTALE
A41: 24 | B41: FERNANDO RAFAEL GONZALEZ MONTEMAYOR (SERVICIO DE PLATAFORMA) | C41: Nombre de la Empresa: GOMO SERVICES Contacto: FERNANDO DISATEL Email: frgm_76@hotmail.com Remisiones con IVA | D41: Fernando Disatel - 81 1799 2490 Email:frgm_76@hotmail.com | E41: 674 | F41: JOSE LUIS | G41: =[1]DICIEMBRE!$BA$42 -> 3220.026 | H41: =ENERO!BA40 -> 3220.026 | S41: =(38.8*0.16+38.8)*E41 -> 30335.392 | AM41: 30335.39 | AX41: =SUM(H41+S41+T41-U41-V41-W41-X41-Y41-Z41-AA41-AB41-AC41-AD41-AE41-AF41-AG41-AH41-AI41-AJ41-AK41-AL41-AM41-AN41-AO41-AP41-AQ41-AR41-AS41-AT41-AU41-AV41-AW41) -> 3220.028
A42: 25 | B42: FERNANDO REYES HERNANDES | D42: COMODATO Fernando Reyes - 81 1821 3781 Viridiana Flores - 81 1796 4130 arnol84reyeshdz@gmail.com | E42: 1 | F42: JOSE LUIS | G42: =[1]DICIEMBRE!$BA$43 -> 348 | H42: =ENERO!BA41 -> 0 | S42: =(300*0.16+300)*E42 -> 348 | AE42: 348 | AX42: =SUM(H42+S42+T42-U42-V42-W42-X42-Y42-Z42-AA42-AB42-AC42-AD42-AE42-AF42-AG42-AH42-AI42-AJ42-AK42-AL42-AM42-AN42-AO42-AP42-AQ42-AR42-AS42-AT42-AU42-AV42-AW42) -> 0
A43: 26 | B43: FINPAIS | C43: Nombre de la Empresa: FINPAIS S.A. DE C.V. RFC. FCO130429629 CFDI: Gastos en general Forma de Pago: TransferenciaTeléfono: 81 8208 7559 Contacto: Katty Email: administracion@finpais.com.mx | D43: COMODATO Katty - 81 8208 7559 Email:administracion@finpais.com.mx | E43: 7 | F43: JOSE LUIS | G43: =[1]DICIEMBRE!$BA$44 -> 2598.3956 | H43: =ENERO!BA42 -> 5486.7956 | S43: =(320*0.16+320)*E43 -> 2598.4 | AX43: =SUM(H43+S43+T43-U43-V43-W43-X43-Y43-Z43-AA43-AB43-AC43-AD43-AE43-AF43-AG43-AH43-AI43-AJ43-AK43-AL43-AM43-AN43-AO43-AP43-AQ43-AR43-AS43-AT43-AU43-AV43-AW43) -> 8085.1956
A44: 27 | B44: FINXERT - FERNANDO VILLARREAL | D44: Fernando Villarreal - 81 2348 6430 | E44: 4 | G44: =[1]DICIEMBRE!$BA$45 -> 0 | H44: =ENERO!BA43 -> 0.0012 | S44: =(290*0.16+290)*E44+(405.99*0.16+405.99) -> 1816.5484 | T44: =4400*0.16+4400 -> 5104 | AB44: 6920.55 | AX44: =SUM(H44+S44+T44-U44-V44-W44-X44-Y44-Z44-AA44-AB44-AC44-AD44-AE44-AF44-AG44-AH44-AI44-AJ44-AK44-AL44-AM44-AN44-AO44-AP44-AQ44-AR44-AS44-AT44-AU44-AV44-AW44) -> -0.0004 | AY44: COB. FEB'25: 2 EQP. Y 3 MENS. PROP. 21 DIAS, 13 DIAS Y 8 DIAS
A45: 28 | B45: FLETES ESPECIALIZADOS AGL | D45: COMODATO Sr. Ariel - 81 1974 2676 fletesagl@gmail.com | E45: 18 | F45: JOSE LUIS | G45: =[1]DICIEMBRE!$BA$46 -> 9.094947e-13 | H45: =ENERO!BA44 -> 9.094947e-13 | S45: =(300*0.16+300)*E45+(380*0.16+380) -> 6704.8 | T45: =1537.2*0.16+1537.2 -> 1783.152 | AB45: 8487.95 | AX45: =SUM(H45+S45+T45-U45-V45-W45-X45-Y45-Z45-AA45-AB45-AC45-AD45-AE45-AF45-AG45-AH45-AI45-AJ45-AK45-AL45-AM45-AN45-AO45-AP45-AQ45-AR45-AS45-AT45-AU45-AV45-AW45) -> 0.002 | AY45: COB. FEB'25: 4 INST. Y 4 MENS. PROP. 23, 6 Y 3 DIAS
A46: 29 | B46: FREIGHT HP-PACK MEXICO (DAVID FRANCISCO ARCOS) | D46: COMODATO Carlos Salinas - (201) 748 9020 David Francisco - 81 1033 1916 davidarcosfrancisco1991@gmail.com | E46: 19 | F46: JOSE LUIS | H46: =ENERO!BA45 -> 9604.8 | S46: =1190.4*0.16+1190.4 -> 1380.864 | V46: 9604.8 | AX46: =SUM(H46+S46+T46-U46-V46-W46-X46-Y46-Z46-AA46-AB46-AC46-AD46-AE46-AF46-AG46-AH46-AI46-AJ46-AK46-AL46-AM46-AN46-AO46-AP46-AQ46-AR46-AS46-AT46-AU46-AV46-AW46) -> 1380.864 | AY46: COB. FEB'25: 9 MENS. PROP. COBRAR EN MARZO MENS. COMPL. DE LAS PRIMERAS 19 UNIDADES
A47: 30 | B47: GEORGINA MELISSA GOMEZ RODELA - PETROVACTOR | C47: Nombre de la Empresa: GEORGINA MELISSA GOMEZ RODELA RFC.: GORG8204295H5 CFDI: Gastos en General Forma de Pago: Transferencia Teléfono: 833 104 3672 Gisela Suarez - 81 1049 7882 Contacto: Griselda Suarez (Petrovactor) Email: griselda@petrovactor.com; facturagmgr@gmail.com; | D47: Georgina Gomez - 833 134 5812 Anahí Juarez - 833 104 3672 Email:facturagmgr@gmail.com; anaiwork7@gmail.com | E47: 14 | F47: JOSE LUIS | G47: =[1]DICIEMBRE!$BA$50 -> -0.0004 | H47: =ENERO!BA46 -> -0.0004 | S47: =(250*0.16+250)*E47 -> 4060 | AE47: 4060 | AX47: =SUM(H47+S47+T47-U47-V47-W47-X47-Y47-Z47-AA47-AB47-AC47-AD47-AE47-AF47-AG47-AH47-AI47-AJ47-AK47-AL47-AM47-AN47-AO47-AP47-AQ47-AR47-AS47-AT47-AU47-AV47-AW47) -> -0.0004
A48: 31 | B48: GRUPO CASTOR ACERTIVA CONSTRUCCIONES, S.A. DE C.V. (CASTOR) | C48: Nombre de la Empresa: ACERTIVA CONTRUCCIONES S.A. DE C.V. RFC. ACO9605025G2 CFDI: Comunicaciones Satelitales Forma de Pago: Transferencia Teléfono: 818 347 7712 / 13 ext. 106 Contacto: Sr. Santos / Srta.(s) Janeth Villa / Karla Guerra / Fabiola García Email: fabiola.garcia@lsadministracion.com | D48: Srta. Janeth Villa 81 8347 7712 / 13 Ext. 106 Email:fabiola.garcia@lsadministracion.com; | E48: 1 | F48: JOSE LUIS | G48: =[1]DICIEMBRE!$BA$52 -> 0 | H48: =ENERO!BA47 -> 0 | S48: 348 | AB48: 348 | AX48: =SUM(H48+S48+T48-U48-V48-W48-X48-Y48-Z48-AA48-AB48-AC48-AD48-AE48-AF48-AG48-AH48-AI48-AJ48-AK48-AL48-AM48-AN48-AO48-AP48-AQ48-AR48-AS48-AT48-AU48-AV48-AW48) -> 0
A49: 32 | B49: GRUPO CASTOR ORGANIZACIÓN CASTOR AG, S.A. DE C.V. | C49: Nombre de la Empresa: ORGANIZACIÓN CASTOR S. A. DE C. V. RFC. OCA121001RX9 CFDI: Comunicaciones Satelitales Forma de Pago: Transferencia Teléfono: 818 347 7712 / 13 ext. 106 Contacto: Sr. Santos / Srta.(s) Janeth Villa / Karla Guerra / Fabiola García Email: fabiola.garcia@lsadministracion.com | D49: Srta. Janeth Villa 81 8347 7712 / 13 Ext. 106 Email:fabiola.garcia@lsadministracion.com; | E49: 2 | F49: JOSE LUIS | G49: =[1]DICIEMBRE!$BA$53 -> 0 | H49: =ENERO!BA48 -> 0 | S49: 696 | AB49: 696 | AX49: =SUM(H49+S49+T49-U49-V49-W49-X49-Y49-Z49-AA49-AB49-AC49-AD49-AE49-AF49-AG49-AH49-AI49-AJ49-AK49-AL49-AM49-AN49-AO49-AP49-AQ49-AR49-AS49-AT49-AU49-AV49-AW49) -> 0
A50: 33 | B50: GREGORY AJMEL MARTINEZ GARCIA (TEOURO TRANSPORTES) | D50: COMODATO Gregory Martínez García 81 1041 6798 greck_090@hotmail.com | E50: 3 | F50: JOSE LUIS | G50: =[1]DICIEMBRE!$BA$54 -> 0 | H50: =ENERO!BA49 -> 0 | S50: =(300*0.16+300)*E50 -> 1044 | AB50: 1044 | AX50: =SUM(H50+S50+T50-U50-V50-W50-X50-Y50-Z50-AA50-AB50-AC50-AD50-AE50-AF50-AG50-AH50-AI50-AJ50-AK50-AL50-AM50-AN50-AO50-AP50-AQ50-AR50-AS50-AT50-AU50-AV50-AW50) -> 0
A51: 34 | B51: GRUPO AMBIENTAL Y RESIDUOS INDUSTRIALES S.A. DE C. V. (GARISA) | C51: Nombre de la Empresa: GRUPO AMBIENTAL Y RESIDUOS INDUSTRIALES S.A. DE C.V. RFC.: GAR1503063C1 CFDI: Gastos en General. Forma de Pago: Transferencia Electrónica Contacto: Verónica Coronado Teléfono: 812 165 1133 / 8119575404 Email: garisav@hotmail.com | D51: Veronica Coronado- 812 165 1133 / 811 957 5404 Email:garisav@hotmail.com | E51: 3 | F51: JOSE LUIS | G51: =[1]DICIEMBRE!$BA$49 -> 0 | H51: =ENERO!BA50 -> 0 | S51: =(300*0.16+300)*E51 -> 1044 | AE51: 1044 | AX51: =SUM(H51+S51+T51-U51-V51-W51-X51-Y51-Z51-AA51-AB51-AC51-AD51-AE51-AF51-AG51-AH51-AI51-AJ51-AK51-AL51-AM51-AN51-AO51-AP51-AQ51-AR51-AS51-AT51-AU51-AV51-AW51) -> 0
A52: 35 | B52: GRUPO DIESEL HH | D52: Marisol Alvarado - 33 3486 8750 / Norma Navarro Oficina - 33 1401 2246 33 1654 3312 Email:azulitalia@live.com.mx | E52: 4 | F52: JOSE LUIS | G52: =[1]DICIEMBRE!$BA$56 -> 0 | H52: =ENERO!BA51 -> 0 | S52: =(300*0.16+300)*E52 -> 1392 | Y52: 1392 | AX52: =SUM(H52+S52+T52-U52-V52-W52-X52-Y52-Z52-AA52-AB52-AC52-AD52-AE52-AF52-AG52-AH52-AI52-AJ52-AK52-AL52-AM52-AN52-AO52-AP52-AQ52-AR52-AS52-AT52-AU52-AV52-AW52) -> 0
A53: 36 | B53: HACIENDO EQUIPO EN TU PROYECTO - EQUIPREST | C53: Nombre de la Empresa: HACIENDO EQUIPO EN TU PROYECTO S.A. DE C.V. RFC. EMO180713MC1 CFDI : Gastos en General C.P.: 64000 Regimen Fiscal: R SIMPLIFICADO DE CONFIANZA Forma de Pago: Transferencia Teléfono: 81 2002 4556 Contacto: Oscar Herrera Email:compras@equiprestmx.com 1er Factura: 1951 | D53: Karla - 81 2002 4556 Email:administracion@equiprestmx.com | E53: 3 | F53: JOSE LUIS | G53: =[1]DICIEMBRE!$BA$39 -> 9.094947e-13 | H53: =ENERO!BA52 -> 9.094947e-13 | S53: =(250*0.16+250)*E53 -> 870 | AE53: 870 | AX53: =SUM(H53+S53+T53-U53-V53-W53-X53-Y53-Z53-AA53-AB53-AC53-AD53-AE53-AF53-AG53-AH53-AI53-AJ53-AK53-AL53-AM53-AN53-AO53-AP53-AQ53-AR53-AS53-AT53-AU53-AV53-AW53) -> 9.094947e-13
A54: 37 | B54: HECTOR ALVEAR AGUILAR - KARLA ALVEAR | C54: Nombre de la Empresa: HECTOR ALVEAR AGUILAR RFC. AEAH940117AV1 CFDI : Gastos en General C.P.:67250 Regimen Fiscal: R DE LAS PERSONAS FISICAS CON ACTIVIDADES EMPRESARIALES Y PROFESIONALES Forma de Pago: Transferencia Teléfono: 81 8050 5722 Contacto: Karla Vear Email: Hec_alvear@hotmail.com 1er Factura: 2068 | D54: Karla Alvear - 81 1800 0233 Email:Hec_alvear@hotmail.com | E54: 1 | F54: JOSE LUIS | G54: =[1]DICIEMBRE!$BA$67 -> 0 | H54: =ENERO!BA53 -> 0 | S54: =(300*0.16+300)*E54 -> 348 | AE54: 348 | AX54: =SUM(H54+S54+T54-U54-V54-W54-X54-Y54-Z54-AA54-AB54-AC54-AD54-AE54-AF54-AG54-AH54-AI54-AJ54-AK54-AL54-AM54-AN54-AO54-AP54-AQ54-AR54-AS54-AT54-AU54-AV54-AW54) -> 0
A55: 38 | B55: INDUSTRIAL DE CARBON Y GRAFITO - CARBOGRAF | C55: Nombre de la Empresa: INDUSTRIAL DE CARBON Y GRAFITO, S.A. DE C.V. RFC: ICG 100106 UR0 CFDI: Gastos en general TEL: 16 42 2004 Contacto: Pablo Rodriguez Email: Elda@carbograf.com | D55: Daniela Cabello - 81 8273 6437 Email:julio.campos@carbograf.com marlene@carbograf.com | E55: 4 | F55: JOSE LUIS | G55: =[1]DICIEMBRE!$BA$26 -> 0.0032 | H55: =ENERO!BA54 -> 0.0032 | S55: =(349*0.16+349)*E55 -> 1619.36 | AH55: 1619.36 | AX55: =SUM(H55+S55+T55-U55-V55-W55-X55-Y55-Z55-AA55-AB55-AC55-AD55-AE55-AF55-AG55-AH55-AI55-AJ55-AK55-AL55-AM55-AN55-AO55-AP55-AQ55-AR55-AS55-AT55-AU55-AV55-AW55) -> 0.0032
A56: 39 | B56: INDUSTRIAS PERSISTA LABORO S.A. DE C.V. (ERNESTO GOMEZ) | D56: COMODATO Ernesto Gómez - 81 2001 9256 ernesto.gomez@sanbox.com.mx | E56: 13 | F56: JOSE LUIS | G56: =[1]DICIEMBRE!$BA$58 -> 1525.0064 | H56: =ENERO!BA55 -> -0.0036 | S56: =(250*0.16+250)*E56 -> 3770 | T56: =549*0.16+549 -> 636.84 | Y56: 4406.84 | AX56: =SUM(H56+S56+T56-U56-V56-W56-X56-Y56-Z56-AA56-AB56-AC56-AD56-AE56-AF56-AG56-AH56-AI56-AJ56-AK56-AL56-AM56-AN56-AO56-AP56-AQ56-AR56-AS56-AT56-AU56-AV56-AW56) -> -0.0036 | AY56: COB. FEB'25: 1 INST. NUEVA
A57: 40 | B57: INVERSIONES QUINEXUS - PRESTACOCHE (FINANCIERA) | C57: Nombre de la Empresa: PRESTACOCHE Contacto: Rosy / Talía Carrizales Email: rosa.sr@quinexus.mx; talia.ci@quinexus.mx; Teléfono: 811 499 1431 / 812 147 3082 | D57: Rosy - 812 354 1373 Email:rosa.sr@quinexus.mx; | E57: 7 | F57: JOSE LUIS | G57: =[1]DICIEMBRE!$BA$85 -> 0.0048 | H57: =ENERO!BA56 -> 0.0048 | S57: =(220*0.16+220)*E57 -> 1786.4 | T57: =1950*0.16+1950 -> 2262 | AB57: 4048.4 | AX57: =SUM(H57+S57+T57-U57-V57-W57-X57-Y57-Z57-AA57-AB57-AC57-AD57-AE57-AF57-AG57-AH57-AI57-AJ57-AK57-AL57-AM57-AN57-AO57-AP57-AQ57-AR57-AS57-AT57-AU57-AV57-AW57) -> 0.0048 | AY57: COB. FEB'25: 3 DES-INST.
A58: 41 | B58: JAVIER ANGEL VELAZQUEZ SANCHEZ | C58: Nombre de la Empresa: JAVIER ANGEL VELAZQUEZ SANCHEZ RFC. VESJ4910026E3 CFDI: Comunicaciones satelitales Forma de Pago: Transferencia Teléfono: 812 032 0493 Contacto: Javier Ángel Velázquez Sánchez (FLETES ANGEL VELAZQUEZ) Email: fletesangelvelazquez@gmail.com | D58: Javier Velazquez - 812 032 0493 Email:fletesangelvelazquez@gmail.com | E58: 4 | F58: JOSE LUIS | G58: =[1]DICIEMBRE!$BA$60 -> -0.0048 | H58: =ENERO!BA57 -> -0.0048 | S58: =(330*0.16+330)*E58 -> 1531.2 | AA58: 1531.2 | AX58: =SUM(H58+S58+T58-U58-V58-W58-X58-Y58-Z58-AA58-AB58-AC58-AD58-AE58-AF58-AG58-AH58-AI58-AJ58-AK58-AL58-AM58-AN58-AO58-AP58-AQ58-AR58-AS58-AT58-AU58-AV58-AW58) -> -0.0048
A59: 42 | B59: JESUS ALEJANDRO LOZANO LOZANO - TRANSPORTES TM | D59: ventas@autotransportes-jl.com administracion@autotransportes-jl.com | E59: 1 | F59: JOSE LUIS | G59: =[1]DICIEMBRE!$BA$100 -> 0 | H59: =ENERO!BA58 -> 0 | S59: =300*0.16+300 -> 348 | Y59: 348 | AX59: =SUM(H59+S59+T59-U59-V59-W59-X59-Y59-Z59-AA59-AB59-AC59-AD59-AE59-AF59-AG59-AH59-AI59-AJ59-AK59-AL59-AM59-AN59-AO59-AP59-AQ59-AR59-AS59-AT59-AU59-AV59-AW59) -> 0
A60: 43 | B60: JOSE ANGEL MENDEZ ARRIAGA - TRANSPORTES 2M | C60: Nombre de la Empresa: TRANSPORTES 2M Contacto: José Ángel Méndez Arriaga Teléfono: 812 600 8976 Email: jama_ca@hotmail.com | D60: Jose Angel Mendez Arriaga - 812 600 8976 Email:jama_ca@hotmail.com | E60: 4 | F60: JOSE LUIS | G60: =[1]DICIEMBRE!$BA$98 -> -6 | H60: =ENERO!BA59 -> -6 | S60: =(300*0.16+300)*E60 -> 1392 | AB60: 1386 | AX60: =SUM(H60+S60+T60-U60-V60-W60-X60-Y60-Z60-AA60-AB60-AC60-AD60-AE60-AF60-AG60-AH60-AI60-AJ60-AK60-AL60-AM60-AN60-AO60-AP60-AQ60-AR60-AS60-AT60-AU60-AV60-AW60) -> 0
A61: 44 | B61: JOSE MELQUIADES TOLEDO GARCIA DE LEON | D61: Jose Toledo - 81 1015 9453 Email:j.garcia@grupotranstech.com | E61: 2 | F61: JOSE LUIS | G61: =[1]DICIEMBRE!$BA$63 -> 2.2737368e-13 | H61: =ENERO!BA60 -> 2.2737368e-13 | S61: =(330*0.16+330)*E61 -> 765.6 | AA61: 765.6 | AX61: =SUM(H61+S61+T61-U61-V61-W61-X61-Y61-Z61-AA61-AB61-AC61-AD61-AE61-AF61-AG61-AH61-AI61-AJ61-AK61-AL61-AM61-AN61-AO61-AP61-AQ61-AR61-AS61-AT61-AU61-AV61-AW61) -> 2.2737368e-13
A62: 45 | B62: JUAN ANTONIO DE JESUS GARCIA RAMIREZ - TRANSPORTES GARCÍA | C62: Nombre de la Empresa: JUAN ANTONIO DE JESUS GARCIA RAMIREZ RFC. GARJ810921FM4 CFDI : Por Definir Forma de Pago: Transferencia Teléfono: 811 155 2769 Contacto: Antonio García Email: antoniotransgar@hotmail.es | D62: COMODATO Antonio García - 81 1155 2769 Email:antoniotransgar@hotmail.es | E62: 14 | F62: JOSE LUIS | G62: =[1]DICIEMBRE!$BA$99 -> 0.004 | H62: =ENERO!BA61 -> 4693.364 | S62: =(289*0.16+289)*E62 -> 4693.36 | AF62: 9386.72 | AX62: =SUM(H62+S62+T62-U62-V62-W62-X62-Y62-Z62-AA62-AB62-AC62-AD62-AE62-AF62-AG62-AH62-AI62-AJ62-AK62-AL62-AM62-AN62-AO62-AP62-AQ62-AR62-AS62-AT62-AU62-AV62-AW62) -> 0.004
A63: 46 | B63: JUAN JAVIER CABRIALES CEDILLO (TRANSPORTES RCD) | D63: Juan Cabriales - 81 2947 2650 Email:transportes.rcd.diaz@gmail.com | E63: 4 | F63: JOSE LUIS | G63: =[1]DICIEMBRE!$BA$65 -> -0.0004 | H63: =ENERO!BA63 -> -0.0004 | S63: =(300*0.16+300)*E63 -> 1392 | AA63: 1392 | AX63: =SUM(H63+S63+T63-U63-V63-W63-X63-Y63-Z63-AA63-AB63-AC63-AD63-AE63-AF63-AG63-AH63-AI63-AJ63-AK63-AL63-AM63-AN63-AO63-AP63-AQ63-AR63-AS63-AT63-AU63-AV63-AW63) -> -0.0004
A64: 47 | B64: JUAN MEJIA HERNANDEZ | D64: Juan Mejia - 44 2160 1772 mejiahj@hotmail.com | E64: 1 | F64: JOSE LUIS | G64: =[1]DICIEMBRE!$BA$66 -> 0 | H64: =ENERO!BA64 -> 0 | S64: =(200*0.16+200)*E64 -> 232 | T64: =650*0.16+650 -> 754 | AF64: 986 | AX64: =SUM(H64+S64+T64-U64-V64-W64-X64-Y64-Z64-AA64-AB64-AC64-AD64-AE64-AF64-AG64-AH64-AI64-AJ64-AK64-AL64-AM64-AN64-AO64-AP64-AQ64-AR64-AS64-AT64-AU64-AV64-AW64) -> 0 | AY64: COB. FEB'25: 1 CAMBIO DE SIM
A65: 48 | B65: K3 SOLUCIONES A LA INDUSTRIA ALIMENTICIA | D65: Susana Calvo - 81 1695 4703 proyectos3@serviciosk3.mx | E65: 1 | F65: JOSE LUIS | G65: =[1]DICIEMBRE!$BA$68 -> 0 | H65: =ENERO!BA65 -> 0 | S65: =(300*0.16+300)*E65 -> 348 | AA65: 348 | AX65: =SUM(H65+S65+T65-U65-V65-W65-X65-Y65-Z65-AA65-AB65-AC65-AD65-AE65-AF65-AG65-AH65-AI65-AJ65-AK65-AL65-AM65-AN65-AO65-AP65-AQ65-AR65-AS65-AT65-AU65-AV65-AW65) -> 0
A66: 49 | B66: KARLA ZEBETH CLEMENTINA PEÑA MACIAS (EDUARDO ALMAGUER) | D66: Eduardo Almaguer - 81 2920 4044 abelardoalmaguer1991@gmail.com | E66: 1 | F66: JOSE LUIS | G66: =[1]DICIEMBRE!$BA$69 -> 0 | H66: =ENERO!BA66 -> 0 | S66: =(250*0.16+250)*E66 -> 290 | AF66: 290 | AX66: =SUM(H66+S66+T66-U66-V66-W66-X66-Y66-Z66-AA66-AB66-AC66-AD66-AE66-AF66-AG66-AH66-AI66-AJ66-AK66-AL66-AM66-AN66-AO66-AP66-AQ66-AR66-AS66-AT66-AU66-AV66-AW66) -> 0
A67: 50 | B67: KROHNE DE MEXICO | C67: Nombre de la Empresa: KROHNE DE MEXICO RFC. KME091130LY6 CFDI : Gastos en General C.P.89110 Regimen Fiscal: R GENERAL DE LEY PERSONAS MORALES Forma de Pago: Transferencia Teléfono: (833) 217-3830 Contacto: Email: Pamela@KROHNEMEXICO.com 'erika@krohnemexico.com'; 'israel@krohnemexico.com'; 'maricela@krohnemexico.com' 1er Factura: 2070 | D67: (833) 217-3830 Ext. 101 Email:Pamela@KROHNEMEXICO.com 'erika@krohnemexico.com'; 'israel@krohnemexico.com'; 'maricela@krohnemexico.com' | E67: 19 | F67: JOSE LUIS | G67: =[1]DICIEMBRE!$BA$70 -> 0.002 | H67: =ENERO!BA67 -> 0.002 | S67: =(249*0.16+249)*E67 -> 5487.96 | Z67: 5487.96 | AX67: =SUM(H67+S67+T67-U67-V67-W67-X67-Y67-Z67-AA67-AB67-AC67-AD67-AE67-AF67-AG67-AH67-AI67-AJ67-AK67-AL67-AM67-AN67-AO67-AP67-AQ67-AR67-AS67-AT67-AU67-AV67-AW67) -> 0.002
A68: 51 | B68: LACAR ENERGY LOGISTIC - CARLOS MORENO | D68: Aylin Villanueva - 81 1240 3361 | E68: 4 | F68: JOSE LUIS | G68: =[1]DICIEMBRE!$BA$71 -> 0 | H68: =ENERO!BA68 -> 0 | S68: =(300*0.16+300)*E68+(280*0.16+280) -> 1716.8 | T68: =3600*0.16+3600 -> 4176 | Y68: 5892.8 | AX68: =SUM(H68+S68+T68-U68-V68-W68-X68-Y68-Z68-AA68-AB68-AC68-AD68-AE68-AF68-AG68-AH68-AI68-AJ68-AK68-AL68-AM68-AN68-AO68-AP68-AQ68-AR68-AS68-AT68-AU68-AV68-AW68) -> 0 | AY68: COB. FEB'25: 2 EQP. Y 2 MENS. PROP. 14 DIAS
A69: 52 | B69: LAMBI | C69: Nombre de la Empresa: LAMBI S.A. DE C.V. RFC. LAM9109013H1 CFDI : Gastos en General C.P.66062 Regimen Fiscal: R GENERAL DE LEY PERSONAS MORALES Forma de Pago: Transferencia Teléfono: 81 1908 0591 Contacto: Ericka Ortega Email: eortega@lambi.com.mx 1er Factura: 2008 | D69: Ericka Ortega (Compras) - 81 1908 0591 Email:trafico@lambi.com.mx jrojas@lambi.com.mx dquijas@lambi.com.mx | E69: 2 | F69: JOSE LUIS | G69: =[1]DICIEMBRE!$BA$72 -> -0.008 | H69: =ENERO!BA69 -> -0.008 | S69: =(249*0.16+249)*E69 -> 577.68 | AH69: 577.67 | AX69: =SUM(H69+S69+T69-U69-V69-W69-X69-Y69-Z69-AA69-AB69-AC69-AD69-AE69-AF69-AG69-AH69-AI69-AJ69-AK69-AL69-AM69-AN69-AO69-AP69-AQ69-AR69-AS69-AT69-AU69-AV69-AW69) -> 0.002
A70: 53 | B70: LEMURA VIVIENDA | C70: Nombre de la Empresa: LEMURA VIVIENDA S.A. DE C.V. RFC. LVI170630MEA CFDI: Gastos en general Forma de Pago: Transferencia Teléfono: 81 1624 4288 Contacto: Ignacio Gaxiola Email: igaxiola@lemura.com.mx | D70: Ignacio Gaxiola - 81 1624 4288 Email:igaxiola@lemura.com.mx | E70: 1 | F70: JOSE LUIS | G70: =[1]DICIEMBRE!$BA$73 -> -866.52 | H70: =ENERO!BA70 -> -577.68 | S70: =(249*0.16+249)*E70 -> 288.84 | AX70: =SUM(H70+S70+T70-U70-V70-W70-X70-Y70-Z70-AA70-AB70-AC70-AD70-AE70-AF70-AG70-AH70-AI70-AJ70-AK70-AL70-AM70-AN70-AO70-AP70-AQ70-AR70-AS70-AT70-AU70-AV70-AW70) -> -288.84 | AY70: PAGO 6 MENSUALIDADES ADELANTADAS COBRAR HASTA ABRIL 2025
A71: 54 | B71: LUIS ALBERTO DAVILA SALAZAR | C71: Nombre de la Empresa: LUIS ALBERTO DÁVILA SALAZAR RFC. DASL701219TM3 CFDI: Gastos en general Forma de Pago: Transferencia Teléfono: 813 074 5638 Contacto: Luis Dávila Email: luisdavila1970@gmail.com; luis.davila@alsglobal.com | D71: Luis Davila - 813 074 5638 Email:luisdavila1970@gmail.com | E71: 1 | F71: JOSE LUIS | G71: =[1]DICIEMBRE!$BA$74 -> 0 | H71: =ENERO!BA71 -> 0 | S71: 348 | AB71: 348 | AX71: =SUM(H71+S71+T71-U71-V71-W71-X71-Y71-Z71-AA71-AB71-AC71-AD71-AE71-AF71-AG71-AH71-AI71-AJ71-AK71-AL71-AM71-AN71-AO71-AP71-AQ71-AR71-AS71-AT71-AU71-AV71-AW71) -> 0
A72: 55 | B72: LUIS JAVIER GONZALEZ PEREZ | C72: Nombre de la Empresa: LUIS JAVIER GONZALEZ PEREZ RFC. GOPL9105308A6 CFDI: Gastos en general Forma de Pago: Transferencia Teléfono: 811 907 9148 Contacto: Luis Javier Gonzalez Email: ljgonzalez3591@gmail.com | D72: Luis Javier Gonzalez Perez - 811 907 9148 Email:ljgonzalez3591@gmail.com | E72: 1 | F72: JOSE LUIS | G72: =[1]DICIEMBRE!$BA$76 -> 0 | H72: =ENERO!BA72 -> 0 | S72: =(300*0.16+300)*E72 -> 348 | AE72: 348 | AX72: =SUM(H72+S72+T72-U72-V72-W72-X72-Y72-Z72-AA72-AB72-AC72-AD72-AE72-AF72-AG72-AH72-AI72-AJ72-AK72-AL72-AM72-AN72-AO72-AP72-AQ72-AR72-AS72-AT72-AU72-AV72-AW72) -> 0
A73: 56 | B73: MARINE DEL VALLE MENDOZA PEREZ - EDUARDO VENTURA MENDOZA | D73: Marine Mexico - 81 1994 9256 Eduardo Ventura - 81 3090 4628 Email:mendozael2003@yahoo.com | E73: 11 | F73: JOSE LUIS | G73: =[1]DICIEMBRE!$BA$36 -> 0.0012 | H73: =ENERO!BA73 -> -0.0076 | S73: =(250*0.16+250)*E73 -> 3190 | Z73: 3189.99 | AX73: =SUM(H73+S73+T73-U73-V73-W73-X73-Y73-Z73-AA73-AB73-AC73-AD73-AE73-AF73-AG73-AH73-AI73-AJ73-AK73-AL73-AM73-AN73-AO73-AP73-AQ73-AR73-AS73-AT73-AU73-AV73-AW73) -> 0.0024
A74: 57 | B74: MARIO ALBERTO CABALLERO GARZA | D74: Mario Caballero - 81 1213 3136 | E74: 3 | F74: JOSE LUIS | G74: =[1]DICIEMBRE!$BA$78 -> 0.0012 | H74: =ENERO!BA74 -> 0.0012 | S74: =(250*0.16+250)*E74 -> 870 | AC74: 870 | AX74: =SUM(H74+S74+T74-U74-V74-W74-X74-Y74-Z74-AA74-AB74-AC74-AD74-AE74-AF74-AG74-AH74-AI74-AJ74-AK74-AL74-AM74-AN74-AO74-AP74-AQ74-AR74-AS74-AT74-AU74-AV74-AW74) -> 0.0012
A75: 58 | B75: MARMOL Y GRANITO RIO - GERARDO NIETO | D75: Gerardo Nieto - 81 1184 1231 Email:fizz98@hotmail.com consueloer@marmolemperador.com | E75: 5 | F75: JOSE LUIS | G75: =[1]DICIEMBRE!$BA$51 -> 0 | H75: =ENERO!BA75 -> 0 | S75: =(300*0.16+300)*E75 -> 1740 | Z75: 1740 | AX75: =SUM(H75+S75+T75-U75-V75-W75-X75-Y75-Z75-AA75-AB75-AC75-AD75-AE75-AF75-AG75-AH75-AI75-AJ75-AK75-AL75-AM75-AN75-AO75-AP75-AQ75-AR75-AS75-AT75-AU75-AV75-AW75) -> 0
A76: 59 | B76: MARTINEZ & DE LA ROSA CONSTRUCCIONES - ANTONIO MARTINEZ | D76: COMODATO Brenda Araujo - 81 3421 7089 Ing. Antonio Martínez -81 1537 7636 Email:facturas@myrconsa.mx catalinac@myrconsa.mx antoniomtz@myrconsa.mx | E76: 14 | F76: JOSE LUIS | G76: =[1]DICIEMBRE!$BA$22 -> -1.8189894e-12 | H76: =ENERO!BA76 -> -0.002 | S76: =(279*0.16+279)*E76 -> 4530.96 | Z76: 4530.96 | AX76: =SUM(H76+S76+T76-U76-V76-W76-X76-Y76-Z76-AA76-AB76-AC76-AD76-AE76-AF76-AG76-AH76-AI76-AJ76-AK76-AL76-AM76-AN76-AO76-AP76-AQ76-AR76-AS76-AT76-AU76-AV76-AW76) -> -0.002
A77: 60 | B77: MCJ CHILLER - EVERARDO NUNCIO CUELLAR | D77: COMODATO Everardo Nuncio - 81 1823 3384 Pagos Brenda Ocañas - 81 7654 2904/81 18 72 2728 Email:oficina@mcjchillerservice.com | E77: 9 | F77: JOSE LUIS | G77: =[1]DICIEMBRE!$BA$40 -> 0.0004 | H77: =ENERO!BA77 -> 0.0004 | S77: =(269*0.16+269)*E77 -> 2808.36 | T77: =500*0.16+500 -> 580 | Z77: 3388.36 | AX77: =SUM(H77+S77+T77-U77-V77-W77-X77-Y77-Z77-AA77-AB77-AC77-AD77-AE77-AF77-AG77-AH77-AI77-AJ77-AK77-AL77-AM77-AN77-AO77-AP77-AQ77-AR77-AS77-AT77-AU77-AV77-AW77) -> 0.0004 | AY77: COB. FEB'25: 1 RE-INST.
A78: 61 | B78: MIGUEL EDUARDO CASAS ARIZMENDI - MIGUEL ANGEL CASAS | C78: Nombre de la Empresa: MIGUEL EDUARDO CASAS ARIZMENDI RFC.: CAAM980824PA1 CFDI: Por Definir Forma de Pago: TransferenciaTeléfono: 811 418 8880 Contacto: Nidia Arizmendi Email: mactransportacion@gmail.com | D78: COMODATO Miguel Angel Casas - 811 566 5492 Email:mactransportacion@gmail.com | E78: 17 | F78: JOSE LUIS | H78: =ENERO!BA78 -> 0 | S78: =(289*0.16+289)*E78 -> 5699.08 | T78: =856.86*0.16+856.86 -> 993.9576 | AW78: 6693.04 | AX78: =SUM(H78+S78+T78-U78-V78-W78-X78-Y78-Z78-AA78-AB78-AC78-AD78-AE78-AF78-AG78-AH78-AI78-AJ78-AK78-AL78-AM78-AN78-AO78-AP78-AQ78-AR78-AS78-AT78-AU78-AV78-AW78) -> -0.0024 | AY78: COB. FEB'25: 2 INST. NUEVAS Y 2 MENS. PROP. 7 DIAS
A79: 62 | B79: MYA TRANSPORTES, S.A. DE C.V. (MOLIENDAS Y ALIMENTOS) | C79: Nombre de la Empresa: MYA TRANSPORTES S.A. DE C.V. RFC. MTR0705245M3 CFDI: Por definir Forma de Pago: Cheque Bancario Teléfono: 81 8351 8283 Contacto: Srta. Elizabeth Garza / Sr. (s) Eduardo Garza / Emeterio Vargas. Email: administracion@myatsa.com; evargas@moliendas.com; egarza@moliendas.com; garzacavazos@hotmail.com, | D79: COMODATO Elizabeth Garza - 81 8351 8283 ext.126 Eduardo Garza / Emeterio Vargas Email:administracion@myatsa.com; evargas@moliendas.com; egarza@moliendas.com; garzacavazos@hotmail.com | E79: 16 | F79: DANIEL ESTRADA | G79: =[1]DICIEMBRE!$BA$81 -> -0.0012 | H79: =ENERO!BA79 -> -0.0012 | S79: =(5250+300)*0.16+5250+300 -> 6438 | AV79: 6438 | AX79: =SUM(H79+S79+T79-U79-V79-W79-X79-Y79-Z79-AA79-AB79-AC79-AD79-AE79-AF79-AG79-AH79-AI79-AJ79-AK79-AL79-AM79-AN79-AO79-AP79-AQ79-AR79-AS79-AT79-AU79-AV79-AW79) -> -0.0012 | AY79: JOSE LUIS CONFIRMA DEPOSITO
A80: 63 | B80: NORMA LETICIA GONZALEZ VAZQUEZ (AARON ARRATIA AGUILAR) | D80: COMODATO Aaron Arratia Aguilar - 81 2339 0793 aaronarratiaaguilarisamel12@gmail.com | E80: 5 | F80: JOSE LUIS | G80: =[1]DICIEMBRE!$BA$119 -> -0.02 | H80: =ENERO!BA123 -> -0.02 | S80: =(300*0.16+300)*E80 -> 1740 | T80: =1647*0.16+1647 -> 1910.52 | Y80: 3650.5 | AX80: =SUM(H80+S80+T80-U80-V80-W80-X80-Y80-Z80-AA80-AB80-AC80-AD80-AE80-AF80-AG80-AH80-AI80-AJ80-AK80-AL80-AM80-AN80-AO80-AP80-AQ80-AR80-AS80-AT80-AU80-AV80-AW80) -> 0 | AY80: COB. FEB'25: 3 INST. NUEVAS, CAMBIA A ESQUEMA DE FACTURACION 05-FEBRERO-2025
A81: 64 | B81: PABLO EMILIANO RODRIGUEZ DURAN | D81: COMODATO Pablo Rodriguez - 81 2010 3744 pablordzmasper@hotmail.com | E81: 2 | F81: JOSE LUIS | G81: =[1]DICIEMBRE!$BA$83 -> 0 | H81: =ENERO!BA80 -> 0 | S81: =(300*0.16+300)*E81 -> 696 | AI81: 696 | AX81: =SUM(H81+S81+T81-U81-V81-W81-X81-Y81-Z81-AA81-AB81-AC81-AD81-AE81-AF81-AG81-AH81-AI81-AJ81-AK81-AL81-AM81-AN81-AO81-AP81-AQ81-AR81-AS81-AT81-AU81-AV81-AW81) -> 0
A82: 65 | B82: PACKET CAR DE MONTERREY - PABLO ERNESTO CADENA ACEVEDO | C82: Nombre de la Empresa: PACKET CAR DE MONTERREY S.A. DE C.V. RFC. PCM200703M63 CFDI: Por definir Forma de Pago: Transferencia Teléfono: 811 722 2636 Contacto: Pablo Ernesto Cadena Acevedo Email: docrem@hotmail.com | D82: Pablo E. Cadena Acevedo - 811 722 2636 Email:docrem@hotmail.com | E82: 8 | F82: JOSE LUIS | G82: =[1]DICIEMBRE!$BA$82 -> 2784.0048 | H82: =ENERO!BA81 -> 0.0048 | S82: =(300*0.16+300)*E82 -> 2784 | AB82: 2784 | AX82: =SUM(H82+S82+T82-U82-V82-W82-X82-Y82-Z82-AA82-AB82-AC82-AD82-AE82-AF82-AG82-AH82-AI82-AJ82-AK82-AL82-AM82-AN82-AO82-AP82-AQ82-AR82-AS82-AT82-AU82-AV82-AW82) -> 0.0048
A83: 66 | B83: PREFOM | D83: COMODATO Hugo Díaz - 81 1290 4608 admin@bloquerafbk.com | E83: 4 | F83: JOSE LUIS | G83: =[1]DICIEMBRE!$BA$84 -> 0 | H83: =ENERO!BA82 -> 0 | S83: =(220*0.16+220)*E83 -> 1020.8 | AE83: 1020.8 | AX83: =SUM(H83+S83+T83-U83-V83-W83-X83-Y83-Z83-AA83-AB83-AC83-AD83-AE83-AF83-AG83-AH83-AI83-AJ83-AK83-AL83-AM83-AN83-AO83-AP83-AQ83-AR83-AS83-AT83-AU83-AV83-AW83) -> 0
A84: 67 | B84: QUITAKILOS | D84: Myrian Guerra - 811 636 1249 81 8359 4400 Email:facturacion@quitakilos.com adriana@quitakilos.com | E84: 3 | F84: JOSE LUIS | G84: =[1]DICIEMBRE!$BA$87 -> -0.0044 | H84: =ENERO!BA84 -> -0.0044 | S84: =(250*0.16+250)*E84 -> 870 | AB84: 870 | AX84: =SUM(H84+S84+T84-U84-V84-W84-X84-Y84-Z84-AA84-AB84-AC84-AD84-AE84-AF84-AG84-AH84-AI84-AJ84-AK84-AL84-AM84-AN84-AO84-AP84-AQ84-AR84-AS84-AT84-AU84-AV84-AW84) -> -0.0044
A85: 68 | B85: RAUL MURO RODRIGUEZ - EDGAR MURO | D85: COMODATO Edgar Muro - 81 2255 3176 transportesmuro@hotmail.com | E85: 3 | F85: JOSE LUIS | G85: =[1]DICIEMBRE!$BA$88 -> 4.5474735e-13 | H85: =ENERO!BA85 -> 4.5474735e-13 | S85: =(300*0.16+300)*E85 -> 1044 | AE85: 1044 | AX85: =SUM(H85+S85+T85-U85-V85-W85-X85-Y85-Z85-AA85-AB85-AC85-AD85-AE85-AF85-AG85-AH85-AI85-AJ85-AK85-AL85-AM85-AN85-AO85-AP85-AQ85-AR85-AS85-AT85-AU85-AV85-AW85) -> 4.5474735e-13
A86: 69 | B86: RAYAS SERVICIOS Y DESARROLLOS INTEGRALES | D86: Cristel del Rio - 844 380 0154 Alfonso - 81 3643 2962 Email:alonsogaspar578@gmail.com | E86: 5 | F86: JOSE LUIS | G86: =[1]DICIEMBRE!$BA$89 -> 0 | H86: =ENERO!BA86 -> 0 | S86: =(300*0.16+300)*E86 -> 1740 | AC86: 1740 | AX86: =SUM(H86+S86+T86-U86-V86-W86-X86-Y86-Z86-AA86-AB86-AC86-AD86-AE86-AF86-AG86-AH86-AI86-AJ86-AK86-AL86-AM86-AN86-AO86-AP86-AQ86-AR86-AS86-AT86-AU86-AV86-AW86) -> 0
A87: 70 | B87: ROBERTO CARLOS AVILA GUZMAN | D87: COMODATO Roberto Avila - 81 8088 2340 fletes-avila@hotmail.com | E87: 8 | F87: JOSE LUIS | G87: =[1]DICIEMBRE!$BA$90 -> 0 | H87: =ENERO!BA87 -> 0 | S87: =(300*0.16+300)*E87 -> 2784 | AC87: 2784 | AX87: =SUM(H87+S87+T87-U87-V87-W87-X87-Y87-Z87-AA87-AB87-AC87-AD87-AE87-AF87-AG87-AH87-AI87-AJ87-AK87-AL87-AM87-AN87-AO87-AP87-AQ87-AR87-AS87-AT87-AU87-AV87-AW87) -> 0
A88: 71 | B88: RODRIGO MORENO VILLARREAL | D88: COMODATO Rodrigo Moreno - 81 1410 4886 | E88: 3 | F88: JOSE LUIS | G88: =[1]DICIEMBRE!$BA$92 -> 0 | H88: =ENERO!BA88 -> 0 | S88: =(300*0.16+300)*E88 -> 1044 | AF88: 1044 | AX88: =SUM(H88+S88+T88-U88-V88-W88-X88-Y88-Z88-AA88-AB88-AC88-AD88-AE88-AF88-AG88-AH88-AI88-AJ88-AK88-AL88-AM88-AN88-AO88-AP88-AQ88-AR88-AS88-AT88-AU88-AV88-AW88) -> 0
A89: 72 | B89: SEI ARQUITECTOS - DANIELA OCHOA | D89: Contacto: Nohemi Montemayor Teléfono: 81 1495 0269 Email:daniela.ochoa@seiarquitectos.com claudia.martinez@seiarquitectos.com: | E89: 2 | F89: JOSE LUIS | G89: =[1]DICIEMBRE!$BA$33 -> 0.0012 | H89: =ENERO!BA89 -> 0.0012 | S89: =(250*0.16+250)*E89 -> 580 | AB89: 580 | AX89: =SUM(H89+S89+T89-U89-V89-W89-X89-Y89-Z89-AA89-AB89-AC89-AD89-AE89-AF89-AG89-AH89-AI89-AJ89-AK89-AL89-AM89-AN89-AO89-AP89-AQ89-AR89-AS89-AT89-AU89-AV89-AW89) -> 0.0012
A90: 73 | B90: SERGIO EDIÑHO ARRIAGA HERNANDEZ | D90: Contacto: Sergio Ediñho Arriaga Hdz Teléfono: 81 2402 5624 se.arriaga@hotmail.com | E90: 2 | H90: =166.66*0.16+166.66 -> 193.3256 | S90: =650*0.16+650 -> 754 | AE90: 947.33 | AX90: =SUM(H90+S90+T90-U90-V90-W90-X90-Y90-Z90-AA90-AB90-AC90-AD90-AE90-AF90-AG90-AH90-AI90-AJ90-AK90-AL90-AM90-AN90-AO90-AP90-AQ90-AR90-AS90-AT90-AU90-AV90-AW90) -> -0.0044 | AY90: COB. FEB'25: 1 REACTIVAION DE CUENTA Y SALDO PENDIENTE DE OCTUBRE 2024
A91: 74 | B91: SERVICIO DE ALMACENAMIENTO Y TRANSPORTE RG II - CESAR RODRIGUEZ (GP MET LOGISTICS) | D91: Contacto: Cesar Rodriguez Teléfono: 81 3088 0606 Proveedores@cbrlogistics.com cesar.rdz@cbrlogistics.com | E91: 5 | F91: JOSE LUIS | G91: =[1]DICIEMBRE!$BA$29 -> 2900 | H91: =ENERO!BA90 -> 4350 | S91: =(250*0.16+250)*E91 -> 1450 | AM91: 5800 | AX91: =SUM(H91+S91+T91-U91-V91-W91-X91-Y91-Z91-AA91-AB91-AC91-AD91-AE91-AF91-AG91-AH91-AI91-AJ91-AK91-AL91-AM91-AN91-AO91-AP91-AQ91-AR91-AS91-AT91-AU91-AV91-AW91) -> 0 | AY91: SE MIGRARA UNIDAD A CESAR RODRIGUEZ - ANTES GP MET LOGISTICS
A92: 75 | B92: SERVICIOS LOGISTICOS MARSEL - CLAUDIA LUNA GUTIERREZ TRANSMARSEL | C92: Nombre de la Empresa: CLAUDIA LUNA GUTIERREZ RFC. LUGC700301TKA CFDI: Comunicaciones satelitales Forma de Pago: Transferencia Teléfono: 811 155 5054 / 8183646871 Contacto: Sergio Leal / Jazmín Email: bazoon_300@hotmail.com; clg.lgc@hotmail.com; transportesmarsel@hotmail.com; | D92: Sergio Leal - 811 155 5054 Jazmín - 818 364 6871 Email:bazoon_300@hotmail.com; clg.lgc@hotmail.com; transportesmarsel@hotmail.com; | E92: 12 | F92: JOSE LUIS | G92: =[1]DICIEMBRE!$BA$30 -> 0 | H92: =ENERO!BA91 -> 0 | S92: =(250*0.16+250)*E92 -> 3480 | AA92: 3480 | AX92: =SUM(H92+S92+T92-U92-V92-W92-X92-Y92-Z92-AA92-AB92-AC92-AD92-AE92-AF92-AG92-AH92-AI92-AJ92-AK92-AL92-AM92-AN92-AO92-AP92-AQ92-AR92-AS92-AT92-AU92-AV92-AW92) -> 0
A93: 76 | B93: SH TRANSPORTACIONES DRP TRANSPORTES | C93: Nombre de la Empresa: DRP TRANSPORTES S. DE R. L. DE C.V. RFC.: DTR210720A25 CFDI : G03 Forma de Pago: Transferencia Teléfono: 81 1421 3083 Contacto: Francisco Sanchez Email: fsancheznoreste@hotmail.es | D93: Francisco Sanchez - 81 1421 3083 Email:fsancheznoreste@hotmail.es | E93: 4 | F93: JOSE LUIS | G93: =[1]DICIEMBRE!$BA$93 -> -0.0848 | H93: =ENERO!BA92 -> -0.0848 | S93: =(350*0.16+350)*E93 -> 1624 | T93: =1100*0.16+1100 -> 1276 | AF93: 2899.92 | AX93: =SUM(H93+S93+T93-U93-V93-W93-X93-Y93-Z93-AA93-AB93-AC93-AD93-AE93-AF93-AG93-AH93-AI93-AJ93-AK93-AL93-AM93-AN93-AO93-AP93-AQ93-AR93-AS93-AT93-AU93-AV93-AW93) -> -0.0048 | AY93: COB. FEB'25: 1 REVISION Y 1 REEMPLAZO DE EQP., CAMBIA COBRANZA EN CANTIDAD DE UNIDADES AHORA SE LE COBRARAN 4 A DRP Y 8 A JUAN FRANCISCO SANCHEZ
A94: 77 | B94: SH TRANSPORTACIONES JUAN FRANCISCO SANCHEZ CONTRERAS | C94: Nombre de la Empresa: JUAN FRANCISCO SANCHEZ CONTRERAS RFC.: SACJ7811022UA CFDI : G03 Forma de Pago: Transferencia Teléfono: 81 1421 3083 Contacto: Francisco Sanchez Email: fsancheznoreste@hotmail.es | D94: Francisco Sanchez - 81 1421 3083 Email:fsancheznoreste@hotmail.es | E94: 8 | F94: JOSE LUIS | G94: =[1]DICIEMBRE!$BA$94 -> -0.0088 | H94: =ENERO!BA93 -> -0.0088 | S94: =(350*0.16+350)*E94 -> 3248 | AF94: 3247.99 | AX94: =SUM(H94+S94+T94-U94-V94-W94-X94-Y94-Z94-AA94-AB94-AC94-AD94-AE94-AF94-AG94-AH94-AI94-AJ94-AK94-AL94-AM94-AN94-AO94-AP94-AQ94-AR94-AS94-AT94-AU94-AV94-AW94) -> 0.0012 | AY94: CAMBIA COBRANZA EN CANTIDAD DE UNIDADES AHORA SE LE COBRARAN 4 A DRP Y 8 A JUAN FRANCISCO SANCHEZ
A95: 78 | B95: SILVIA NERI SALAZAR - ACERTRANS | C95: Nombre de la Empresa: SILVIA NERI SALAZAR RFC.: NESS6001221GA CFDI: Gastos en general Forma de Pago: Transferencia Teléfono: 811 521 3582 / 811 044 7961 Contacto: Arturo Sifuentes / Silvia Neri Salazar Email: ventas@acertrans.com.mx; logisticasifal@hotmail.com; Silvia-neri@hotmail.com; | D95: Arturo Sifuentes - 811 521 3582 Silvia Neri Salazar - 811 044 7961 Email: silvia-neri@hotmail.com; ventas@acertrans.com.mx; logisticasifal@hotmail.com; | E95: 6 | F95: JOSE LUIS | G95: =[1]DICIEMBRE!$BA$19 -> 0 | H95: =ENERO!BA94 -> 0 | S95: =350*E95*0.16+350*E95 -> 2436 | T95: =1905*0.16+1905 -> 2209.8 | Z95: 4645.8 | AX95: =SUM(H95+S95+T95-U95-V95-W95-X95-Y95-Z95-AA95-AB95-AC95-AD95-AE95-AF95-AG95-AH95-AI95-AJ95-AK95-AL95-AM95-AN95-AO95-AP95-AQ95-AR95-AS95-AT95-AU95-AV95-AW95) -> 0 | AY95: COB. FEB'25: 1 EQP. E INST. NUEVA Y 1 MENS. PROP. 9 DIAS
A96: 79 | B96: SINDUSA SERVICIOS INDUSTRIALES – PABLO MORALES | D96: Pablo Morales - 81 3529 5622 | E96: 1 | H96: =ENERO!BA95 -> 0 | S96: =(249*0.16+249)*E96 -> 288.84 | Z96: 288.84 | AX96: =SUM(H96+S96+T96-U96-V96-W96-X96-Y96-Z96-AA96-AB96-AC96-AD96-AE96-AF96-AG96-AH96-AI96-AJ96-AK96-AL96-AM96-AN96-AO96-AP96-AQ96-AR96-AS96-AT96-AU96-AV96-AW96) -> 5.6843419e-14
A97: 80 | B97: SITELECOM SERVICIOS DE INGENIERIA Y TELECOMUNICACIONES | D97: COMODATO Anel - 773 132 8093 Fermin Uribe Ramos - 7732188379 Alejandro - 77 1393 3704 eber.sannicolas@sitelecom.lat | E97: 9 | F97: JOSE LUIS | G97: =[1]DICIEMBRE!$BA$95 -> 4.5474735e-13 | H97: =ENERO!BA96 -> 4.5474735e-13 | S97: =(300*0.16+300)*E97 -> 3132 | AB97: 3132 | AX97: =SUM(H97+S97+T97-U97-V97-W97-X97-Y97-Z97-AA97-AB97-AC97-AD97-AE97-AF97-AG97-AH97-AI97-AJ97-AK97-AL97-AM97-AN97-AO97-AP97-AQ97-AR97-AS97-AT97-AU97-AV97-AW97) -> 4.5474735e-13
A98: 81 | B98: TEGMESA S.A. DE C.V. - GRUAS TEGMESA | C98: Nombre de la Empresa: GRUAS TEGMESA S.A. DE C.V. RFC. GTE1602233N9 CFDI : Gastos en general Forma de Pago: Transferencia Teléfono: 81 1908 2914 Contacto: Julia Gonzalez Sosa Email: julia@construtecacero.com.mx | D98: COMODATO Raul Hernandez - 811 2422 086 Julia Graciela Gzz. Sosa - 811 9082 914 Email:gruastegmesa@construtecacero.com.mx julia@construtecacero.com.mx | E98: 13 | F98: JOSE LUIS | G98: =[1]DICIEMBRE!$BA$55 -> -0.0004 | H98: =ENERO!BA97 -> -0.0004 | S98: =(300*0.16+300)*E98 -> 4524 | T98: =1000*0.16+1000 -> 1160 | AG98: 5684 | AX98: =SUM(H98+S98+T98-U98-V98-W98-X98-Y98-Z98-AA98-AB98-AC98-AD98-AE98-AF98-AG98-AH98-AI98-AJ98-AK98-AL98-AM98-AN98-AO98-AP98-AQ98-AR98-AS98-AT98-AU98-AV98-AW98) -> -0.0004 | AY98: COB. FEB'25: 2 RE-INST.
A99: 82 | B99: TRACTO TRANSPORTES FRASAGA - ISMAEL ESCAREÑO | D99: Ismael Escareño - 81 3079 9137 | E99: 2 | F99: JOSE LUIS | G99: =[1]DICIEMBRE!$BA$97 -> 2909.6628 | H99: =ENERO!BA98 -> 3895.6628 | S99: =(250*0.16+250)*E99 -> 580 | AA99: 500 | AS99: 727.66 | AX99: =SUM(H99+S99+T99-U99-V99-W99-X99-Y99-Z99-AA99-AB99-AC99-AD99-AE99-AF99-AG99-AH99-AI99-AJ99-AK99-AL99-AM99-AN99-AO99-AP99-AQ99-AR99-AS99-AT99-AU99-AV99-AW99) -> 3248.0028
A100: 83 | B100: TRANSPORTES BESERKER - ERNESTO GOMEZ | D100: COMODATO Ernesto Gómez - 81 2001 9256 ernesto.gomez@sanbox.com.mx | E100: 5 | F100: JOSE LUIS | H100: =ENERO!BA99 -> 9.094947e-13 | S100: =(175*0.16+175)*E100 -> 1015 | Z100: 1015 | AX100: =SUM(H100+S100+T100-U100-V100-W100-X100-Y100-Z100-AA100-AB100-AC100-AD100-AE100-AF100-AG100-AH100-AI100-AJ100-AK100-AL100-AM100-AN100-AO100-AP100-AQ100-AR100-AS100-AT100-AU100-AV100-AW100) -> 9.094947e-13 | AY100: COB. FEB'25: 5 MENS. PROP. 21 DIAS, COBRAR EN MARZO MENS. COMPL.
A101: 84 | B101: TRANSPORTE STA ELENA GRAL ZUAZUA NL CARGA Y PERSONAL - FRANCELIA | C101: Nombre de la Empresa: TRANSPORTES STA ELENA GRAL ZUAZUA NL CARGA Y PERSONAL S.A. DE C.V. RFC. TSE210312P9A CFDI: Gastos en General Forma de Pago: Transferencia Teléfono: 811 244 6019 Contacto: Argelio Arrambide Email: santaelenasadecv2021@gmail.com | D101: Argelio Arrambide - 8112446019 Email:santaelenasadecv2021@gmail.com | E101: 9 | F101: MARIO ULISES | G101: =[1]DICIEMBRE!$BA$47 -> 0.0028 | H101: =ENERO!BA100 -> 0.0028 | S101: =(275*0.16+275)*E101 -> 2871 | AI101: 2871 | AX101: =SUM(H101+S101+T101-U101-V101-W101-X101-Y101-Z101-AA101-AB101-AC101-AD101-AE101-AF101-AG101-AH101-AI101-AJ101-AK101-AL101-AM101-AN101-AO101-AP101-AQ101-AR101-AS101-AT101-AU101-AV101-AW101) -> 0.0028
A102: 85 | B102: USA MACHINERY & RENTALS | D102: COMODATO Ramiro - 81 2319 4917 | E102: 3 | H102: =ENERO!BA101 -> 9.094947e-13 | S102: =(189.36*0.16+189.36)*E102 -> 658.9728 | AB102: 658.97 | AX102: =SUM(H102+S102+T102-U102-V102-W102-X102-Y102-Z102-AA102-AB102-AC102-AD102-AE102-AF102-AG102-AH102-AI102-AJ102-AK102-AL102-AM102-AN102-AO102-AP102-AQ102-AR102-AS102-AT102-AU102-AV102-AW102) -> 0.0028 | AY102: COB. FEB'25: 3 MENS. PROP. 19 DIAS COBRAR EN MARZO MENS. COMPL. PDTES. 2 INST. YA PAGADAS
...

Sheet MARZO
B2: Cobranza Total 2025 | D2: =SUM(S2+S3+S4+S5+S6+S7+S8+S9+S10+S11+S12+S13+D5) -> 626927.51 | E2: Saldos 2024 | S2: =G216 -> 34476.146
E3: Enero`25 | S3: =H216-S2 -> 9667.248
B4: COBRANZA MARZO 2025 | E4: Febrero´25 | S4: =I216 -> 6487.8524
B5: MARZO'2025 | D5: =S216+T216+U216 -> 576296.26 | E5: Marzo'25 | S5: =J216 -> 0
B6: Recuperación del 01 al 02 | D6: =SUM(V216:W216) -> 4330.86 | E6: Abril´25 | S6: =K216 -> 0
B7: Recuperación del 03 al 09 | D7: =SUM(X216:AD216) -> 146485.36 | E7: Mayo´25 | S7: =L216 -> 0
B8: Recuperación del 10 al 16 | D8: =SUM(AE216:AK216) -> 93625.4 | E8: Junio´25 | S8: =M216 -> 0
B9: Recuperación del 17 al 23 | D9: =SUM(AL216:AR216) -> 154914.9 | E9: Julio´25 | S9: =N216 -> 0
B10: Recuperación del 24 al 30 | D10: =SUM(AS216:AY216) -> 163928.32 | E10: Agosto'25 | S10: =O216 -> 0
B11: Recuperación del 31 | D11: =SUM(AZ216) -> 18015.17 | E11: Septiembre'25 | S11: =P216 -> 0
E12: Octubre'25 | S12: =Q216 -> 0
B13: Total Recuperado | D13: =SUM(D6:D11) -> 581300.01 | E13: Noviembre'25 | S13: =R216 -> 0
B14: Por Recuperar | D14: =D2-D13 -> 45627.498 | E14: Total de Arrastre: | S14: =SUM(S2:S13) -> 50631.247
A16: NO. | B16: CLIENTE | C16: DATOS FISCALES | D16: CONTACTO | E16: UNI | F16: VENTA | G16: ATRASO | S16: IMPORTE MAR´2025 | T16: SERV. EXTRAS | U16: DES % | V16: 1 | W16: 2 | X16: 3 | Y16: 4 | Z16: 5 | AA16: 6 | AB16: 7 | AC16: 8 | AD16: 9 | AE16: 10 | AF16: 11 | AG16: 12 | AH16: 13 | AI16: 14 | AJ16: 15 | AK16: 16 | AL16: 17 | AM16: 18 | AN16: 19 | AO16: 20 | AP16: 21 | AQ16: 22 | AR16: 23 | AS16: 24 | AT16: 25 | AU16: 26 | AV16: 27 | AW16: 28 | AX16: 29 | AY16: 30 | AZ16: 31 | BA16: SALDOS PENDIENTES | BB16: COMENTARIOS | BC16: ESTATUS PROMESA DE PAGO
G17: 2024 | H17: ENE | I17: FEB | J17: MAR | K17: ABR | L17: MAY | M17: JUN | N17: JUL | O17: AGO | P17: SEP | Q17: OCT | R17: NOV | V17: S | W17: D | X17: L | Y17: M | Z17: M | AA17: J | AB17: V | AC17: S | AD17: D | AE17: L | AF17: M | AG17: M | AH17: J | AI17: V | AJ17: S | AK17: D | AL17: L | AM17: M | AN17: M | AO17: J | AP17: V | AQ17: S | AR17: D | AS17: L | AT17: M | AU17: M | AV17: J | AW17: V | AX17: S | AY17: D | AZ17: L
A18: 1 | B18: ADRIANA ORANDAY DAVILA - RODRIGO ALANIS | D18: Rodrigo Alanis - 81 2861 1509 Email:adrianaoranday@gmail.com alanis_rodrigo@hotmail.com | E18: 1 | F18: JOSE LUIS | G18: =[1]DICIEMBRE!$BA$91 -> 290 | H18: =ENERO!BA18 -> 580 | I18: =FEBRERO!AX18 -> 870 | S18: =(250*0.16+250)*E18 -> 290 | BA18: =SUM(I18+S18+T18-U18-V18-W18-X18-Y18-Z18-AA18-AB18-AC18-AD18-AE18-AF18-AG18-AH18-AI18-AJ18-AK18-AL18-AM18-AN18-AO18-AP18-AQ18-AR18-AS18-AT18-AU18-AV18-AW18-AX18-AY18-AZ18) -> 1160
A19: 2 | B19: ALIMENTOS REGIOMONTANOS PERCAM - ALIMENTOS GRUPER | C19: Nombre de la Empresa: ALIMENTOS GUPER S.A. DE C.V. Contacto: Nancy Paola Perales Teléfono: 811 801 4266 Email: alimentosgupersacv@gmail.com | D19: Alejandro Garcia - 81 2034 3938 Nancy Paola Perales - 8118014266 Alimentosregiopercam@gmail.com alimentosgupersacv@gmail.com | E19: 18 | F19: DANIEL ESTRADA | G19: =[1]DICIEMBRE!$BA$21 -> -0.3952 | H19: =ENERO!BA19 -> -0.3952 | I19: =FEBRERO!AX19 -> 0.0048 | S19: =(300*0.16+300)*E19 -> 6264 | T19: =500*0.16+500 -> 580 | Z19: 6844 | BA19: =SUM(I19+S19+T19-U19-V19-W19-X19-Y19-Z19-AA19-AB19-AC19-AD19-AE19-AF19-AG19-AH19-AI19-AJ19-AK19-AL19-AM19-AN19-AO19-AP19-AQ19-AR19-AS19-AT19-AU19-AV19-AW19-AX19-AY19-AZ19) -> 0.0048 | BB19: COB. MAR'25: 1 REVISION
A20: 3 | B20: AUTO EXPRESS GERAL 21 S.A. DE C.V. - LUIS GERARDO BOLAÑOS GARCIA | C20: Nombre de la Empresa: LUIS GERARDO BOLAÑOS GARCIA RFC. BOGL8702094H5 CFDI: Gastos en general Forma de Pago: Transferencia Teléfono: 811 027 0226 Contacto: Luis Gerardo Bolaños García Email: luismty0902@gmail.com; | D20: Luis Gerardo Bolaños García - 811 027 0226 Email:expressgeral19@gmail.com luismty0902@gmail.com | E20: 5 | F20: JOSE LUIS | G20: =[1]DICIEMBRE!$BA$75 -> 3190.0028 | H20: =ENERO!BA20 -> 0.0028 | I20: =FEBRERO!AX20 -> 0.0028 | S20: =(280*0.16+280)*E20 -> 1624 | AO20: 1624 | BA20: =SUM(I20+S20+T20-U20-V20-W20-X20-Y20-Z20-AA20-AB20-AC20-AD20-AE20-AF20-AG20-AH20-AI20-AJ20-AK20-AL20-AM20-AN20-AO20-AP20-AQ20-AR20-AS20-AT20-AU20-AV20-AW20-AX20-AY20-AZ20) -> 0.0028
A21: 4 | B21: AUTOEXPRESS MATA | C21: Nombre de la Empresa: AUTOEXPRESS MATA S.A. DE C.V. RFC. AMA040520BZ2 CFDI : Forma de Pago: Transferencia Teléfono: 81 1029 1017 Contacto: Edgar Garza Email: | D21: COMODATO Edgar Garza - 81 1029 1017 | E21: 4 | F21: JOSE LUIS | G21: =[1]DICIEMBRE!$BA$23 -> -0.0032 | H21: =ENERO!BA21 -> -0.0032 | I21: =FEBRERO!AX21 -> -0.0032 | S21: =(299*0.16+299)*E21 -> 1387.36 | T21: =500*0.16+500 -> 580 | AP21: 1967.36 | BA21: =SUM(I21+S21+T21-U21-V21-W21-X21-Y21-Z21-AA21-AB21-AC21-AD21-AE21-AF21-AG21-AH21-AI21-AJ21-AK21-AL21-AM21-AN21-AO21-AP21-AQ21-AR21-AS21-AT21-AU21-AV21-AW21-AX21-AY21-AZ21) -> -0.0032 | BB21: COB. MAR'25: 1 RECONFIGURACION DE EQUIPO Y CAMBIO DE SIM
A22: 5 | B22: AUTOREDES EL BAJIO | D22: COMODATO Mane Troncoso -833 192 6706 Email:admontubored@hotmail.com | E22: 10 | F22: JOSE LUIS | G22: =[1]DICIEMBRE!$BA$24 -> -0.3952 | H22: =ENERO!BA22 -> -0.3952 | I22: =FEBRERO!AX22 -> 0.0048 | S22: =(270*0.16+270)*E22 -> 3132 | X22: 3132 | BA22: =SUM(I22+S22+T22-U22-V22-W22-X22-Y22-Z22-AA22-AB22-AC22-AD22-AE22-AF22-AG22-AH22-AI22-AJ22-AK22-AL22-AM22-AN22-AO22-AP22-AQ22-AR22-AS22-AT22-AU22-AV22-AW22-AX22-AY22-AZ22) -> 0.0048
A23: 6 | B23: BAWOMA CONTROL TOTAL S.A. DE C.V. - FUMIGAZ | C23: Nombre de la Empresa: BAWOMA CONTROL TOTAL S.A. DE C.V. RFC.: BCT100310834 CFDI: Gastos en General Forma de Pago: Transferencia Teléfono: 81 1811 0645 Contacto: Manuel Rico Email: supervisorfumigaz@outlook.com | D23: COMODATO Manuel Rico - 81 1811 0645 Email:supervisorfumigaz@outlook.com | E23: 2 | F23: JOSE LUIS | G23: =[1]DICIEMBRE!$BA$48 -> 696 | H23: =ENERO!BA23 -> 696 | I23: =FEBRERO!AX23 -> 0 | S23: =(300*0.16+300)*1 -> 348 | AP23: 348 | BA23: =SUM(I23+S23+T23-U23-V23-W23-X23-Y23-Z23-AA23-AB23-AC23-AD23-AE23-AF23-AG23-AH23-AI23-AJ23-AK23-AL23-AM23-AN23-AO23-AP23-AQ23-AR23-AS23-AT23-AU23-AV23-AW23-AX23-AY23-AZ23) -> 0 | BB23: PDTE. 1 DES-INST. YA PAGADA
A24: 7 | B24: BE ONE SYSTEMS | D24: Lydia Colunga - 81 1176 3598 Edgar Valentin (Pagos) - 81 1970 7000 Email:edgar.valentin@beone.mx lydia@beone.mx | E24: 1 | F24: JOSE LUIS | G24: =[1]DICIEMBRE!$BA$25 -> 0 | H24: =ENERO!BA24 -> 0 | I24: =FEBRERO!AX24 -> 0 | S24: =250*0.16+250 -> 290 | X24: 290 | BA24: =SUM(I24+S24+T24-U24-V24-W24-X24-Y24-Z24-AA24-AB24-AC24-AD24-AE24-AF24-AG24-AH24-AI24-AJ24-AK24-AL24-AM24-AN24-AO24-AP24-AQ24-AR24-AS24-AT24-AU24-AV24-AW24-AX24-AY24-AZ24) -> 0
A25: 8 | B25: BRANDO IVAN MARTINEZ GOVEA - JOSUE FERNANDEZ | D25: Josue Fernandez - 81 1977 0958 Email:jfhz@icloud.com | E25: 5 | F25: JOSE LUIS | G25: =[1]DICIEMBRE!$BA$64 -> 0.0068 | H25: =ENERO!BA25 -> 0.0068 | I25: =FEBRERO!AX25 -> -0.0032 | S25: =(250*0.16+250)*E25 -> 1450 | AA25: 1450 | BA25: =SUM(I25+S25+T25-U25-V25-W25-X25-Y25-Z25-AA25-AB25-AC25-AD25-AE25-AF25-AG25-AH25-AI25-AJ25-AK25-AL25-AM25-AN25-AO25-AP25-AQ25-AR25-AS25-AT25-AU25-AV25-AW25-AX25-AY25-AZ25) -> -0.0032
A26: 9 | B26: CARLOS JONATHAN MARTINEZ RIVERA | D26: Jonathan Rivera - 81 1696 5321 jonathanrivera22929@gmail.com | E26: 1 | F26: JOSE LUIS | G26: =[1]DICIEMBRE!$BA$134 -> 0 | H26: =ENERO!BA139 -> 48 | I26: =FEBRERO!AX26 -> 0 | S26: =(300*0.16+300)*E26 -> 348 | Y26: 348 | BA26: =SUM(I26+S26+T26-U26-V26-W26-X26-Y26-Z26-AA26-AB26-AC26-AD26-AE26-AF26-AG26-AH26-AI26-AJ26-AK26-AL26-AM26-AN26-AO26-AP26-AQ26-AR26-AS26-AT26-AU26-AV26-AW26-AX26-AY26-AZ26) -> 0 | BB26: CAMBIA A ESQUEMA DE FACTURACION 05-FEBRERO-2025
A27: 10 | B27: CARNES RIBHAUS | D27: COMODATO Tania Reyes - 81 1631 2529 Roberta Treviño - 81 1909 7008 Email:facturas@carnesribhaus.com.mx robertaribhaus@gmail.com | E27: 5 | F27: JOSE LUIS | G27: =[1]DICIEMBRE!$BA$27 -> 0.004 | H27: =ENERO!BA26 -> 0.004 | I27: =FEBRERO!AX27 -> 0.004 | S27: =(279*0.16+279)*E27 -> 1618.2 | Y27: 1618.2 | BA27: =SUM(I27+S27+T27-U27-V27-W27-X27-Y27-Z27-AA27-AB27-AC27-AD27-AE27-AF27-AG27-AH27-AI27-AJ27-AK27-AL27-AM27-AN27-AO27-AP27-AQ27-AR27-AS27-AT27-AU27-AV27-AW27-AX27-AY27-AZ27) -> 0.004
A28: 11 | B28: CARPACK, S.A. DE C.V. | C28: Nombre de la Empresa: CARPACK S.A. DE C.V. RFC.: CAR070302UU2 CFDI: Gastos en General Forma de Pago: TransferenciaTeléfono: 811 277 9070 Contacto: Kelly Mayorga Email: compras@carpack.com.mx; antonioespinosa@carpack.com.mx; elizabeth@carpack.com.mx; | D28: COMODATO Kelly Mayorga - 8112779070 Elizabeth Campos - 8116635976 8181919205 Ext. 107 Email:antonioespinosa@carpack.com.mx; elizabeth@carpack.com.mx; compras@carpack.com.mx; pagos@carpack.com.mx | E28: 5 | F28: JOSE LUIS | G28: =[1]DICIEMBRE!$BA$28 -> 0.0028 | H28: =ENERO!BA27 -> 0.0028 | I28: =FEBRERO!AX28 -> 0.0028 | S28: =(280*0.16+280)*E28 -> 1624 | AA28: 1624 | BA28: =SUM(I28+S28+T28-U28-V28-W28-X28-Y28-Z28-AA28-AB28-AC28-AD28-AE28-AF28-AG28-AH28-AI28-AJ28-AK28-AL28-AM28-AN28-AO28-AP28-AQ28-AR28-AS28-AT28-AU28-AV28-AW28-AX28-AY28-AZ28) -> 0.0028
A29: 12 | B29: COMERCIALIZADORA AGROPECUARIA ICK -JORGE ADRIAN RIVERA | C29: Nombre de la Empresa: COMERCIALIZADORA AGROPECUARIA ICK S.A. DE C.V. RFC.: CAI220330VD7 CFDI: Gastos en general Teléfono: 81 2860 1814 Contacto: Adrian Rivera Email: adrian.rmoxica75@gmail.com | D29: COMODATO Adrian Rivera - 81 2860 1814 Email:adrian.rmoxica75@gmail.com | E29: 4 | F29: JOSE LUIS | G29: =[1]DICIEMBRE!$BA$20 -> 0 | H29: =ENERO!BA28 -> 0 | I29: =FEBRERO!AX29 -> 0 | S29: =(300*0.16+300)*E29 -> 1392 | Y29: 1392 | BA29: =SUM(I29+S29+T29-U29-V29-W29-X29-Y29-Z29-AA29-AB29-AC29-AD29-AE29-AF29-AG29-AH29-AI29-AJ29-AK29-AL29-AM29-AN29-AO29-AP29-AQ29-AR29-AS29-AT29-AU29-AV29-AW29-AX29-AY29-AZ29) -> 0
A30: 13 | B30: COMERCIALIZADORA FUERZA CEMENTERA | D30: Candy - 81 2634 9644 candymoreno@forzadelnorte.com | E30: 5 | F30: JOSE LUIS | G30: =[1]DICIEMBRE!$BA$31 -> -3480 | H30: =ENERO!BA29 -> -1740 | I30: =FEBRERO!AX30 -> 0 | S30: =(300*0.16+300)*E30 -> 1740 | AE30: 5220 | BA30: =SUM(I30+S30+T30-U30-V30-W30-X30-Y30-Z30-AA30-AB30-AC30-AD30-AE30-AF30-AG30-AH30-AI30-AJ30-AK30-AL30-AM30-AN30-AO30-AP30-AQ30-AR30-AS30-AT30-AU30-AV30-AW30-AX30-AY30-AZ30) -> -3480 | BB30: PAGO 3 MESES COBRAR HASTA JUNIO 2025
A31: 14 | B31: COMERCIALIZADORA Y LOGISTICA SIFAL - ARTURO SIFUENTES | D31: Arturo Sifuentes - 811 521 3582 Email: silvia-neri@hotmail.com; ventas@acertrans.com.mx; logisticasifal@hotmail.com; | E31: 5 | F31: JOSE LUIS | G31: =[1]DICIEMBRE!$BA$18 -> -128 | H31: =ENERO!BA30 -> -128 | I31: =FEBRERO!AX31 -> -128 | S31: =(350*0.16+350)*E31 -> 2030 | AO31: 2030 | BA31: =SUM(I31+S31+T31-U31-V31-W31-X31-Y31-Z31-AA31-AB31-AC31-AD31-AE31-AF31-AG31-AH31-AI31-AJ31-AK31-AL31-AM31-AN31-AO31-AP31-AQ31-AR31-AS31-AT31-AU31-AV31-AW31-AX31-AY31-AZ31) -> -128
A32: 15 | B32: COMPAÑÍA MADERERA CUAUHTEMOC | D32: COMODATO Daniel Cardenas - 81 2634 0402 Email:recepcionfacturas@ciamaderera.com | E32: 5 | F32: JOSE LUIS | G32: =[1]DICIEMBRE!$BA$77 -> 0.0012 | H32: =ENERO!BA31 -> 0.0012 | I32: =FEBRERO!AX32 -> 0.0012 | S32: =(250*0.16+250)*4+(300*0.16+300)*1 -> 1508 | Z32: 1508 | BA32: =SUM(I32+S32+T32-U32-V32-W32-X32-Y32-Z32-AA32-AB32-AC32-AD32-AE32-AF32-AG32-AH32-AI32-AJ32-AK32-AL32-AM32-AN32-AO32-AP32-AQ32-AR32-AS32-AT32-AU32-AV32-AW32-AX32-AY32-AZ32) -> 0.0012
A33: 16 | B33: CONTINENTAL PARABELLUM - GRUPO SAR | D33: Alan Rodriguez finanzas.gposar@gmail.com | E33: 6 | F33: MARIO ULISES | G33: =[1]DICIEMBRE!$BA$32 -> 0 | H33: =ENERO!BA32 -> -0.004 | I33: =FEBRERO!AX33 -> -0.004 | S33: =(279*0.16+279)*E33 -> 1941.84 | AF33: 1941.84 | BA33: =SUM(I33+S33+T33-U33-V33-W33-X33-Y33-Z33-AA33-AB33-AC33-AD33-AE33-AF33-AG33-AH33-AI33-AJ33-AK33-AL33-AM33-AN33-AO33-AP33-AQ33-AR33-AS33-AT33-AU33-AV33-AW33-AX33-AY33-AZ33) -> -0.004
A34: 17 | B34: DISTRIBUIDORA FERRELECTRICA Y MATERIALES EXPRESS - DEX MATERIALES | D34: Aleyda - 81 3402 1812 Rolando Ziragem 811 077 1470 812 597 2700 / 812 332 3606 oficina@dexmateriales.com; rzgc@hotmail.com; rolando@dexmateriales.com; | E34: 9 | F34: JOSE LUIS | G34: =[1]DICIEMBRE!$BA$34 -> 0 | H34: =ENERO!BA34 -> 0 | I34: =FEBRERO!AX35 -> 0 | S34: =(300*0.16+300)*E34 -> 3132 | AI34: 18792 | BA34: =SUM(I34+S34+T34-U34-V34-W34-X34-Y34-Z34-AA34-AB34-AC34-AD34-AE34-AF34-AG34-AH34-AI34-AJ34-AK34-AL34-AM34-AN34-AO34-AP34-AQ34-AR34-AS34-AT34-AU34-AV34-AW34-AX34-AY34-AZ34) -> -15660 | BB34: PAGARA 6 MENS. COBRAR HASTA EL MES DE SEPTIEMBRE 2025 CAMBIA A ESQUEMA DE MENSUALIDAD 06-SEPTIEMBRE-2024 Y DA DE BAJA 3 UNIDADES Y SE SEPARA CUENTA A COMERCIALIZADORA FUERZA CEMENTERA
A35: 18 | B35: EDGAR ALBERTO CORTEZ TREVIÑO | D35: Edgar Cortez - 81 8185 6454 | E35: 1 | F35: JOSE LUIS | G35: =[1]DICIEMBRE!$BA$35 -> 0 | H35: =ENERO!BA35 -> 0 | I35: =FEBRERO!AX36 -> 0 | S35: =(250*0.16+250)*E35 -> 290 | AB35: 290 | BA35: =SUM(I35+S35+T35-U35-V35-W35-X35-Y35-Z35-AA35-AB35-AC35-AD35-AE35-AF35-AG35-AH35-AI35-AJ35-AK35-AL35-AM35-AN35-AO35-AP35-AQ35-AR35-AS35-AT35-AU35-AV35-AW35-AX35-AY35-AZ35) -> 0
A36: 19 | B36: ELIZABETH RENTERIA REVILLA | C36: Nombre de la Empresa: ELIZABETH RENTERÍA REVILLA RFC. RERE760807SX9 CFDI: Gastos en general Forma de Pago: TransferenciaTeléfono: 811 810 0155 Contacto: Elizabeth Rentería Email: e.lic@live.com.mx | D36: Elizabeth Renteria - 811 810 0155 Email:e.lic@live.com.mx | E36: 2 | F36: JOSE LUIS | G36: =[1]DICIEMBRE!$BA$37 -> 0 | H36: =ENERO!BA36 -> 0 | I36: =FEBRERO!AX37 -> -0.0044 | S36: =(250*0.16+250)*E36 -> 580 | Y36: 580 | BA36: =SUM(I36+S36+T36-U36-V36-W36-X36-Y36-Z36-AA36-AB36-AC36-AD36-AE36-AF36-AG36-AH36-AI36-AJ36-AK36-AL36-AM36-AN36-AO36-AP36-AQ36-AR36-AS36-AT36-AU36-AV36-AW36-AX36-AY36-AZ36) -> -0.0044
A37: 20 | B37: ENDER INDUSTRIAL (EMMANUEL VAZQUEZ - SINERGIX ) | C37: Nombre de la Empresa: ENDER INDUSTRIAL S.A. DE C.V. RFC.: SIS1703089V6 CFDI: Gastos en General. Forma de Pago: Transferencia Teléfono: 813 055 7409 / 81) 2141 0506 Contacto: Emmanuel Vázquez / Sonia Lugo Email: emmanuel@sinergix.net; sonia@sinergix.net; | D37: COMODATO Emmanuel Vazquez - 81 3055 7409 Sonia Lugo (pagos) - 81 2141 0506 Email:sandra@enderindustrial.com claudia@enderindustrial.com belen@enderindustrial.com facturas@enderindustrial.com; emmanuel@sinergix.net; | E37: 7 | F37: JOSE LUIS | G37: =[1]DICIEMBRE!$BA$38 -> -753.9924 | H37: =ENERO!BA37 -> -753.9924 | I37: =FEBRERO!AX38 -> -753.9924 | S37: =(350*0.16+350)*E37 -> 2842 | AF37: 2842 | BA37: =SUM(I37+S37+T37-U37-V37-W37-X37-Y37-Z37-AA37-AB37-AC37-AD37-AE37-AF37-AG37-AH37-AI37-AJ37-AK37-AL37-AM37-AN37-AO37-AP37-AQ37-AR37-AS37-AT37-AU37-AV37-AW37-AX37-AY37-AZ37) -> -753.9924
A38: 21 | B38: ENDO LASER MICROQUIRURGICO - INSTITUTO VIDAURRI DE OJOS (DANIELA MEDELLIN) | D38: Daniela Medellín - 81 1588 8485 Email:monitoreo@endolaser.com.mx | E38: 4 | F38: JOSE LUIS | G38: =[1]DICIEMBRE!$BA$59 -> 6.8212103e-13 | H38: =ENERO!BA38 -> 9.094947e-13 | I38: =FEBRERO!AX39 -> 1.1368684e-12 | S38: =(249*0.16+249)*E38 -> 1155.36 | AE38: 1155.36 | BA38: =SUM(I38+S38+T38-U38-V38-W38-X38-Y38-Z38-AA38-AB38-AC38-AD38-AE38-AF38-AG38-AH38-AI38-AJ38-AK38-AL38-AM38-AN38-AO38-AP38-AQ38-AR38-AS38-AT38-AU38-AV38-AW38-AX38-AY38-AZ38) -> 1.3642421e-12
A39: 22 | B39: EXTINTORES Y EQUIPOS MONTERREY (SERGIO GONZALEZ) | D39: COMODATO Gabriela - 81 2077 4512 Sergio Gonzalez - 81 8654 2753 sergio.jr987@outlook.com | E39: 2 | F39: JOSE LUIS | G39: =[1]DICIEMBRE!$BA$41 -> 0 | H39: =ENERO!BA39 -> 0 | I39: =FEBRERO!AX40 -> 0 | S39: =(300*0.16+300)*2 -> 696 | AB39: 696 | BA39: =SUM(I39+S39+T39-U39-V39-W39-X39-Y39-Z39-AA39-AB39-AC39-AD39-AE39-AF39-AG39-AH39-AI39-AJ39-AK39-AL39-AM39-AN39-AO39-AP39-AQ39-AR39-AS39-AT39-AU39-AV39-AW39-AX39-AY39-AZ39) -> 0 | BB39: PDTE 1 INSTALACION YA PAGADA SOLO COBRAR PROP. CUANDO SE INSTALE
A40: 23 | B40: FERNANDO RAFAEL GONZALEZ MONTEMAYOR (SERVICIO DE PLATAFORMA) | C40: Nombre de la Empresa: GOMO SERVICES Contacto: FERNANDO DISATEL Email: frgm_76@hotmail.com Remisiones con IVA | D40: Fernando Disatel - 81 1799 2490 Email:frgm_76@hotmail.com | E40: 674 | F40: JOSE LUIS | G40: =[1]DICIEMBRE!$BA$42 -> 3220.026 | H40: =ENERO!BA40 -> 3220.026 | I40: =FEBRERO!AX41 -> 3220.028 | S40: =(38.8*0.16+38.8)*E40 -> 30335.392 | AT40: 30335.39 | BA40: =SUM(I40+S40+T40-U40-V40-W40-X40-Y40-Z40-AA40-AB40-AC40-AD40-AE40-AF40-AG40-AH40-AI40-AJ40-AK40-AL40-AM40-AN40-AO40-AP40-AQ40-AR40-AS40-AT40-AU40-AV40-AW40-AX40-AY40-AZ40) -> 3220.03
A41: 24 | B41: FERNANDO REYES HERNANDES | D41: COMODATO Fernando Reyes - 81 1821 3781 Viridiana Flores - 81 1796 4130 arnol84reyeshdz@gmail.com | E41: 1 | F41: JOSE LUIS | G41: =[1]DICIEMBRE!$BA$43 -> 348 | H41: =ENERO!BA41 -> 0 | I41: =FEBRERO!AX42 -> 0 | S41: =(300*0.16+300)*E41 -> 348 | AN41: 348 | BA41: =SUM(I41+S41+T41-U41-V41-W41-X41-Y41-Z41-AA41-AB41-AC41-AD41-AE41-AF41-AG41-AH41-AI41-AJ41-AK41-AL41-AM41-AN41-AO41-AP41-AQ41-AR41-AS41-AT41-AU41-AV41-AW41-AX41-AY41-AZ41) -> 0
A42: 25 | B42: FINPAIS | C42: Nombre de la Empresa: FINPAIS S.A. DE C.V. RFC. FCO130429629 CFDI: Gastos en general Forma de Pago: TransferenciaTeléfono: 81 8208 7559 Contacto: Katty Email: administracion@finpais.com.mx | D42: COMODATO Katty - 81 8208 7559 Email:administracion@finpais.com.mx | E42: 7 | F42: JOSE LUIS | G42: =[1]DICIEMBRE!$BA$44 -> 2598.3956 | H42: =ENERO!BA42 -> 5486.7956 | I42: =FEBRERO!AX43 -> 8085.1956 | S42: =(320*0.16+320)*E42 -> 2598.4 | BA42: =SUM(I42+S42+T42-U42-V42-W42-X42-Y42-Z42-AA42-AB42-AC42-AD42-AE42-AF42-AG42-AH42-AI42-AJ42-AK42-AL42-AM42-AN42-AO42-AP42-AQ42-AR42-AS42-AT42-AU42-AV42-AW42-AX42-AY42-AZ42) -> 10683.596
A43: 26 | B43: FINXERT - FERNANDO VILLARREAL | D43: Fernando Villarreal - 81 2348 6430 | E43: 4 | G43: =[1]DICIEMBRE!$BA$45 -> 0 | H43: =ENERO!BA43 -> 0.0012 | I43: =FEBRERO!AX44 -> -0.0004 | S43: =(290*0.16+290)*E43 -> 1345.6 | AH43: 1345.6 | BA43: =SUM(I43+S43+T43-U43-V43-W43-X43-Y43-Z43-AA43-AB43-AC43-AD43-AE43-AF43-AG43-AH43-AI43-AJ43-AK43-AL43-AM43-AN43-AO43-AP43-AQ43-AR43-AS43-AT43-AU43-AV43-AW43-AX43-AY43-AZ43) -> -0.0004 | BB43: TIENE 6 UNIDADES CON LA INSTALACION NUEVA
A44: 27 | B44: FLETES ESPECIALIZADOS AGL | D44: COMODATO Sr. Ariel - 81 1974 2676 fletesagl@gmail.com | E44: 18 | F44: JOSE LUIS | G44: =[1]DICIEMBRE!$BA$46 -> 9.094947e-13 | H44: =ENERO!BA44 -> 9.094947e-13 | I44: =FEBRERO!AX45 -> 0.002 | S44: =(300*0.16+300)*E44 -> 6264 | AE44: 6264 | BA44: =SUM(I44+S44+T44-U44-V44-W44-X44-Y44-Z44-AA44-AB44-AC44-AD44-AE44-AF44-AG44-AH44-AI44-AJ44-AK44-AL44-AM44-AN44-AO44-AP44-AQ44-AR44-AS44-AT44-AU44-AV44-AW44-AX44-AY44-AZ44) -> 0.002
A45: 28 | B45: FREIGHT HP-PACK MEXICO (DAVID FRANCISCO ARCOS) | D45: COMODATO Carlos Salinas - (201) 748 9020 David Francisco - 81 1033 1916 davidarcosfrancisco1991@gmail.com | E45: 22 | F45: JOSE LUIS | H45: =ENERO!BA45 -> 9604.8 | I45: =FEBRERO!AX46 -> 1380.864 | S45: =(279*0.16+279)*E45 -> 7120.08 | T45: =(549*0.16+549)*2 -> 1273.68 | V45: 1380.86 | AK45: 8393.76 | BA45: =SUM(I45+S45+T45-U45-V45-W45-X45-Y45-Z45-AA45-AB45-AC45-AD45-AE45-AF45-AG45-AH45-AI45-AJ45-AK45-AL45-AM45-AN45-AO45-AP45-AQ45-AR45-AS45-AT45-AU45-AV45-AW45-AX45-AY45-AZ45) -> 0.004 | BB45: COB. MAR '25: 22 MENS. Y 2 INST.
A46: 29 | B46: GEORGINA MELISSA GOMEZ RODELA - PETROVACTOR | C46: Nombre de la Empresa: GEORGINA MELISSA GOMEZ RODELA RFC.: GORG8204295H5 CFDI: Gastos en General Forma de Pago: Transferencia Teléfono: 833 104 3672 Gisela Suarez - 81 1049 7882 Contacto: Griselda Suarez (Petrovactor) Email: griselda@petrovactor.com; facturagmgr@gmail.com; | D46: Georgina Gomez - 833 134 5812 Anahí Juarez - 833 104 3672 Email:facturagmgr@gmail.com; anaiwork7@gmail.com | E46: 14 | F46: JOSE LUIS | G46: =[1]DICIEMBRE!$BA$50 -> -0.0004 | H46: =ENERO!BA46 -> -0.0004 | I46: =FEBRERO!AX47 -> -0.0004 | S46: =(250*0.16+250)*E46 -> 4060 | Y46: 4060 | BA46: =SUM(I46+S46+T46-U46-V46-W46-X46-Y46-Z46-AA46-AB46-AC46-AD46-AE46-AF46-AG46-AH46-AI46-AJ46-AK46-AL46-AM46-AN46-AO46-AP46-AQ46-AR46-AS46-AT46-AU46-AV46-AW46-AX46-AY46-AZ46) -> -0.0004
A47: 30 | B47: GRUPO CASTOR ACERTIVA CONSTRUCCIONES, S.A. DE C.V. (CASTOR) | C47: Nombre de la Empresa: ACERTIVA CONTRUCCIONES S.A. DE C.V. RFC. ACO9605025G2 CFDI: Comunicaciones Satelitales Forma de Pago: Transferencia Teléfono: 818 347 7712 / 13 ext. 106 Contacto: Sr. Santos / Srta.(s) Janeth Villa / Karla Guerra / Fabiola García Email: fabiola.garcia@lsadministracion.com | D47: Srta. Janeth Villa 81 8347 7712 / 13 Ext. 106 Email:fabiola.garcia@lsadministracion.com; | E47: 1 | F47: JOSE LUIS | G47: =[1]DICIEMBRE!$BA$52 -> 0 | H47: =ENERO!BA47 -> 0 | I47: =FEBRERO!AX48 -> 0 | S47: 348 | AP47: 348 | BA47: =SUM(I47+S47+T47-U47-V47-W47-X47-Y47-Z47-AA47-AB47-AC47-AD47-AE47-AF47-AG47-AH47-AI47-AJ47-AK47-AL47-AM47-AN47-AO47-AP47-AQ47-AR47-AS47-AT47-AU47-AV47-AW47-AX47-AY47-AZ47) -> 0
A48: 31 | B48: GRUPO CASTOR ORGANIZACIÓN CASTOR AG, S.A. DE C.V. | C48: Nombre de la Empresa: ORGANIZACIÓN CASTOR S. A. DE C. V. RFC. OCA121001RX9 CFDI: Comunicaciones Satelitales Forma de Pago: Transferencia Teléfono: 818 347 7712 / 13 ext. 106 Contacto: Sr. Santos / Srta.(s) Janeth Villa / Karla Guerra / Fabiola García Email: fabiola.garcia@lsadministracion.com | D48: Srta. Janeth Villa 81 8347 7712 / 13 Ext. 106 Email:fabiola.garcia@lsadministracion.com; | E48: 2 | F48: JOSE LUIS | G48: =[1]DICIEMBRE!$BA$53 -> 0 | H48: =ENERO!BA48 -> 0 | I48: =FEBRERO!AX49 -> 0 | S48: 696 | AB48: 696 | BA48: =SUM(I48+S48+T48-U48-V48-W48-X48-Y48-Z48-AA48-AB48-AC48-AD48-AE48-AF48-AG48-AH48-AI48-AJ48-AK48-AL48-AM48-AN48-AO48-AP48-AQ48-AR48-AS48-AT48-AU48-AV48-AW48-AX48-AY48-AZ48) -> 0
A49: 32 | B49: GREGORY AJMEL MARTINEZ GARCIA (TEOURO TRANSPORTES) | D49: COMODATO Gregory Martínez García 81 1041 6798 greck_090@hotmail.com | E49: 3 | F49: JOSE LUIS | G49: =[1]DICIEMBRE!$BA$54 -> 0 | H49: =ENERO!BA49 -> 0 | I49: =FEBRERO!AX50 -> 0 | S49: =(300*0.16+300)*E49 -> 1044 | AG49: 1044 | BA49: =SUM(I49+S49+T49-U49-V49-W49-X49-Y49-Z49-AA49-AB49-AC49-AD49-AE49-AF49-AG49-AH49-AI49-AJ49-AK49-AL49-AM49-AN49-AO49-AP49-AQ49-AR49-AS49-AT49-AU49-AV49-AW49-AX49-AY49-AZ49) -> 0
A50: 33 | B50: GRUPO AMBIENTAL Y RESIDUOS INDUSTRIALES S.A. DE C. V. (GARISA) | C50: Nombre de la Empresa: GRUPO AMBIENTAL Y RESIDUOS INDUSTRIALES S.A. DE C.V. RFC.: GAR1503063C1 CFDI: Gastos en General. Forma de Pago: Transferencia Electrónica Contacto: Verónica Coronado Teléfono: 812 165 1133 / 8119575404 Email: garisav@hotmail.com | D50: Veronica Coronado- 812 165 1133 / 811 957 5404 Email:garisav@hotmail.com | E50: 3 | F50: JOSE LUIS | G50: =[1]DICIEMBRE!$BA$49 -> 0 | H50: =ENERO!BA50 -> 0 | I50: =FEBRERO!AX51 -> 0 | S50: =(300*0.16+300)*E50 -> 1044 | AI50: 1044 | BA50: =SUM(I50+S50+T50-U50-V50-W50-X50-Y50-Z50-AA50-AB50-AC50-AD50-AE50-AF50-AG50-AH50-AI50-AJ50-AK50-AL50-AM50-AN50-AO50-AP50-AQ50-AR50-AS50-AT50-AU50-AV50-AW50-AX50-AY50-AZ50) -> 0
A51: 34 | B51: GRUPO COMERCIAL CHAPA - MERARY OLVERA | D51: Merary Olvera Cazarez - 81 1741 9785 ventas1@comercialchaoa.com | E51: 1 | F51: JOSE LUIS | S51: =(250*0.16+250)*E51 -> 290 | T51: =2200*0.16+2200 -> 2552 | AO51: 2842 | BA51: =SUM(I51+S51+T51-U51-V51-W51-X51-Y51-Z51-AA51-AB51-AC51-AD51-AE51-AF51-AG51-AH51-AI51-AJ51-AK51-AL51-AM51-AN51-AO51-AP51-AQ51-AR51-AS51-AT51-AU51-AV51-AW51-AX51-AY51-AZ51) -> 0 | BB51: CLIENTE NUEVO 01-MARZO-2025
A52: 35 | B52: GRUPO DIESEL HH | D52: Marisol Alvarado - 33 3486 8750 / Norma Navarro Oficina - 33 1401 2246 33 1654 3312 Email:azulitalia@live.com.mx | E52: 4 | F52: JOSE LUIS | G52: =[1]DICIEMBRE!$BA$56 -> 0 | H52: =ENERO!BA51 -> 0 | I52: =FEBRERO!AX52 -> 0 | S52: =(300*0.16+300)*E52 -> 1392 | Y52: 1392 | BA52: =SUM(I52+S52+T52-U52-V52-W52-X52-Y52-Z52-AA52-AB52-AC52-AD52-AE52-AF52-AG52-AH52-AI52-AJ52-AK52-AL52-AM52-AN52-AO52-AP52-AQ52-AR52-AS52-AT52-AU52-AV52-AW52-AX52-AY52-AZ52) -> 0
A53: 36 | B53: HACIENDO EQUIPO EN TU PROYECTO - EQUIPREST | C53: Nombre de la Empresa: HACIENDO EQUIPO EN TU PROYECTO S.A. DE C.V. RFC. EMO180713MC1 CFDI : Gastos en General C.P.: 64000 Regimen Fiscal: R SIMPLIFICADO DE CONFIANZA Forma de Pago: Transferencia Teléfono: 81 2002 4556 Contacto: Oscar Herrera Email:compras@equiprestmx.com 1er Factura: 1951 | D53: Karla Jessica Jasso - 81 2002 4556 Email:administracion@equiprestmx.com | E53: 3 | F53: JOSE LUIS | G53: =[1]DICIEMBRE!$BA$39 -> 9.094947e-13 | H53: =ENERO!BA52 -> 9.094947e-13 | I53: =FEBRERO!AX53 -> 9.094947e-13 | S53: =(250*0.16+250)*E53 -> 870 | Y53: 870 | BA53: =SUM(I53+S53+T53-U53-V53-W53-X53-Y53-Z53-AA53-AB53-AC53-AD53-AE53-AF53-AG53-AH53-AI53-AJ53-AK53-AL53-AM53-AN53-AO53-AP53-AQ53-AR53-AS53-AT53-AU53-AV53-AW53-AX53-AY53-AZ53) -> 9.094947e-13
A54: 37 | B54: HECTOR ALVEAR AGUILAR - KARLA ALVEAR | C54: Nombre de la Empresa: HECTOR ALVEAR AGUILAR RFC. AEAH940117AV1 CFDI : Gastos en General C.P.:67250 Regimen Fiscal: R DE LAS PERSONAS FISICAS CON ACTIVIDADES EMPRESARIALES Y PROFESIONALES Forma de Pago: Transferencia Teléfono: 81 8050 5722 Contacto: Karla Vear Email: Hec_alvear@hotmail.com 1er Factura: 2068 | D54: Karla Alvear - 81 1800 0233 Email:Hec_alvear@hotmail.com | E54: 1 | F54: JOSE LUIS | G54: =[1]DICIEMBRE!$BA$67 -> 0 | H54: =ENERO!BA53 -> 0 | I54: =FEBRERO!AX54 -> 0 | S54: =(300*0.16+300)*E54 -> 348 | AI54: 348 | BA54: =SUM(I54+S54+T54-U54-V54-W54-X54-Y54-Z54-AA54-AB54-AC54-AD54-AE54-AF54-AG54-AH54-AI54-AJ54-AK54-AL54-AM54-AN54-AO54-AP54-AQ54-AR54-AS54-AT54-AU54-AV54-AW54-AX54-AY54-AZ54) -> 0
A55: 38 | B55: INDUSTRIAL DE CARBON Y GRAFITO - CARBOGRAF | C55: Nombre de la Empresa: INDUSTRIAL DE CARBON Y GRAFITO, S.A. DE C.V. RFC: ICG 100106 UR0 CFDI: Gastos en general TEL: 16 42 2004 Contacto: Pablo Rodriguez Email: Elda@carbograf.com | D55: Daniela Cabello - 81 8273 6437 Email:julio.campos@carbograf.com marlene@carbograf.com | E55: 4 | F55: JOSE LUIS | G55: =[1]DICIEMBRE!$BA$26 -> 0.0032 | H55: =ENERO!BA54 -> 0.0032 | I55: =FEBRERO!AX55 -> 0.0032 | S55: =(349*0.16+349)*E55 -> 1619.36 | AH55: 1619.36 | BA55: =SUM(I55+S55+T55-U55-V55-W55-X55-Y55-Z55-AA55-AB55-AC55-AD55-AE55-AF55-AG55-AH55-AI55-AJ55-AK55-AL55-AM55-AN55-AO55-AP55-AQ55-AR55-AS55-AT55-AU55-AV55-AW55-AX55-AY55-AZ55) -> 0.0032
A56: 39 | B56: INDUSTRIAS PERSISTA LABORO S.A. DE C.V. (ERNESTO GOMEZ) | D56: COMODATO Ernesto Gómez - 81 2001 9256 ernesto.gomez@sanbox.com.mx | E56: 14 | F56: JOSE LUIS | G56: =[1]DICIEMBRE!$BA$58 -> 1525.0064 | H56: =ENERO!BA55 -> -0.0036 | I56: =FEBRERO!AX56 -> -0.0036 | S56: =(250*0.16+250)*E56 -> 4060 | T56: =549*0.16+549 -> 636.84 | Y56: 4696.84 | BA56: =SUM(I56+S56+T56-U56-V56-W56-X56-Y56-Z56-AA56-AB56-AC56-AD56-AE56-AF56-AG56-AH56-AI56-AJ56-AK56-AL56-AM56-AN56-AO56-AP56-AQ56-AR56-AS56-AT56-AU56-AV56-AW56-AX56-AY56-AZ56) -> -0.0036 | BB56: COB. MAR'25: 1 INST. NUEVA
A57: 40 | B57: INVERSIONES QUINEXUS - PRESTACOCHE (FINANCIERA) | C57: Nombre de la Empresa: PRESTACOCHE Contacto: Rosy / Talía Carrizales Email: rosa.sr@quinexus.mx; talia.ci@quinexus.mx; Teléfono: 811 499 1431 / 812 147 3082 | D57: Rosy - 812 354 1373 Email:rosa.sr@quinexus.mx; | E57: 8 | F57: JOSE LUIS | G57: =[1]DICIEMBRE!$BA$85 -> 0.0048 | H57: =ENERO!BA56 -> 0.0048 | I57: =FEBRERO!AX57 -> 0.0048 | S57: =(220*0.16+220)*E57 -> 2041.6 | T57: =6100*0.16+6100 -> 7076 | AB57: 9117.6 | BA57: =SUM(I57+S57+T57-U57-V57-W57-X57-Y57-Z57-AA57-AB57-AC57-AD57-AE57-AF57-AG57-AH57-AI57-AJ57-AK57-AL57-AM57-AN57-AO57-AP57-AQ57-AR57-AS57-AT57-AU57-AV57-AW57-AX57-AY57-AZ57) -> 0.0048 | BB57: COB. MAR'25: 4 REVISIONES, 4 DES-INST., 1 RE-INST. Y 1 VISITA EN FALSO
A58: 41 | B58: JAVIER ANGEL VELAZQUEZ SANCHEZ | C58: Nombre de la Empresa: JAVIER ANGEL VELAZQUEZ SANCHEZ RFC. VESJ4910026E3 CFDI: Comunicaciones satelitales Forma de Pago: Transferencia Teléfono: 812 032 0493 Contacto: Javier Ángel Velázquez Sánchez (FLETES ANGEL VELAZQUEZ) Email: fletesangelvelazquez@gmail.com | D58: Javier Velazquez - 812 032 0493 Email:fletesangelvelazquez@gmail.com | E58: 4 | F58: JOSE LUIS | G58: =[1]DICIEMBRE!$BA$60 -> -0.0048 | H58: =ENERO!BA57 -> -0.0048 | I58: =FEBRERO!AX58 -> -0.0048 | S58: =(330*0.16+330)*E58 -> 1531.2 | AB58: 1531.2 | BA58: =SUM(I58+S58+T58-U58-V58-W58-X58-Y58-Z58-AA58-AB58-AC58-AD58-AE58-AF58-AG58-AH58-AI58-AJ58-AK58-AL58-AM58-AN58-AO58-AP58-AQ58-AR58-AS58-AT58-AU58-AV58-AW58-AX58-AY58-AZ58) -> -0.0048
A59: 42 | B59: JAVIER ARMENTA MARROQUIN | D59: Javier Armenta - 667 348 6917 | E59: 1 | F59: JOSE LUIS | S59: =(799*0.16+799)*E59 -> 926.84 | T59: =2500*0.16+2500 -> 2900 | AB59: 3826.84 | BA59: =SUM(I59+S59+T59-U59-V59-W59-X59-Y59-Z59-AA59-AB59-AC59-AD59-AE59-AF59-AG59-AH59-AI59-AJ59-AK59-AL59-AM59-AN59-AO59-AP59-AQ59-AR59-AS59-AT59-AU59-AV59-AW59-AX59-AY59-AZ59) -> 0 | BB59: CLIENTE NUEVO 07-MARZO-2025 DASH CAM
A60: 43 | B60: JESUS ALEJANDRO LOZANO LOZANO - TRANSPORTES TM | D60: ventas@autotransportes-jl.com administracion@autotransportes-jl.com | E60: 1 | F60: JOSE LUIS | G60: =[1]DICIEMBRE!$BA$100 -> 0 | H60: =ENERO!BA58 -> 0 | I60: =FEBRERO!AX59 -> 0 | S60: =300*0.16+300 -> 348 | AH60: 348 | BA60: =SUM(I60+S60+T60-U60-V60-W60-X60-Y60-Z60-AA60-AB60-AC60-AD60-AE60-AF60-AG60-AH60-AI60-AJ60-AK60-AL60-AM60-AN60-AO60-AP60-AQ60-AR60-AS60-AT60-AU60-AV60-AW60-AX60-AY60-AZ60) -> 0
A61: 44 | B61: JOSE ANGEL MENDEZ ARRIAGA - TRANSPORTES 2M | C61: Nombre de la Empresa: TRANSPORTES 2M Contacto: José Ángel Méndez Arriaga Teléfono: 812 600 8976 Email: jama_ca@hotmail.com | D61: Jose Angel Mendez Arriaga - 812 600 8976 Email:jama_ca@hotmail.com | E61: 4 | F61: JOSE LUIS | G61: =[1]DICIEMBRE!$BA$98 -> -6 | H61: =ENERO!BA59 -> -6 | I61: =FEBRERO!AX60 -> 0 | S61: =(300*0.16+300)*E61 -> 1392 | AF61: 1392 | BA61: =SUM(I61+S61+T61-U61-V61-W61-X61-Y61-Z61-AA61-AB61-AC61-AD61-AE61-AF61-AG61-AH61-AI61-AJ61-AK61-AL61-AM61-AN61-AO61-AP61-AQ61-AR61-AS61-AT61-AU61-AV61-AW61-AX61-AY61-AZ61) -> 0
A62: 45 | B62: JOSE MELQUIADES TOLEDO GARCIA DE LEON | D62: Jose Toledo - 81 1015 9453 Email:j.garcia@grupotranstech.com | E62: 2 | F62: JOSE LUIS | G62: =[1]DICIEMBRE!$BA$63 -> 2.2737368e-13 | H62: =ENERO!BA60 -> 2.2737368e-13 | I62: =FEBRERO!AX61 -> 2.2737368e-13 | S62: =(330*0.16+330)*E62 -> 765.6 | Y62: 765.6 | BA62: =SUM(I62+S62+T62-U62-V62-W62-X62-Y62-Z62-AA62-AB62-AC62-AD62-AE62-AF62-AG62-AH62-AI62-AJ62-AK62-AL62-AM62-AN62-AO62-AP62-AQ62-AR62-AS62-AT62-AU62-AV62-AW62-AX62-AY62-AZ62) -> 2.2737368e-13
A63: 46 | B63: JUAN ANTONIO DE JESUS GARCIA RAMIREZ - TRANSPORTES GARCÍA | C63: Nombre de la Empresa: JUAN ANTONIO DE JESUS GARCIA RAMIREZ RFC. GARJ810921FM4 CFDI : Por Definir Forma de Pago: Transferencia Teléfono: 811 155 2769 Contacto: Antonio García Email: antoniotransgar@hotmail.es | D63: COMODATO Antonio García - 81 1155 2769 Email:antoniotransgar@hotmail.es | E63: 14 | F63: JOSE LUIS | G63: =[1]DICIEMBRE!$BA$99 -> 0.004 | H63: =ENERO!BA61 -> 4693.364 | I63: =FEBRERO!AX62 -> 0.004 | S63: =(289*0.16+289)*E63 -> 4693.36 | BA63: =SUM(I63+S63+T63-U63-V63-W63-X63-Y63-Z63-AA63-AB63-AC63-AD63-AE63-AF63-AG63-AH63-AI63-AJ63-AK63-AL63-AM63-AN63-AO63-AP63-AQ63-AR63-AS63-AT63-AU63-AV63-AW63-AX63-AY63-AZ63) -> 4693.364
A64: 47 | B64: JUAN JAVIER CABRIALES CEDILLO (TRANSPORTES RCD) | D64: Juan Cabriales - 81 2947 2650 Email:transportes.rcd.diaz@gmail.com | E64: 4 | F64: JOSE LUIS | G64: =[1]DICIEMBRE!$BA$65 -> -0.0004 | H64: =ENERO!BA63 -> -0.0004 | I64: =FEBRERO!AX63 -> -0.0004 | S64: =(300*0.16+300)*E64 -> 1392 | Z64: 1392 | BA64: =SUM(I64+S64+T64-U64-V64-W64-X64-Y64-Z64-AA64-AB64-AC64-AD64-AE64-AF64-AG64-AH64-AI64-AJ64-AK64-AL64-AM64-AN64-AO64-AP64-AQ64-AR64-AS64-AT64-AU64-AV64-AW64-AX64-AY64-AZ64) -> -0.0004
A65: 48 | B65: JUAN MEJIA HERNANDEZ | D65: Juan Mejia - 44 2160 1772 mejiahj@hotmail.com | E65: 1 | F65: JOSE LUIS | G65: =[1]DICIEMBRE!$BA$66 -> 0 | H65: =ENERO!BA64 -> 0 | I65: =FEBRERO!AX64 -> 0 | S65: =(200*0.16+200)*E65 -> 232 | Y65: 232 | BA65: =SUM(I65+S65+T65-U65-V65-W65-X65-Y65-Z65-AA65-AB65-AC65-AD65-AE65-AF65-AG65-AH65-AI65-AJ65-AK65-AL65-AM65-AN65-AO65-AP65-AQ65-AR65-AS65-AT65-AU65-AV65-AW65-AX65-AY65-AZ65) -> 0
A66: 49 | B66: K3 SOLUCIONES A LA INDUSTRIA ALIMENTICIA | D66: Susana Calvo - 81 1695 4703 proyectos3@serviciosk3.mx | E66: 1 | F66: JOSE LUIS | G66: =[1]DICIEMBRE!$BA$68 -> 0 | H66: =ENERO!BA65 -> 0 | I66: =FEBRERO!AX65 -> 0 | S66: =(300*0.16+300)*E66 -> 348 | Y66: 348 | BA66: =SUM(I66+S66+T66-U66-V66-W66-X66-Y66-Z66-AA66-AB66-AC66-AD66-AE66-AF66-AG66-AH66-AI66-AJ66-AK66-AL66-AM66-AN66-AO66-AP66-AQ66-AR66-AS66-AT66-AU66-AV66-AW66-AX66-AY66-AZ66) -> 0
A67: 50 | B67: KARLA ZEBETH CLEMENTINA PEÑA MACIAS (EDUARDO ALMAGUER) | D67: Eduardo Almaguer - 81 2920 4044 abelardoalmaguer1991@gmail.com | E67: 1 | F67: JOSE LUIS | G67: =[1]DICIEMBRE!$BA$69 -> 0 | H67: =ENERO!BA66 -> 0 | I67: =FEBRERO!AX66 -> 0 | S67: =(250*0.16+250)*E67 -> 290 | AO67: 290 | BA67: =SUM(I67+S67+T67-U67-V67-W67-X67-Y67-Z67-AA67-AB67-AC67-AD67-AE67-AF67-AG67-AH67-AI67-AJ67-AK67-AL67-AM67-AN67-AO67-AP67-AQ67-AR67-AS67-AT67-AU67-AV67-AW67-AX67-AY67-AZ67) -> 0
A68: 51 | B68: KROHNE DE MEXICO | C68: Nombre de la Empresa: KROHNE DE MEXICO RFC. KME091130LY6 CFDI : Gastos en General C.P.89110 Regimen Fiscal: R GENERAL DE LEY PERSONAS MORALES Forma de Pago: Transferencia Teléfono: (833) 217-3830 Contacto: Email: Pamela@KROHNEMEXICO.com 'erika@krohnemexico.com'; 'israel@krohnemexico.com'; 'maricela@krohnemexico.com' 1er Factura: 2070 | D68: (833) 217-3830 Ext. 101 Email:Pamela@KROHNEMEXICO.com 'erika@krohnemexico.com'; 'israel@krohnemexico.com'; 'maricela@krohnemexico.com' | E68: 19 | F68: JOSE LUIS | G68: =[1]DICIEMBRE!$BA$70 -> 0.002 | H68: =ENERO!BA67 -> 0.002 | I68: =FEBRERO!AX67 -> 0.002 | S68: =(249*0.16+249)*E68 -> 5487.96 | AA68: 5487.96 | BA68: =SUM(I68+S68+T68-U68-V68-W68-X68-Y68-Z68-AA68-AB68-AC68-AD68-AE68-AF68-AG68-AH68-AI68-AJ68-AK68-AL68-AM68-AN68-AO68-AP68-AQ68-AR68-AS68-AT68-AU68-AV68-AW68-AX68-AY68-AZ68) -> 0.002
A69: 52 | B69: LACAR ENERGY LOGISTIC - CARLOS MORENO | D69: Aylin Villanueva - 81 1240 3361 | E69: 4 | F69: JOSE LUIS | G69: =[1]DICIEMBRE!$BA$71 -> 0 | H69: =ENERO!BA68 -> 0 | I69: =FEBRERO!AX68 -> 0 | S69: =(300*0.16+300)*E69 -> 1392 | Z69: 1392 | BA69: =SUM(I69+S69+T69-U69-V69-W69-X69-Y69-Z69-AA69-AB69-AC69-AD69-AE69-AF69-AG69-AH69-AI69-AJ69-AK69-AL69-AM69-AN69-AO69-AP69-AQ69-AR69-AS69-AT69-AU69-AV69-AW69-AX69-AY69-AZ69) -> 0
A70: 53 | B70: LAMBI | C70: Nombre de la Empresa: LAMBI S.A. DE C.V. RFC. LAM9109013H1 CFDI : Gastos en General C.P.66062 Regimen Fiscal: R GENERAL DE LEY PERSONAS MORALES Forma de Pago: Transferencia Teléfono: 81 1908 0591 Contacto: Ericka Ortega Email: eortega@lambi.com.mx 1er Factura: 2008 | D70: Ericka Ortega (Compras) - 81 1908 0591 Email:trafico@lambi.com.mx jrojas@lambi.com.mx dquijas@lambi.com.mx | E70: 2 | F70: JOSE LUIS | G70: =[1]DICIEMBRE!$BA$72 -> -0.008 | H70: =ENERO!BA69 -> -0.008 | I70: =FEBRERO!AX69 -> 0.002 | S70: =(249*0.16+249)*E70 -> 577.68 | AH70: 577.68 | BA70: =SUM(I70+S70+T70-U70-V70-W70-X70-Y70-Z70-AA70-AB70-AC70-AD70-AE70-AF70-AG70-AH70-AI70-AJ70-AK70-AL70-AM70-AN70-AO70-AP70-AQ70-AR70-AS70-AT70-AU70-AV70-AW70-AX70-AY70-AZ70) -> 0.002
A71: 54 | B71: LEMURA VIVIENDA | C71: Nombre de la Empresa: LEMURA VIVIENDA S.A. DE C.V. RFC. LVI170630MEA CFDI: Gastos en general Forma de Pago: Transferencia Teléfono: 81 1624 4288 Contacto: Ignacio Gaxiola Email: igaxiola@lemura.com.mx | D71: Ignacio Gaxiola - 81 1624 4288 Email:igaxiola@lemura.com.mx | E71: 1 | F71: JOSE LUIS | G71: =[1]DICIEMBRE!$BA$73 -> -866.52 | H71: =ENERO!BA70 -> -577.68 | I71: =FEBRERO!AX70 -> -288.84 | S71: =(249*0.16+249)*E71 -> 288.84 | BA71: =SUM(I71+S71+T71-U71-V71-W71-X71-Y71-Z71-AA71-AB71-AC71-AD71-AE71-AF71-AG71-AH71-AI71-AJ71-AK71-AL71-AM71-AN71-AO71-AP71-AQ71-AR71-AS71-AT71-AU71-AV71-AW71-AX71-AY71-AZ71) -> 2.2737368e-12 | BB71: PAGO 6 MENSUALIDADES ADELANTADAS COBRAR HASTA ABRIL 2025
A72: 55 | B72: LUIS ALBERTO DAVILA SALAZAR | C72: Nombre de la Empresa: LUIS ALBERTO DÁVILA SALAZAR RFC. DASL701219TM3 CFDI: Gastos en general Forma de Pago: Transferencia Teléfono: 813 074 5638 Contacto: Luis Dávila Email: luisdavila1970@gmail.com; luis.davila@alsglobal.com | D72: Luis Davila - 813 074 5638 Email:luisdavila1970@gmail.com | E72: 1 | F72: JOSE LUIS | G72: =[1]DICIEMBRE!$BA$74 -> 0 | H72: =ENERO!BA71 -> 0 | I72: =FEBRERO!AX71 -> 0 | S72: 348 | AF72: 348 | BA72: =SUM(I72+S72+T72-U72-V72-W72-X72-Y72-Z72-AA72-AB72-AC72-AD72-AE72-AF72-AG72-AH72-AI72-AJ72-AK72-AL72-AM72-AN72-AO72-AP72-AQ72-AR72-AS72-AT72-AU72-AV72-AW72-AX72-AY72-AZ72) -> 0
A73: 56 | B73: LUIS JAVIER GONZALEZ PEREZ | C73: Nombre de la Empresa: LUIS JAVIER GONZALEZ PEREZ RFC. GOPL9105308A6 CFDI: Gastos en general Forma de Pago: Transferencia Teléfono: 811 907 9148 Contacto: Luis Javier Gonzalez Email: ljgonzalez3591@gmail.com | D73: Luis Javier Gonzalez Perez - 811 907 9148 Email:ljgonzalez3591@gmail.com | E73: 1 | F73: JOSE LUIS | G73: =[1]DICIEMBRE!$BA$76 -> 0 | H73: =ENERO!BA72 -> 0 | I73: =FEBRERO!AX72 -> 0 | S73: =(300*0.16+300)*E73 -> 348 | AG73: 348 | BA73: =SUM(I73+S73+T73-U73-V73-W73-X73-Y73-Z73-AA73-AB73-AC73-AD73-AE73-AF73-AG73-AH73-AI73-AJ73-AK73-AL73-AM73-AN73-AO73-AP73-AQ73-AR73-AS73-AT73-AU73-AV73-AW73-AX73-AY73-AZ73) -> 0
A74: 57 | B74: MARINE DEL VALLE MENDOZA PEREZ - EDUARDO VENTURA MENDOZA | D74: Marine Mexico - 81 1994 9256 Eduardo Ventura - 81 3090 4628 Email:mendozael2003@yahoo.com | E74: 11 | F74: JOSE LUIS | G74: =[1]DICIEMBRE!$BA$36 -> 0.0012 | H74: =ENERO!BA73 -> -0.0076 | I74: =FEBRERO!AX73 -> 0.0024 | S74: =(250*0.16+250)*E74 -> 3190 | Z74: 3190 | BA74: =SUM(I74+S74+T74-U74-V74-W74-X74-Y74-Z74-AA74-AB74-AC74-AD74-AE74-AF74-AG74-AH74-AI74-AJ74-AK74-AL74-AM74-AN74-AO74-AP74-AQ74-AR74-AS74-AT74-AU74-AV74-AW74-AX74-AY74-AZ74) -> 0.0024
A75: 58 | B75: MARIO ALBERTO CABALLERO GARZA | D75: Mario Caballero - 81 1213 3136 | E75: 3 | F75: JOSE LUIS | G75: =[1]DICIEMBRE!$BA$78 -> 0.0012 | H75: =ENERO!BA74 -> 0.0012 | I75: =FEBRERO!AX74 -> 0.0012 | S75: =(250*0.16+250)*E75 -> 870 | AB75: 870 | BA75: =SUM(I75+S75+T75-U75-V75-W75-X75-Y75-Z75-AA75-AB75-AC75-AD75-AE75-AF75-AG75-AH75-AI75-AJ75-AK75-AL75-AM75-AN75-AO75-AP75-AQ75-AR75-AS75-AT75-AU75-AV75-AW75-AX75-AY75-AZ75) -> 0.0012
A76: 59 | B76: MARMOL Y GRANITO RIO - GERARDO NIETO | D76: Gerardo Nieto - 81 1184 1231 Email:fizz98@hotmail.com consueloer@marmolemperador.com | E76: 5 | F76: JOSE LUIS | G76: =[1]DICIEMBRE!$BA$51 -> 0 | H76: =ENERO!BA75 -> 0 | I76: =FEBRERO!AX75 -> 0 | S76: =(300*0.16+300)*E76 -> 1740 | Z76: 1740 | BA76: =SUM(I76+S76+T76-U76-V76-W76-X76-Y76-Z76-AA76-AB76-AC76-AD76-AE76-AF76-AG76-AH76-AI76-AJ76-AK76-AL76-AM76-AN76-AO76-AP76-AQ76-AR76-AS76-AT76-AU76-AV76-AW76-AX76-AY76-AZ76) -> 0
A77: 60 | B77: MARTINEZ & DE LA ROSA CONSTRUCCIONES - ANTONIO MARTINEZ | D77: COMODATO Brenda Araujo - 81 3421 7089 Ing. Antonio Martínez -81 1537 7636 Email:facturas@myrconsa.mx catalinac@myrconsa.mx antoniomtz@myrconsa.mx | E77: 15 | F77: JOSE LUIS | G77: =[1]DICIEMBRE!$BA$22 -> -1.8189894e-12 | H77: =ENERO!BA76 -> -0.002 | I77: =FEBRERO!AX76 -> -0.002 | S77: =(279*0.16+279)*E77 -> 4854.6 | T77: =(1850*0.16+1850)+500*0.16+500 -> 2726 | Z77: 7580.6 | BA77: =SUM(I77+S77+T77-U77-V77-W77-X77-Y77-Z77-AA77-AB77-AC77-AD77-AE77-AF77-AG77-AH77-AI77-AJ77-AK77-AL77-AM77-AN77-AO77-AP77-AQ77-AR77-AS77-AT77-AU77-AV77-AW77-AX77-AY77-AZ77) -> -0.002 | BB77: COB. MAR'25: 1 REEMPLAZO DE EQUIPO Y 1 INST. NUEVA
A78: 61 | B78: MCJ CHILLER - EVERARDO NUNCIO CUELLAR | D78: COMODATO Everardo Nuncio - 81 1823 3384 Pagos Brenda Ocañas - 81 7654 2904/81 18 72 2728 Email:oficina@mcjchillerservice.com | E78: 8 | F78: JOSE LUIS | G78: =[1]DICIEMBRE!$BA$40 -> 0.0004 | H78: =ENERO!BA77 -> 0.0004 | I78: =FEBRERO!AX77 -> 0.0004 | S78: =(269*0.16+269)*E78 -> 2496.32 | T78: =500*0.16+500 -> 580 | AE78: 3076.32 | BA78: =SUM(I78+S78+T78-U78-V78-W78-X78-Y78-Z78-AA78-AB78-AC78-AD78-AE78-AF78-AG78-AH78-AI78-AJ78-AK78-AL78-AM78-AN78-AO78-AP78-AQ78-AR78-AS78-AT78-AU78-AV78-AW78-AX78-AY78-AZ78) -> 0.0004 | BB78: COB. MAR'25: 1 DES-INST.
A79: 62 | B79: MIGUEL EDUARDO CASAS ARIZMENDI - MIGUEL ANGEL CASAS | C79: Nombre de la Empresa: MIGUEL EDUARDO CASAS ARIZMENDI RFC.: CAAM980824PA1 CFDI: Por Definir Forma de Pago: TransferenciaTeléfono: 811 418 8880 Contacto: Nidia Arizmendi Email: mactransportacion@gmail.com | D79: COMODATO Miguel Angel Casas - 811 566 5492 Email:mactransportacion@gmail.com | E79: 17 | F79: JOSE LUIS | H79: =ENERO!BA78 -> 0 | I79: =FEBRERO!AX78 -> -0.0024 | S79: =(289*0.16+289)*E79 -> 5699.08 | AW79: 5699.08 | BA79: =SUM(I79+S79+T79-U79-V79-W79-X79-Y79-Z79-AA79-AB79-AC79-AD79-AE79-AF79-AG79-AH79-AI79-AJ79-AK79-AL79-AM79-AN79-AO79-AP79-AQ79-AR79-AS79-AT79-AU79-AV79-AW79-AX79-AY79-AZ79) -> -0.0024
A80: 63 | B80: MYA TRANSPORTES, S.A. DE C.V. (MOLIENDAS Y ALIMENTOS) | C80: Nombre de la Empresa: MYA TRANSPORTES S.A. DE C.V. RFC. MTR0705245M3 CFDI: Por definir Forma de Pago: Cheque Bancario Teléfono: 81 8351 8283 Contacto: Srta. Elizabeth Garza / Sr. (s) Eduardo Garza / Emeterio Vargas. Email: administracion@myatsa.com; evargas@moliendas.com; egarza@moliendas.com; garzacavazos@hotmail.com, | D80: COMODATO Elizabeth Garza - 81 8351 8283 ext.126 Eduardo Garza / Emeterio Vargas Email:administracion@myatsa.com; evargas@moliendas.com; egarza@moliendas.com; garzacavazos@hotmail.com | E80: 16 | F80: DANIEL ESTRADA | G80: =[1]DICIEMBRE!$BA$81 -> -0.0012 | H80: =ENERO!BA79 -> -0.0012 | I80: =FEBRERO!AX79 -> -0.0012 | S80: =(5250+300)*0.16+5250+300 -> 6438 | AW80: 6438 | BA80: =SUM(I80+S80+T80-U80-V80-W80-X80-Y80-Z80-AA80-AB80-AC80-AD80-AE80-AF80-AG80-AH80-AI80-AJ80-AK80-AL80-AM80-AN80-AO80-AP80-AQ80-AR80-AS80-AT80-AU80-AV80-AW80-AX80-AY80-AZ80) -> -0.0012
A81: 64 | B81: NORMA LETICIA GONZALEZ VAZQUEZ (AARON ARRATIA AGUILAR) | D81: COMODATO Aaron Arratia Aguilar - 81 2339 0793 aaronarratiaaguilarisamel12@gmail.com | E81: 5 | F81: JOSE LUIS | G81: =[1]DICIEMBRE!$BA$119 -> -0.02 | H81: =ENERO!BA123 -> -0.02 | I81: =FEBRERO!AX80 -> 0 | S81: =(300*0.16+300)*E81 -> 1740 | AE81: 1740 | BA81: =SUM(I81+S81+T81-U81-V81-W81-X81-Y81-Z81-AA81-AB81-AC81-AD81-AE81-AF81-AG81-AH81-AI81-AJ81-AK81-AL81-AM81-AN81-AO81-AP81-AQ81-AR81-AS81-AT81-AU81-AV81-AW81-AX81-AY81-AZ81) -> 0
A82: 65 | B82: PABLO EMILIANO RODRIGUEZ DURAN | D82: COMODATO Pablo Rodriguez - 81 2010 3744 pablordzmasper@hotmail.com | E82: 2 | F82: JOSE LUIS | G82: =[1]DICIEMBRE!$BA$83 -> 0 | H82: =ENERO!BA80 -> 0 | I82: =FEBRERO!AX81 -> 0 | S82: =(300*0.16+300)*E82 -> 696 | AJ82: 696 | BA82: =SUM(I82+S82+T82-U82-V82-W82-X82-Y82-Z82-AA82-AB82-AC82-AD82-AE82-AF82-AG82-AH82-AI82-AJ82-AK82-AL82-AM82-AN82-AO82-AP82-AQ82-AR82-AS82-AT82-AU82-AV82-AW82-AX82-AY82-AZ82) -> 0
A83: 66 | B83: PACKET CAR DE MONTERREY - PABLO ERNESTO CADENA ACEVEDO | C83: Nombre de la Empresa: PACKET CAR DE MONTERREY S.A. DE C.V. RFC. PCM200703M63 CFDI: Por definir Forma de Pago: Transferencia Teléfono: 811 722 2636 Contacto: Pablo Ernesto Cadena Acevedo Email: docrem@hotmail.com | D83: Pablo E. Cadena Acevedo - 811 722 2636 Email:docrem@hotmail.com | E83: 8 | F83: JOSE LUIS | G83: =[1]DICIEMBRE!$BA$82 -> 2784.0048 | H83: =ENERO!BA81 -> 0.0048 | I83: =FEBRERO!AX82 -> 0.0048 | S83: =(300*0.16+300)*E83 -> 2784 | AT83: 2784 | BA83: =SUM(I83+S83+T83-U83-V83-W83-X83-Y83-Z83-AA83-AB83-AC83-AD83-AE83-AF83-AG83-AH83-AI83-AJ83-AK83-AL83-AM83-AN83-AO83-AP83-AQ83-AR83-AS83-AT83-AU83-AV83-AW83-AX83-AY83-AZ83) -> 0.0048
A84: 67 | B84: PREFOM | D84: COMODATO Hugo Díaz - 81 1290 4608 admin@bloquerafbk.com | E84: 4 | F84: JOSE LUIS | G84: =[1]DICIEMBRE!$BA$84 -> 0 | H84: =ENERO!BA82 -> 0 | I84: =FEBRERO!AX83 -> 0 | S84: =(220*0.16+220)*E84 -> 1020.8 | Z84: 1020.8 | BA84: =SUM(I84+S84+T84-U84-V84-W84-X84-Y84-Z84-AA84-AB84-AC84-AD84-AE84-AF84-AG84-AH84-AI84-AJ84-AK84-AL84-AM84-AN84-AO84-AP84-AQ84-AR84-AS84-AT84-AU84-AV84-AW84-AX84-AY84-AZ84) -> 0
A85: 68 | B85: QUITAKILOS | D85: Myrian Guerra - 811 636 1249 81 8359 4400 Email:facturacion@quitakilos.com adriana@quitakilos.com | E85: 3 | F85: JOSE LUIS | G85: =[1]DICIEMBRE!$BA$87 -> -0.0044 | H85: =ENERO!BA84 -> -0.0044 | I85: =FEBRERO!AX84 -> -0.0044 | S85: =(250*0.16+250)*E85 -> 870 | AA85: 870 | BA85: =SUM(I85+S85+T85-U85-V85-W85-X85-Y85-Z85-AA85-AB85-AC85-AD85-AE85-AF85-AG85-AH85-AI85-AJ85-AK85-AL85-AM85-AN85-AO85-AP85-AQ85-AR85-AS85-AT85-AU85-AV85-AW85-AX85-AY85-AZ85) -> -0.0044
A86: 69 | B86: RAUL MURO RODRIGUEZ - EDGAR MURO | D86: COMODATO Edgar Muro - 81 2255 3176 transportesmuro@hotmail.com | E86: 5 | F86: JOSE LUIS | G86: =[1]DICIEMBRE!$BA$88 -> 4.5474735e-13 | H86: =ENERO!BA85 -> 4.5474735e-13 | I86: =FEBRERO!AX85 -> 4.5474735e-13 | S86: =(300*0.16+300)*E86 -> 1740 | T86: =(549*0.16+549)*2 -> 1273.68 | AA86: 3013.68 | BA86: =SUM(I86+S86+T86-U86-V86-W86-X86-Y86-Z86-AA86-AB86-AC86-AD86-AE86-AF86-AG86-AH86-AI86-AJ86-AK86-AL86-AM86-AN86-AO86-AP86-AQ86-AR86-AS86-AT86-AU86-AV86-AW86-AX86-AY86-AZ86) -> 4.5474735e-13 | BB86: COB. MAR'25: 2 INST. NUEVAS
A87: 70 | B87: RAYAS SERVICIOS Y DESARROLLOS INTEGRALES | D87: Cristel del Rio - 844 380 0154 Alfonso - 81 3643 2962 Email:alonsogaspar578@gmail.com | E87: 5 | F87: JOSE LUIS | G87: =[1]DICIEMBRE!$BA$89 -> 0 | H87: =ENERO!BA86 -> 0 | I87: =FEBRERO!AX86 -> 0 | S87: =(300*0.16+300)*E87 -> 1740 | AA87: 1740 | BA87: =SUM(I87+S87+T87-U87-V87-W87-X87-Y87-Z87-AA87-AB87-AC87-AD87-AE87-AF87-AG87-AH87-AI87-AJ87-AK87-AL87-AM87-AN87-AO87-AP87-AQ87-AR87-AS87-AT87-AU87-AV87-AW87-AX87-AY87-AZ87) -> 0
A88: 71 | B88: REYNOL MENCHACA MARTINEZ - FABIOLA ORTIZ | D88: COMODATO Fabiola Ortiz - 81 8082 4502 Reynol_menchaca94@hotmail.com fabiola.rojas15@hotmail.com | E88: 1 | F88: JOSE LUIS | S88: =(300*0.16+300)*E88 -> 348 | V88: 300 | X88: 48 | BA88: =SUM(I88+S88+T88-U88-V88-W88-X88-Y88-Z88-AA88-AB88-AC88-AD88-AE88-AF88-AG88-AH88-AI88-AJ88-AK88-AL88-AM88-AN88-AO88-AP88-AQ88-AR88-AS88-AT88-AU88-AV88-AW88-AX88-AY88-AZ88) -> 0 | BB88: CAMBIA A ESQUEMA DE FACTURACION 04-MARZO-2025
A89: 72 | B89: ROBERTO CARLOS AVILA GUZMAN | D89: COMODATO Roberto Avila - 81 8088 2340 fletes-avila@hotmail.com | E89: 8 | F89: JOSE LUIS | G89: =[1]DICIEMBRE!$BA$90 -> 0 | H89: =ENERO!BA87 -> 0 | I89: =FEBRERO!AX87 -> 0 | S89: =(300*0.16+300)*E89 -> 2784 | AB89: 2784 | BA89: =SUM(I89+S89+T89-U89-V89-W89-X89-Y89-Z89-AA89-AB89-AC89-AD89-AE89-AF89-AG89-AH89-AI89-AJ89-AK89-AL89-AM89-AN89-AO89-AP89-AQ89-AR89-AS89-AT89-AU89-AV89-AW89-AX89-AY89-AZ89) -> 0
A90: 73 | B90: RODRIGO MORENO VILLARREAL | D90: COMODATO Rodrigo Moreno - 81 1410 4886 | E90: 3 | F90: JOSE LUIS | G90: =[1]DICIEMBRE!$BA$92 -> 0 | H90: =ENERO!BA88 -> 0 | I90: =FEBRERO!AX88 -> 0 | S90: =(300*0.16+300)*E90 -> 1044 | AM90: 1044 | BA90: =SUM(I90+S90+T90-U90-V90-W90-X90-Y90-Z90-AA90-AB90-AC90-AD90-AE90-AF90-AG90-AH90-AI90-AJ90-AK90-AL90-AM90-AN90-AO90-AP90-AQ90-AR90-AS90-AT90-AU90-AV90-AW90-AX90-AY90-AZ90) -> 0
A91: 74 | B91: SEI ARQUITECTOS - DANIELA OCHOA | D91: Contacto: Nohemi Montemayor Teléfono: 81 1495 0269 Email:daniela.ochoa@seiarquitectos.com claudia.martinez@seiarquitectos.com: | E91: 2 | F91: JOSE LUIS | G91: =[1]DICIEMBRE!$BA$33 -> 0.0012 | H91: =ENERO!BA89 -> 0.0012 | I91: =FEBRERO!AX89 -> 0.0012 | S91: =(250*0.16+250)*E91 -> 580 | BA91: =SUM(I91+S91+T91-U91-V91-W91-X91-Y91-Z91-AA91-AB91-AC91-AD91-AE91-AF91-AG91-AH91-AI91-AJ91-AK91-AL91-AM91-AN91-AO91-AP91-AQ91-AR91-AS91-AT91-AU91-AV91-AW91-AX91-AY91-AZ91) -> 580.0012
A92: 75 | B92: SERGIO EDIÑHO ARRIAGA HERNANDEZ | D92: Contacto: Sergio Ediñho Arriaga Hdz Teléfono: 81 2402 5624 se.arriaga@hotmail.com | E92: 1 | H92: =166.66*0.16+166.66 -> 193.3256 | I92: =FEBRERO!AX90 -> -0.0044 | S92: =(250*0.16+250)*E92 -> 290 | AB92: 290 | BA92: =SUM(I92+S92+T92-U92-V92-W92-X92-Y92-Z92-AA92-AB92-AC92-AD92-AE92-AF92-AG92-AH92-AI92-AJ92-AK92-AL92-AM92-AN92-AO92-AP92-AQ92-AR92-AS92-AT92-AU92-AV92-AW92-AX92-AY92-AZ92) -> -0.0044 | BB92: BAJA 31-MARZO-2025
A93: 76 | B93: SERVICIO DE ALMACENAMIENTO Y TRANSPORTE RG II - CESAR RODRIGUEZ (GP MET LOGISTICS) | D93: Contacto: Cesar Rodriguez Teléfono: 81 3088 0606 Proveedores@cbrlogistics.com cesar.rdz@cbrlogistics.com | E93: 5 | F93: JOSE LUIS | G93: =[1]DICIEMBRE!$BA$29 -> 2900 | H93: =ENERO!BA90 -> 4350 | I93: =FEBRERO!AX91 -> 0 | S93: =(250*0.16+250)*E93 -> 1450 | AI93: 1450 | BA93: =SUM(I93+S93+T93-U93-V93-W93-X93-Y93-Z93-AA93-AB93-AC93-AD93-AE93-AF93-AG93-AH93-AI93-AJ93-AK93-AL93-AM93-AN93-AO93-AP93-AQ93-AR93-AS93-AT93-AU93-AV93-AW93-AX93-AY93-AZ93) -> 0 | BB93: SE MIGRARA UNIDAD A CESAR RODRIGUEZ - ANTES GP MET LOGISTICS
A94: 77 | B94: SERVICIOS LOGISTICOS MARSEL - CLAUDIA LUNA GUTIERREZ TRANSMARSEL | C94: Nombre de la Empresa: CLAUDIA LUNA GUTIERREZ RFC. LUGC700301TKA CFDI: Comunicaciones satelitales Forma de Pago: Transferencia Teléfono: 811 155 5054 / 8183646871 Contacto: Sergio Leal / Jazmín Email: bazoon_300@hotmail.com; clg.lgc@hotmail.com; transportesmarsel@hotmail.com; | D94: Sergio Leal - 811 155 5054 Jazmín - 818 364 6871 Email:bazoon_300@hotmail.com; clg.lgc@hotmail.com; transportesmarsel@hotmail.com; | E94: 13 | F94: JOSE LUIS | G94: =[1]DICIEMBRE!$BA$30 -> 0 | H94: =ENERO!BA91 -> 0 | I94: =FEBRERO!AX92 -> 0 | S94: =(250*0.16+250)*E94 -> 3770 | T94: =2254*0.16+2254 -> 2614.64 | Z94: 6384.64 | BA94: =SUM(I94+S94+T94-U94-V94-W94-X94-Y94-Z94-AA94-AB94-AC94-AD94-AE94-AF94-AG94-AH94-AI94-AJ94-AK94-AL94-AM94-AN94-AO94-AP94-AQ94-AR94-AS94-AT94-AU94-AV94-AW94-AX94-AY94-AZ94) -> -9.094947e-13 | BB94: COB. MAR'25: 1 EQP. E INST. NUEVA Y 1 MENS. PROP. 06 DIAS
A95: 78 | B95: SH TRANSPORTACIONES DRP TRANSPORTES | C95: Nombre de la Empresa: DRP TRANSPORTES S. DE R. L. DE C.V. RFC.: DTR210720A25 CFDI : G03 Forma de Pago: Transferencia Teléfono: 81 1421 3083 Contacto: Francisco Sanchez Email: fsancheznoreste@hotmail.es | D95: Francisco Sanchez - 81 1421 3083 Email:fsancheznoreste@hotmail.es | E95: 4 | F95: JOSE LUIS | G95: =[1]DICIEMBRE!$BA$93 -> -0.0848 | H95: =ENERO!BA92 -> -0.0848 | I95: =FEBRERO!AX93 -> -0.0048 | S95: =(350*0.16+350)*E95 -> 1624 | Z95: 1624 | BA95: =SUM(I95+S95+T95-U95-V95-W95-X95-Y95-Z95-AA95-AB95-AC95-AD95-AE95-AF95-AG95-AH95-AI95-AJ95-AK95-AL95-AM95-AN95-AO95-AP95-AQ95-AR95-AS95-AT95-AU95-AV95-AW95-AX95-AY95-AZ95) -> -0.0048
A96: 79 | B96: SH TRANSPORTACIONES JUAN FRANCISCO SANCHEZ CONTRERAS | C96: Nombre de la Empresa: JUAN FRANCISCO SANCHEZ CONTRERAS RFC.: SACJ7811022UA CFDI : G03 Forma de Pago: Transferencia Teléfono: 81 1421 3083 Contacto: Francisco Sanchez Email: fsancheznoreste@hotmail.es | D96: Francisco Sanchez - 81 1421 3083 Email:fsancheznoreste@hotmail.es | E96: 8 | F96: JOSE LUIS | G96: =[1]DICIEMBRE!$BA$94 -> -0.0088 | H96: =ENERO!BA93 -> -0.0088 | I96: =FEBRERO!AX94 -> 0.0012 | S96: =(350*0.16+350)*E96 -> 3248 | Z96: 3248 | BA96: =SUM(I96+S96+T96-U96-V96-W96-X96-Y96-Z96-AA96-AB96-AC96-AD96-AE96-AF96-AG96-AH96-AI96-AJ96-AK96-AL96-AM96-AN96-AO96-AP96-AQ96-AR96-AS96-AT96-AU96-AV96-AW96-AX96-AY96-AZ96) -> 0.0012
A97: 80 | B97: SILVIA NERI SALAZAR - ACERTRANS | C97: Nombre de la Empresa: SILVIA NERI SALAZAR RFC.: NESS6001221GA CFDI: Gastos en general Forma de Pago: Transferencia Teléfono: 811 521 3582 / 811 044 7961 Contacto: Arturo Sifuentes / Silvia Neri Salazar Email: ventas@acertrans.com.mx; logisticasifal@hotmail.com; Silvia-neri@hotmail.com; | D97: Arturo Sifuentes - 811 521 3582 Silvia Neri Salazar - 811 044 7961 Email: silvia-neri@hotmail.com; ventas@acertrans.com.mx; logisticasifal@hotmail.com; | E97: 6 | F97: JOSE LUIS | G97: =[1]DICIEMBRE!$BA$19 -> 0 | H97: =ENERO!BA94 -> 0 | I97: =FEBRERO!AX95 -> 0 | S97: =350*E97*0.16+350*E97 -> 2436 | Z97: 2436 | BA97: =SUM(I97+S97+T97-U97-V97-W97-X97-Y97-Z97-AA97-AB97-AC97-AD97-AE97-AF97-AG97-AH97-AI97-AJ97-AK97-AL97-AM97-AN97-AO97-AP97-AQ97-AR97-AS97-AT97-AU97-AV97-AW97-AX97-AY97-AZ97) -> 0
A98: 81 | B98: SINDUSA SERVICIOS INDUSTRIALES – PABLO MORALES | D98: Pablo Morales - 81 3529 5622 | E98: 2 | H98: =ENERO!BA95 -> 0 | I98: =FEBRERO!AX96 -> 5.6843419e-14 | S98: =(249*0.16+249)*E98 -> 577.68 | T98: =1850*0.16+1850 -> 2146 | Z98: 2723.68 | BA98: =SUM(I98+S98+T98-U98-V98-W98-X98-Y98-Z98-AA98-AB98-AC98-AD98-AE98-AF98-AG98-AH98-AI98-AJ98-AK98-AL98-AM98-AN98-AO98-AP98-AQ98-AR98-AS98-AT98-AU98-AV98-AW98-AX98-AY98-AZ98) -> 4.5474735e-13 | BB98: COB. MAR'25: 1 EQP. E INST. NUEVA
A99: 82 | B99: SITELECOM SERVICIOS DE INGENIERIA Y TELECOMUNICACIONES | D99: COMODATO Anel - 773 132 8093 Fermin Uribe Ramos - 7732188379 Alejandro - 77 1393 3704 eber.sannicolas@sitelecom.lat | E99: 9 | F99: JOSE LUIS | G99: =[1]DICIEMBRE!$BA$95 -> 4.5474735e-13 | H99: =ENERO!BA96 -> 4.5474735e-13 | I99: =FEBRERO!AX97 -> 4.5474735e-13 | S99: =(300*0.16+300)*E99 -> 3132 | AB99: 3132 | BA99: =SUM(I99+S99+T99-U99-V99-W99-X99-Y99-Z99-AA99-AB99-AC99-AD99-AE99-AF99-AG99-AH99-AI99-AJ99-AK99-AL99-AM99-AN99-AO99-AP99-AQ99-AR99-AS99-AT99-AU99-AV99-AW99-AX99-AY99-AZ99) -> 4.5474735e-13
A100: 83 | B100: TEGMESA S.A. DE C.V. - GRUAS TEGMESA | C100: Nombre de la Empresa: GRUAS TEGMESA S.A. DE C.V. RFC. GTE1602233N9 CFDI : Gastos en general Forma de Pago: Transferencia Teléfono: 81 1908 2914 Contacto: Julia Gonzalez Sosa Email: julia@construtecacero.com.mx | D100: COMODATO Raul Hernandez - 811 2422 086 Julia Graciela Gzz. Sosa - 811 9082 914 Email:gruastegmesa@construtecacero.com.mx julia@construtecacero.com.mx | E100: 13 | F100: JOSE LUIS | G100: =[1]DICIEMBRE!$BA$55 -> -0.0004 | H100: =ENERO!BA97 -> -0.0004 | I100: =FEBRERO!AX98 -> -0.0004 | S100: =(300*0.16+300)*E100 -> 4524 | AF100: 4524 | BA100: =SUM(I100+S100+T100-U100-V100-W100-X100-Y100-Z100-AA100-AB100-AC100-AD100-AE100-AF100-AG100-AH100-AI100-AJ100-AK100-AL100-AM100-AN100-AO100-AP100-AQ100-AR100-AS100-AT100-AU100-AV100-AW100-AX100-AY100-AZ100) -> -0.0004
A101: 84 | B101: TRACTO TRANSPORTES FRASAGA - ISMAEL ESCAREÑO | D101: Ismael Escareño - 81 3079 9137 | E101: 2 | F101: JOSE LUIS | G101: =[1]DICIEMBRE!$BA$97 -> 2909.6628 | H101: =ENERO!BA98 -> 3895.6628 | I101: =FEBRERO!AX99 -> 3248.0028 | S101: =(250*0.16+250)*E101 -> 580 | BA101: =SUM(I101+S101+T101-U101-V101-W101-X101-Y101-Z101-AA101-AB101-AC101-AD101-AE101-AF101-AG101-AH101-AI101-AJ101-AK101-AL101-AM101-AN101-AO101-AP101-AQ101-AR101-AS101-AT101-AU101-AV101-AW101-AX101-AY101-AZ101) -> 3828.0028
A102: 85 | B102: TRANSPORTES BESERKER - ERNESTO GOMEZ | D102: COMODATO Ernesto Gómez - 81 2001 9256 ernesto.gomez@sanbox.com.mx | E102: 5 | F102: JOSE LUIS | H102: =ENERO!BA99 -> 9.094947e-13 | I102: =FEBRERO!AX100 -> 9.094947e-13 | S102: =(250*0.16+250)*E102 -> 1450 | AA102: 1450 | BA102: =SUM(I102+S102+T102-U102-V102-W102-X102-Y102-Z102-AA102-AB102-AC102-AD102-AE102-AF102-AG102-AH102-AI102-AJ102-AK102-AL102-AM102-AN102-AO102-AP102-AQ102-AR102-AS102-AT102-AU102-AV102-AW102-AX102-AY102-AZ102) -> 9.094947e-13
...

Sheet ABRIL
B2: Cobranza Total 2025 | D2: =SUM(S2+S3+S4+S5+S6+S7+S8+S9+S10+S11+S12+S13+D5) -> 579375.14 | E2: Saldos 2024 | S2: =G234 -> 26129.564
E3: Enero`25 | S3: =H234-S2 -> 13344.842
B4: COBRANZA ABRIL 2025 | E4: Febrero´25 | S4: =I234 -> -3120.3576
B5: ABRIL'2025 | D5: =S234+T234+U234 -> 538935.64 | E5: Marzo'25 | S5: =J234 -> 4085.4512
B6: Recuperación del 01 al 06 | D6: =SUM(V234:AA234) -> 118029.79 | E6: Abril´25 | S6: =K234 -> 0
B7: Recuperación del 07 al 13 | D7: =SUM(AB234:AH234) -> 100622.04 | E7: Mayo´25 | S7: =L234 -> 0
B8: Recuperación del 14 al 20 | D8: =SUM(AI234:AO234) -> 100082.12 | E8: Junio´25 | S8: =M234 -> 0
B9: Recuperación del 21 al 27 | D9: =SUM(AP234:AV234) -> 127665.74 | E9: Julio´25 | S9: =N234 -> 0
B10: Recuperación del 28 al 30 | D10: =SUM(AW234:AY234) -> 14638 | E10: Agosto'25 | S10: =O234 -> 0
E11: Septiembre'25 | S11: =P234 -> 0
E12: Octubre'25 | S12: =Q234 -> 0
B13: Total Recuperado | D13: =SUM(D6:D11) -> 461037.69 | E13: Noviembre'25 | S13: =R234 -> 0
B14: Por Recuperar | D14: =D2-D13 -> 118337.45 | E14: Total de Arrastre: | S14: =SUM(S2:S13) -> 40439.5
A16: NO. | B16: CLIENTE | C16: DATOS FISCALES | D16: CONTACTO | E16: UNI | F16: VENTA | G16: ATRASO | S16: IMPORTE ABRIL´2025 | T16: SERV. EXTRAS | U16: DES % | V16: 1 | W16: 2 | X16: 3 | Y16: 4 | Z16: 5 | AA16: 6 | AB16: 7 | AC16: 8 | AD16: 9 | AE16: 10 | AF16: 11 | AG16: 12 | AH16: 13 | AI16: 14 | AJ16: 15 | AK16: 16 | AL16: 17 | AM16: 18 | AN16: 19 | AO16: 20 | AP16: 21 | AQ16: 22 | AR16: 23 | AS16: 24 | AT16: 25 | AU16: 26 | AV16: 27 | AW16: 28 | AX16: 29 | AY16: 30 | AZ16: SALDOS PENDIENTES | BA16: COMENTARIOS | BB16: ESTATUS PROMESA DE PAGO
G17: 2024 | H17: ENE | I17: FEB | J17: MAR | K17: ABR | L17: MAY | M17: JUN | N17: JUL | O17: AGO | P17: SEP | Q17: OCT | R17: NOV | V17: M | W17: M | X17: J | Y17: V | Z17: S | AA17: D | AB17: L | AC17: M | AD17: M | AE17: J | AF17: V | AG17: S | AH17: D | AI17: L | AJ17: M | AK17: M | AL17: J | AM17: V | AN17: S | AO17: D | AP17: L | AQ17: M | AR17: M | AS17: J | AT17: V | AU17: S | AV17: D | AW17: L | AX17: M | AY17: M
A18: 1 | B18: ALIMENTOS REGIOMONTANOS PERCAM - ALIMENTOS GRUPER | C18: Nombre de la Empresa: ALIMENTOS GUPER S.A. DE C.V. Contacto: Nancy Paola Perales Teléfono: 811 801 4266 Email: alimentosgupersacv@gmail.com | D18: Alejandro Garcia - 81 2034 3938 Nancy Paola Perales - 8118014266 Alimentosregiopercam@gmail.com alimentosgupersacv@gmail.com | E18: 18 | F18: DANIEL ESTRADA | G18: =[1]DICIEMBRE!$BA$21 -> -0.3952 | H18: =ENERO!BA19 -> -0.3952 | I18: =FEBRERO!AX19 -> 0.0048 | J18: =MARZO!BA19 -> 0.0048 | S18: =(300*0.16+300)*E18 -> 6264 | T18: =500*0.16+500 -> 580 | W18: 6844 | AZ18: =SUM(J18+S18+T18-U18-V18-W18-X18-Y18-Z18-AA18-AB18-AC18-AD18-AE18-AF18-AG18-AH18-AI18-AJ18-AK18-AL18-AM18-AN18-AO18-AP18-AQ18-AR18-AS18-AT18-AU18-AV18-AW18-AX18-AY18) -> 0.0048 | BA18: COB. ABR'25: 1 REVISION
A19: 2 | B19: AUTO EXPRESS GERAL 21 S.A. DE C.V. - LUIS GERARDO BOLAÑOS GARCIA | C19: Nombre de la Empresa: LUIS GERARDO BOLAÑOS GARCIA RFC. BOGL8702094H5 CFDI: Gastos en general Forma de Pago: Transferencia Teléfono: 811 027 0226 Contacto: Luis Gerardo Bolaños García Email: luismty0902@gmail.com; | D19: Luis Gerardo Bolaños García - 811 027 0226 Email:expressgeral19@gmail.com luismty0902@gmail.com | E19: 5 | F19: JOSE LUIS | G19: =[1]DICIEMBRE!$BA$75 -> 3190.0028 | H19: =ENERO!BA20 -> 0.0028 | I19: =FEBRERO!AX20 -> 0.0028 | J19: =MARZO!BA20 -> 0.0028 | S19: =(280*0.16+280)*E19 -> 1624 | AE19: 1624 | AZ19: =SUM(J19+S19+T19-U19-V19-W19-X19-Y19-Z19-AA19-AB19-AC19-AD19-AE19-AF19-AG19-AH19-AI19-AJ19-AK19-AL19-AM19-AN19-AO19-AP19-AQ19-AR19-AS19-AT19-AU19-AV19-AW19-AX19-AY19) -> 0.0028
A20: 3 | B20: AUTOEXPRESS MATA | C20: Nombre de la Empresa: AUTOEXPRESS MATA S.A. DE C.V. RFC. AMA040520BZ2 CFDI : Forma de Pago: Transferencia Teléfono: 81 1029 1017 Contacto: Edgar Garza Email: | D20: COMODATO Edgar Garza - 81 1029 1017 Aexpresmata@gmail.com | E20: 4 | F20: JOSE LUIS | G20: =[1]DICIEMBRE!$BA$23 -> -0.0032 | H20: =ENERO!BA21 -> -0.0032 | I20: =FEBRERO!AX21 -> -0.0032 | J20: =MARZO!BA21 -> -0.0032 | S20: =(299*0.16+299)*E20 -> 1387.36 | AQ20: 1387.36 | AZ20: =SUM(J20+S20+T20-U20-V20-W20-X20-Y20-Z20-AA20-AB20-AC20-AD20-AE20-AF20-AG20-AH20-AI20-AJ20-AK20-AL20-AM20-AN20-AO20-AP20-AQ20-AR20-AS20-AT20-AU20-AV20-AW20-AX20-AY20) -> -0.0032
A21: 4 | B21: AUTOREDES EL BAJIO | D21: COMODATO Mane Troncoso -833 192 6706 Email:admontubored@hotmail.com | E21: 10 | F21: JOSE LUIS | G21: =[1]DICIEMBRE!$BA$24 -> -0.3952 | H21: =ENERO!BA22 -> -0.3952 | I21: =FEBRERO!AX22 -> 0.0048 | J21: =MARZO!BA22 -> 0.0048 | S21: =(270*0.16+270)*E21 -> 3132 | W21: 3132 | AZ21: =SUM(J21+S21+T21-U21-V21-W21-X21-Y21-Z21-AA21-AB21-AC21-AD21-AE21-AF21-AG21-AH21-AI21-AJ21-AK21-AL21-AM21-AN21-AO21-AP21-AQ21-AR21-AS21-AT21-AU21-AV21-AW21-AX21-AY21) -> 0.0048
A22: 5 | B22: BAWOMA CONTROL TOTAL S.A. DE C.V. - FUMIGAZ | C22: Nombre de la Empresa: BAWOMA CONTROL TOTAL S.A. DE C.V. RFC.: BCT100310834 CFDI: Gastos en General Forma de Pago: Transferencia Teléfono: 81 1811 0645 Contacto: Manuel Rico Email: supervisorfumigaz@outlook.com | D22: COMODATO Manuel Rico - 81 1811 0645 Email:supervisorfumigaz@outlook.com | E22: 2 | F22: JOSE LUIS | G22: =[1]DICIEMBRE!$BA$48 -> 696 | H22: =ENERO!BA23 -> 696 | I22: =FEBRERO!AX23 -> 0 | J22: =MARZO!BA23 -> 0 | S22: =(300*0.16+300)*1 -> 348 | AT22: 348 | AZ22: =SUM(J22+S22+T22-U22-V22-W22-X22-Y22-Z22-AA22-AB22-AC22-AD22-AE22-AF22-AG22-AH22-AI22-AJ22-AK22-AL22-AM22-AN22-AO22-AP22-AQ22-AR22-AS22-AT22-AU22-AV22-AW22-AX22-AY22) -> 0 | BA22: PDTE. 1 DES-INST. YA PAGADA
A23: 6 | B23: BE ONE SYSTEMS | D23: Lydia Colunga - 81 1176 3598 Edgar Valentin (Pagos) - 81 1970 7000 Email:edgar.valentin@beone.mx lydia@beone.mx | E23: 1 | F23: JOSE LUIS | G23: =[1]DICIEMBRE!$BA$25 -> 0 | H23: =ENERO!BA24 -> 0 | I23: =FEBRERO!AX24 -> 0 | J23: =MARZO!BA24 -> 0 | S23: =250*0.16+250 -> 290 | W23: 290 | AZ23: =SUM(J23+S23+T23-U23-V23-W23-X23-Y23-Z23-AA23-AB23-AC23-AD23-AE23-AF23-AG23-AH23-AI23-AJ23-AK23-AL23-AM23-AN23-AO23-AP23-AQ23-AR23-AS23-AT23-AU23-AV23-AW23-AX23-AY23) -> 0
A24: 7 | B24: BRANDO IVAN MARTINEZ GOVEA - JOSUE FERNANDEZ | D24: Josue Fernandez - 81 1977 0958 Email:jfhz@icloud.com | E24: 5 | F24: JOSE LUIS | G24: =[1]DICIEMBRE!$BA$64 -> 0.0068 | H24: =ENERO!BA25 -> 0.0068 | I24: =FEBRERO!AX25 -> -0.0032 | J24: =MARZO!BA25 -> -0.0032 | S24: =(250*0.16+250)*E24 -> 1450 | Y24: 1450 | AZ24: =SUM(J24+S24+T24-U24-V24-W24-X24-Y24-Z24-AA24-AB24-AC24-AD24-AE24-AF24-AG24-AH24-AI24-AJ24-AK24-AL24-AM24-AN24-AO24-AP24-AQ24-AR24-AS24-AT24-AU24-AV24-AW24-AX24-AY24) -> -0.0032
A25: 8 | B25: CARLOS JONATHAN MARTINEZ RIVERA | D25: Jonathan Rivera - 81 1696 5321 jonathanrivera22929@gmail.com | E25: 1 | F25: JOSE LUIS | G25: =[1]DICIEMBRE!$BA$134 -> 0 | H25: =ENERO!BA139 -> 48 | I25: =FEBRERO!AX26 -> 0 | J25: =MARZO!BA26 -> 0 | S25: =(300*0.16+300)*E25 -> 348 | AC25: 348 | AZ25: =SUM(J25+S25+T25-U25-V25-W25-X25-Y25-Z25-AA25-AB25-AC25-AD25-AE25-AF25-AG25-AH25-AI25-AJ25-AK25-AL25-AM25-AN25-AO25-AP25-AQ25-AR25-AS25-AT25-AU25-AV25-AW25-AX25-AY25) -> 0
A26: 9 | B26: CARNES RIBHAUS | D26: COMODATO Tania Reyes - 81 1631 2529 Roberta Treviño - 81 1909 7008 Email:facturas@carnesribhaus.com.mx robertaribhaus@gmail.com | E26: 5 | F26: JOSE LUIS | G26: =[1]DICIEMBRE!$BA$27 -> 0.004 | H26: =ENERO!BA26 -> 0.004 | I26: =FEBRERO!AX27 -> 0.004 | J26: =MARZO!BA27 -> 0.004 | S26: =(279*0.16+279)*E26 -> 1618.2 | X26: 1618.2 | AZ26: =SUM(J26+S26+T26-U26-V26-W26-X26-Y26-Z26-AA26-AB26-AC26-AD26-AE26-AF26-AG26-AH26-AI26-AJ26-AK26-AL26-AM26-AN26-AO26-AP26-AQ26-AR26-AS26-AT26-AU26-AV26-AW26-AX26-AY26) -> 0.004
A27: 10 | B27: CARPACK, S.A. DE C.V. | C27: Nombre de la Empresa: CARPACK S.A. DE C.V. RFC.: CAR070302UU2 CFDI: Gastos en General Forma de Pago: TransferenciaTeléfono: 811 277 9070 Contacto: Kelly Mayorga Email: compras@carpack.com.mx; antonioespinosa@carpack.com.mx; elizabeth@carpack.com.mx; | D27: COMODATO Kelly Mayorga - 8112779070 Elizabeth Campos - 8116635976 8181919205 Ext. 107 Email:antonioespinosa@carpack.com.mx; elizabeth@carpack.com.mx; compras@carpack.com.mx; pagos@carpack.com.mx | E27: 5 | F27: JOSE LUIS | G27: =[1]DICIEMBRE!$BA$28 -> 0.0028 | H27: =ENERO!BA27 -> 0.0028 | I27: =FEBRERO!AX28 -> 0.0028 | J27: =MARZO!BA28 -> 0.0028 | S27: =(280*0.16+280)*E27 -> 1624 | X27: 1624 | AZ27: =SUM(J27+S27+T27-U27-V27-W27-X27-Y27-Z27-AA27-AB27-AC27-AD27-AE27-AF27-AG27-AH27-AI27-AJ27-AK27-AL27-AM27-AN27-AO27-AP27-AQ27-AR27-AS27-AT27-AU27-AV27-AW27-AX27-AY27) -> 0.0028
A28: 11 | B28: COMERCIALIZADORA AGROPECUARIA ICK -JORGE ADRIAN RIVERA | C28: Nombre de la Empresa: COMERCIALIZADORA AGROPECUARIA ICK S.A. DE C.V. RFC.: CAI220330VD7 CFDI: Gastos en general Teléfono: 81 2860 1814 Contacto: Adrian Rivera Email: adrian.rmoxica75@gmail.com | D28: COMODATO Adrian Rivera - 81 2860 1814 Email:adrian.rmoxica75@gmail.com | E28: 4 | F28: JOSE LUIS | G28: =[1]DICIEMBRE!$BA$20 -> 0 | H28: =ENERO!BA28 -> 0 | I28: =FEBRERO!AX29 -> 0 | J28: =MARZO!BA29 -> 0 | S28: =(300*0.16+300)*E28 -> 1392 | X28: 1392 | AZ28: =SUM(J28+S28+T28-U28-V28-W28-X28-Y28-Z28-AA28-AB28-AC28-AD28-AE28-AF28-AG28-AH28-AI28-AJ28-AK28-AL28-AM28-AN28-AO28-AP28-AQ28-AR28-AS28-AT28-AU28-AV28-AW28-AX28-AY28) -> 0
A29: 12 | B29: COMERCIALIZADORA FUERZA CEMENTERA | D29: Candy - 81 2634 9644 candymoreno@forzadelnorte.com | E29: 5 | F29: JOSE LUIS | G29: =[1]DICIEMBRE!$BA$31 -> -3480 | H29: =ENERO!BA29 -> -1740 | I29: =FEBRERO!AX30 -> 0 | J29: =MARZO!BA30 -> -3480 | S29: =(300*0.16+300)*E29 -> 1740 | AZ29: =SUM(J29+S29+T29-U29-V29-W29-X29-Y29-Z29-AA29-AB29-AC29-AD29-AE29-AF29-AG29-AH29-AI29-AJ29-AK29-AL29-AM29-AN29-AO29-AP29-AQ29-AR29-AS29-AT29-AU29-AV29-AW29-AX29-AY29) -> -1740 | BA29: PAGO 3 MESES COBRAR HASTA JUNIO 2025
A30: 13 | B30: COMERCIALIZADORA Y LOGISTICA SIFAL - ARTURO SIFUENTES | D30: Arturo Sifuentes - 811 521 3582 Email: silvia-neri@hotmail.com; ventas@acertrans.com.mx; logisticasifal@hotmail.com; | E30: 5 | F30: JOSE LUIS | G30: =[1]DICIEMBRE!$BA$18 -> -128 | H30: =ENERO!BA30 -> -128 | I30: =FEBRERO!AX31 -> -128 | J30: =MARZO!BA31 -> -128 | S30: =(350*0.16+350)*E30 -> 2030 | AK30: 2030 | AZ30: =SUM(J30+S30+T30-U30-V30-W30-X30-Y30-Z30-AA30-AB30-AC30-AD30-AE30-AF30-AG30-AH30-AI30-AJ30-AK30-AL30-AM30-AN30-AO30-AP30-AQ30-AR30-AS30-AT30-AU30-AV30-AW30-AX30-AY30) -> -128
A31: 14 | B31: COMPAÑÍA MADERERA CUAUHTEMOC | D31: COMODATO Daniel Cardenas - 81 2634 0402 Email:recepcionfacturas@ciamaderera.com | E31: 6 | F31: JOSE LUIS | G31: =[1]DICIEMBRE!$BA$77 -> 0.0012 | H31: =ENERO!BA31 -> 0.0012 | I31: =FEBRERO!AX32 -> 0.0012 | J31: =MARZO!BA32 -> 0.0012 | S31: =(250*0.16+250)*5+(300*0.16+300)*1 -> 1798 | T31: =650*0.16+650 -> 754 | Y31: 2552 | AZ31: =SUM(J31+S31+T31-U31-V31-W31-X31-Y31-Z31-AA31-AB31-AC31-AD31-AE31-AF31-AG31-AH31-AI31-AJ31-AK31-AL31-AM31-AN31-AO31-AP31-AQ31-AR31-AS31-AT31-AU31-AV31-AW31-AX31-AY31) -> 0.0012 | BA31: COB. ABR'25: 1 INST. NUEVA
A32: 15 | B32: CONTINENTAL PARABELLUM - GRUPO SAR | D32: Alan Rodriguez finanzas.gposar@gmail.com | E32: 6 | F32: MARIO ULISES | G32: =[1]DICIEMBRE!$BA$32 -> 0 | H32: =ENERO!BA32 -> -0.004 | I32: =FEBRERO!AX33 -> -0.004 | J32: =MARZO!BA33 -> -0.004 | S32: =(279*0.16+279)*E32 -> 1941.84 | AF32: 1941.84 | AZ32: =SUM(J32+S32+T32-U32-V32-W32-X32-Y32-Z32-AA32-AB32-AC32-AD32-AE32-AF32-AG32-AH32-AI32-AJ32-AK32-AL32-AM32-AN32-AO32-AP32-AQ32-AR32-AS32-AT32-AU32-AV32-AW32-AX32-AY32) -> -0.004
A33: 16 | B33: DISTRIBUIDORA FERRELECTRICA Y MATERIALES EXPRESS - DEX MATERIALES | D33: Aleyda - 81 3402 1812 Rolando Ziragem 811 077 1470 812 597 2700 / 812 332 3606 oficina@dexmateriales.com; rzgc@hotmail.com; rolando@dexmateriales.com; | E33: 9 | F33: JOSE LUIS | G33: =[1]DICIEMBRE!$BA$34 -> 0 | H33: =ENERO!BA34 -> 0 | I33: =FEBRERO!AX35 -> 0 | J33: =MARZO!BA34 -> -15660 | S33: =(300*0.16+300)*E33 -> 3132 | AZ33: =SUM(J33+S33+T33-U33-V33-W33-X33-Y33-Z33-AA33-AB33-AC33-AD33-AE33-AF33-AG33-AH33-AI33-AJ33-AK33-AL33-AM33-AN33-AO33-AP33-AQ33-AR33-AS33-AT33-AU33-AV33-AW33-AX33-AY33) -> -12528 | BA33: PAGARA 6 MENS. COBRAR HASTA EL MES DE SEPTIEMBRE 2025 CAMBIA A ESQUEMA DE MENSUALIDAD 06-SEPTIEMBRE-2024 Y DA DE BAJA 3 UNIDADES Y SE SEPARA CUENTA A COMERCIALIZADORA FUERZA CEMENTERA
A34: 17 | B34: EDGAR ALBERTO CORTEZ TREVIÑO | D34: Edgar Cortez - 81 8185 6454 | E34: 1 | F34: JOSE LUIS | G34: =[1]DICIEMBRE!$BA$35 -> 0 | H34: =ENERO!BA35 -> 0 | I34: =FEBRERO!AX36 -> 0 | J34: =MARZO!BA35 -> 0 | S34: =(250*0.16+250)*E34 -> 290 | Y34: 290 | AZ34: =SUM(J34+S34+T34-U34-V34-W34-X34-Y34-Z34-AA34-AB34-AC34-AD34-AE34-AF34-AG34-AH34-AI34-AJ34-AK34-AL34-AM34-AN34-AO34-AP34-AQ34-AR34-AS34-AT34-AU34-AV34-AW34-AX34-AY34) -> 0
A35: 18 | B35: ELIZABETH RENTERIA REVILLA | C35: Nombre de la Empresa: ELIZABETH RENTERÍA REVILLA RFC. RERE760807SX9 CFDI: Gastos en general Forma de Pago: TransferenciaTeléfono: 811 810 0155 Contacto: Elizabeth Rentería Email: e.lic@live.com.mx | D35: Elizabeth Renteria - 811 810 0155 Email:e.lic@live.com.mx | E35: 3 | F35: JOSE LUIS | G35: =[1]DICIEMBRE!$BA$37 -> 0 | H35: =ENERO!BA36 -> 0 | I35: =FEBRERO!AX37 -> -0.0044 | J35: =MARZO!BA36 -> -0.0044 | S35: =(250*0.16+250)*E35 -> 870 | T35: =2016.66*0.16+2016.66 -> 2339.3256 | X35: 3209.32 | AZ35: =SUM(J35+S35+T35-U35-V35-W35-X35-Y35-Z35-AA35-AB35-AC35-AD35-AE35-AF35-AG35-AH35-AI35-AJ35-AK35-AL35-AM35-AN35-AO35-AP35-AQ35-AR35-AS35-AT35-AU35-AV35-AW35-AX35-AY35) -> 0.0012 | BA35: COB. ABR'25: 1 EQP. E INST. NUEVA Y 1 MENS. PROP. 20 DIAS
A36: 19 | B36: ENDER INDUSTRIAL (EMMANUEL VAZQUEZ - SINERGIX ) | C36: Nombre de la Empresa: ENDER INDUSTRIAL S.A. DE C.V. RFC.: SIS1703089V6 CFDI: Gastos en General. Forma de Pago: Transferencia Teléfono: 813 055 7409 / 81) 2141 0506 Contacto: Emmanuel Vázquez / Sonia Lugo Email: emmanuel@sinergix.net; sonia@sinergix.net; | D36: COMODATO Emmanuel Vazquez - 81 3055 7409 Sonia Lugo (pagos) - 81 2141 0506 Email:sandra@enderindustrial.com claudia@enderindustrial.com belen@enderindustrial.com facturas@enderindustrial.com; emmanuel@sinergix.net; | E36: 7 | F36: JOSE LUIS | G36: =[1]DICIEMBRE!$BA$38 -> -753.9924 | H36: =ENERO!BA37 -> -753.9924 | I36: =FEBRERO!AX38 -> -753.9924 | J36: =MARZO!BA37 -> -753.9924 | S36: =(350*0.16+350)*E36 -> 2842 | Y36: 2842 | AZ36: =SUM(J36+S36+T36-U36-V36-W36-X36-Y36-Z36-AA36-AB36-AC36-AD36-AE36-AF36-AG36-AH36-AI36-AJ36-AK36-AL36-AM36-AN36-AO36-AP36-AQ36-AR36-AS36-AT36-AU36-AV36-AW36-AX36-AY36) -> -753.9924
A37: 20 | B37: ENDO LASER MICROQUIRURGICO - INSTITUTO VIDAURRI DE OJOS (DANIELA MEDELLIN) | D37: Daniela Medellín - 81 1588 8485 Email:monitoreo@endolaser.com.mx | E37: 4 | F37: JOSE LUIS | G37: =[1]DICIEMBRE!$BA$59 -> 6.8212103e-13 | H37: =ENERO!BA38 -> 9.094947e-13 | I37: =FEBRERO!AX39 -> 1.1368684e-12 | J37: =MARZO!BA38 -> 1.3642421e-12 | S37: =(249*0.16+249)*E37 -> 1155.36 | Y37: 1155.36 | AZ37: =SUM(J37+S37+T37-U37-V37-W37-X37-Y37-Z37-AA37-AB37-AC37-AD37-AE37-AF37-AG37-AH37-AI37-AJ37-AK37-AL37-AM37-AN37-AO37-AP37-AQ37-AR37-AS37-AT37-AU37-AV37-AW37-AX37-AY37) -> 1.5916157e-12
A38: 21 | B38: EXTINTORES Y EQUIPOS MONTERREY (SERGIO GONZALEZ) | D38: COMODATO Gabriela - 81 2077 4512 Sergio Gonzalez - 81 8654 2753 sergio.jr987@outlook.com | E38: 2 | F38: JOSE LUIS | G38: =[1]DICIEMBRE!$BA$41 -> 0 | H38: =ENERO!BA39 -> 0 | I38: =FEBRERO!AX40 -> 0 | J38: =MARZO!BA39 -> 0 | S38: =(300*0.16+300)*2 -> 696 | AB38: 696 | AZ38: =SUM(J38+S38+T38-U38-V38-W38-X38-Y38-Z38-AA38-AB38-AC38-AD38-AE38-AF38-AG38-AH38-AI38-AJ38-AK38-AL38-AM38-AN38-AO38-AP38-AQ38-AR38-AS38-AT38-AU38-AV38-AW38-AX38-AY38) -> 0 | BA38: PDTE 1 INSTALACION YA PAGADA SOLO COBRAR PROP. CUANDO SE INSTALE
A39: 22 | B39: FERNANDO RAFAEL GONZALEZ MONTEMAYOR (SERVICIO DE PLATAFORMA) | C39: Nombre de la Empresa: GOMO SERVICES Contacto: FERNANDO DISATEL Email: frgm_76@hotmail.com Remisiones con IVA | D39: Fernando Disatel - 81 1799 2490 Email:frgm_76@hotmail.com | E39: 674 | F39: JOSE LUIS | G39: =[1]DICIEMBRE!$BA$42 -> 3220.026 | H39: =ENERO!BA40 -> 3220.026 | I39: =FEBRERO!AX41 -> 3220.028 | J39: =MARZO!BA40 -> 3220.03 | S39: =(38.8*0.16+38.8)*E39 -> 30335.392 | AS39: 30335.39 | AZ39: =SUM(J39+S39+T39-U39-V39-W39-X39-Y39-Z39-AA39-AB39-AC39-AD39-AE39-AF39-AG39-AH39-AI39-AJ39-AK39-AL39-AM39-AN39-AO39-AP39-AQ39-AR39-AS39-AT39-AU39-AV39-AW39-AX39-AY39) -> 3220.032
A40: 23 | B40: FERNANDO REYES HERNANDES | D40: COMODATO Fernando Reyes - 81 1821 3781 Viridiana Flores - 81 1796 4130 arnol84reyeshdz@gmail.com | E40: 1 | F40: JOSE LUIS | G40: =[1]DICIEMBRE!$BA$43 -> 348 | H40: =ENERO!BA41 -> 0 | I40: =FEBRERO!AX42 -> 0 | J40: =MARZO!BA41 -> 0 | S40: =(300*0.16+300)*E40 -> 348 | AW40: 348 | AZ40: =SUM(J40+S40+T40-U40-V40-W40-X40-Y40-Z40-AA40-AB40-AC40-AD40-AE40-AF40-AG40-AH40-AI40-AJ40-AK40-AL40-AM40-AN40-AO40-AP40-AQ40-AR40-AS40-AT40-AU40-AV40-AW40-AX40-AY40) -> 0
A41: 24 | B41: FINPAIS | C41: Nombre de la Empresa: FINPAIS S.A. DE C.V. RFC. FCO130429629 CFDI: Gastos en general Forma de Pago: TransferenciaTeléfono: 81 8208 7559 Contacto: Katty Email: administracion@finpais.com.mx | D41: COMODATO Katty - 81 8208 7559 Email:administracion@finpais.com.mx | E41: 7 | F41: JOSE LUIS | G41: =[1]DICIEMBRE!$BA$44 -> 2598.3956 | H41: =ENERO!BA42 -> 5486.7956 | I41: =FEBRERO!AX43 -> 8085.1956 | J41: =MARZO!BA42 -> 10683.596 | S41: =(320*0.16+320)*E41 -> 2598.4 | AR41: 8085.2 | AZ41: =SUM(J41+S41+T41-U41-V41-W41-X41-Y41-Z41-AA41-AB41-AC41-AD41-AE41-AF41-AG41-AH41-AI41-AJ41-AK41-AL41-AM41-AN41-AO41-AP41-AQ41-AR41-AS41-AT41-AU41-AV41-AW41-AX41-AY41) -> 5196.7956
A42: 25 | B42: FINXERT - FERNANDO VILLARREAL | D42: Fernando Villarreal - 81 2348 6430 | E42: 6 | G42: =[1]DICIEMBRE!$BA$45 -> 0 | H42: =ENERO!BA43 -> 0.0012 | I42: =FEBRERO!AX44 -> -0.0004 | J42: =MARZO!BA43 -> -0.0004 | S42: =(290*0.16+290)*E42 -> 2018.4 | T42: =2432*0.16+2432 -> 2821.12 | AS42: 4839.52 | AZ42: =SUM(J42+S42+T42-U42-V42-W42-X42-Y42-Z42-AA42-AB42-AC42-AD42-AE42-AF42-AG42-AH42-AI42-AJ42-AK42-AL42-AM42-AN42-AO42-AP42-AQ42-AR42-AS42-AT42-AU42-AV42-AW42-AX42-AY42) -> -0.0004 | BA42: COB. ABR'25: 1 EQP. E INST. NUEVA Y 1 MENS. PROP. 24 DIAS
A43: 26 | B43: FLETES ESPECIALIZADOS AGL | D43: COMODATO Sr. Ariel - 81 1974 2676 fletesagl@gmail.com | E43: 18 | F43: JOSE LUIS | G43: =[1]DICIEMBRE!$BA$46 -> 9.094947e-13 | H43: =ENERO!BA44 -> 9.094947e-13 | I43: =FEBRERO!AX45 -> 0.002 | J43: =MARZO!BA44 -> 0.002 | S43: =(300*0.16+300)*E43 -> 6264 | AB43: 6264 | AZ43: =SUM(J43+S43+T43-U43-V43-W43-X43-Y43-Z43-AA43-AB43-AC43-AD43-AE43-AF43-AG43-AH43-AI43-AJ43-AK43-AL43-AM43-AN43-AO43-AP43-AQ43-AR43-AS43-AT43-AU43-AV43-AW43-AX43-AY43) -> 0.002
A44: 27 | B44: FREIGHT HP-PACK MEXICO (DAVID FRANCISCO ARCOS) | D44: COMODATO Carlos Salinas - (201) 748 9020 David Francisco - 81 1033 1916 davidarcosfrancisco1991@gmail.com | E44: 22 | F44: JOSE LUIS | H44: =ENERO!BA45 -> 9604.8 | I44: =FEBRERO!AX46 -> 1380.864 | J44: =MARZO!BA45 -> 0.004 | S44: =(279*0.16+279)*E44 -> 7120.08 | T44: =12497*0.16+12497 -> 14496.52 | AG44: 7120.08 | AZ44: =SUM(J44+S44+T44-U44-V44-W44-X44-Y44-Z44-AA44-AB44-AC44-AD44-AE44-AF44-AG44-AH44-AI44-AJ44-AK44-AL44-AM44-AN44-AO44-AP44-AQ44-AR44-AS44-AT44-AU44-AV44-AW44-AX44-AY44) -> 14496.524 | BA44: COB. ABR'25: INTEGRACION DE WEB SERVICE POR 15 UNIDADES
A45: 28 | B45: GEORGINA MELISSA GOMEZ RODELA - PETROVACTOR | C45: Nombre de la Empresa: GEORGINA MELISSA GOMEZ RODELA RFC.: GORG8204295H5 CFDI: Gastos en General Forma de Pago: Transferencia Teléfono: 833 104 3672 Gisela Suarez - 81 1049 7882 Contacto: Griselda Suarez (Petrovactor) Email: griselda@petrovactor.com; facturagmgr@gmail.com; | D45: Georgina Gomez - 833 134 5812 Anahí Juarez - 833 104 3672 Email:facturagmgr@gmail.com; anaiwork7@gmail.com | E45: 14 | F45: JOSE LUIS | G45: =[1]DICIEMBRE!$BA$50 -> -0.0004 | H45: =ENERO!BA46 -> -0.0004 | I45: =FEBRERO!AX47 -> -0.0004 | J45: =MARZO!BA46 -> -0.0004 | S45: =(250*0.16+250)*E45 -> 4060 | T45: =650*0.16+650 -> 754 | AC45: 4814 | AZ45: =SUM(J45+S45+T45-U45-V45-W45-X45-Y45-Z45-AA45-AB45-AC45-AD45-AE45-AF45-AG45-AH45-AI45-AJ45-AK45-AL45-AM45-AN45-AO45-AP45-AQ45-AR45-AS45-AT45-AU45-AV45-AW45-AX45-AY45) -> -0.0004 | BA45: COB. ABR'25: 1 REVISION
A46: 29 | B46: GRUPO CASTOR ACERTIVA CONSTRUCCIONES, S.A. DE C.V. (CASTOR) | C46: Nombre de la Empresa: ACERTIVA CONTRUCCIONES S.A. DE C.V. RFC. ACO9605025G2 CFDI: Comunicaciones Satelitales Forma de Pago: Transferencia Teléfono: 818 347 7712 / 13 ext. 106 Contacto: Sr. Santos / Srta.(s) Janeth Villa / Karla Guerra / Fabiola García Email: fabiola.garcia@lsadministracion.com | D46: Srta. Janeth Villa 81 8347 7712 / 13 Ext. 106 Email:fabiola.garcia@lsadministracion.com; | E46: 1 | F46: JOSE LUIS | G46: =[1]DICIEMBRE!$BA$52 -> 0 | H46: =ENERO!BA47 -> 0 | I46: =FEBRERO!AX48 -> 0 | J46: =MARZO!BA47 -> 0 | S46: 348 | AZ46: =SUM(J46+S46+T46-U46-V46-W46-X46-Y46-Z46-AA46-AB46-AC46-AD46-AE46-AF46-AG46-AH46-AI46-AJ46-AK46-AL46-AM46-AN46-AO46-AP46-AQ46-AR46-AS46-AT46-AU46-AV46-AW46-AX46-AY46) -> 348
A47: 30 | B47: GRUPO CASTOR ORGANIZACIÓN CASTOR AG, S.A. DE C.V. | C47: Nombre de la Empresa: ORGANIZACIÓN CASTOR S. A. DE C. V. RFC. OCA121001RX9 CFDI: Comunicaciones Satelitales Forma de Pago: Transferencia Teléfono: 818 347 7712 / 13 ext. 106 Contacto: Sr. Santos / Srta.(s) Janeth Villa / Karla Guerra / Fabiola García Email: fabiola.garcia@lsadministracion.com | D47: Srta. Janeth Villa 81 8347 7712 / 13 Ext. 106 Email:fabiola.garcia@lsadministracion.com; | E47: 2 | F47: JOSE LUIS | G47: =[1]DICIEMBRE!$BA$53 -> 0 | H47: =ENERO!BA48 -> 0 | I47: =FEBRERO!AX49 -> 0 | J47: =MARZO!BA48 -> 0 | S47: 696 | AB47: 696 | AZ47: =SUM(J47+S47+T47-U47-V47-W47-X47-Y47-Z47-AA47-AB47-AC47-AD47-AE47-AF47-AG47-AH47-AI47-AJ47-AK47-AL47-AM47-AN47-AO47-AP47-AQ47-AR47-AS47-AT47-AU47-AV47-AW47-AX47-AY47) -> 0
A48: 31 | B48: GREGORY AJMEL MARTINEZ GARCIA (TEOURO TRANSPORTES) | D48: COMODATO Gregory Martínez García 81 1041 6798 greck_090@hotmail.com | E48: 3 | F48: JOSE LUIS | G48: =[1]DICIEMBRE!$BA$54 -> 0 | H48: =ENERO!BA49 -> 0 | I48: =FEBRERO!AX50 -> 0 | J48: =MARZO!BA49 -> 0 | S48: =(300*0.16+300)*E48 -> 1044 | AE48: 1044 | AZ48: =SUM(J48+S48+T48-U48-V48-W48-X48-Y48-Z48-AA48-AB48-AC48-AD48-AE48-AF48-AG48-AH48-AI48-AJ48-AK48-AL48-AM48-AN48-AO48-AP48-AQ48-AR48-AS48-AT48-AU48-AV48-AW48-AX48-AY48) -> 0
A49: 32 | B49: GRUPO AMBIENTAL Y RESIDUOS INDUSTRIALES S.A. DE C. V. (GARISA) | C49: Nombre de la Empresa: GRUPO AMBIENTAL Y RESIDUOS INDUSTRIALES S.A. DE C.V. RFC.: GAR1503063C1 CFDI: Gastos en General. Forma de Pago: Transferencia Electrónica Contacto: Verónica Coronado Teléfono: 812 165 1133 / 8119575404 Email: garisav@hotmail.com | D49: Veronica Coronado- 812 165 1133 / 811 957 5404 Email:garisav@hotmail.com | E49: 3 | F49: JOSE LUIS | G49: =[1]DICIEMBRE!$BA$49 -> 0 | H49: =ENERO!BA50 -> 0 | I49: =FEBRERO!AX51 -> 0 | J49: =MARZO!BA50 -> 0 | S49: =(300*0.16+300)*E49 -> 1044 | AF49: 1044 | AZ49: =SUM(J49+S49+T49-U49-V49-W49-X49-Y49-Z49-AA49-AB49-AC49-AD49-AE49-AF49-AG49-AH49-AI49-AJ49-AK49-AL49-AM49-AN49-AO49-AP49-AQ49-AR49-AS49-AT49-AU49-AV49-AW49-AX49-AY49) -> 0
A50: 33 | B50: GRUPO COMERCIAL CHAPA - MERARY OLVERA | D50: Merary Olvera Cazarez - 81 1741 9785 ventas1@comercialchaoa.com | E50: 1 | F50: JOSE LUIS | J50: =MARZO!BA51 -> 0 | S50: =(250*0.16+250)*E50 -> 290 | T50: =250*0.16+250 -> 290 | AE50: 580 | AZ50: =SUM(J50+S50+T50-U50-V50-W50-X50-Y50-Z50-AA50-AB50-AC50-AD50-AE50-AF50-AG50-AH50-AI50-AJ50-AK50-AL50-AM50-AN50-AO50-AP50-AQ50-AR50-AS50-AT50-AU50-AV50-AW50-AX50-AY50) -> 0 | BA50: COB. ABR'25: 1 VISITA EN FALSO
A51: 34 | B51: GRUPO DIESEL HH | D51: Marisol Alvarado - 33 3486 8750 / Norma Navarro Oficina - 33 1401 2246 33 1654 3312 Email:azulitalia@live.com.mx | E51: 4 | F51: JOSE LUIS | G51: =[1]DICIEMBRE!$BA$56 -> 0 | H51: =ENERO!BA51 -> 0 | I51: =FEBRERO!AX52 -> 0 | J51: =MARZO!BA52 -> 0 | S51: =(300*0.16+300)*E51 -> 1392 | W51: 1392 | AZ51: =SUM(J51+S51+T51-U51-V51-W51-X51-Y51-Z51-AA51-AB51-AC51-AD51-AE51-AF51-AG51-AH51-AI51-AJ51-AK51-AL51-AM51-AN51-AO51-AP51-AQ51-AR51-AS51-AT51-AU51-AV51-AW51-AX51-AY51) -> 0
A52: 35 | B52: HACIENDO EQUIPO EN TU PROYECTO - EQUIPREST | C52: Nombre de la Empresa: HACIENDO EQUIPO EN TU PROYECTO S.A. DE C.V. RFC. EMO180713MC1 CFDI : Gastos en General C.P.: 64000 Regimen Fiscal: R SIMPLIFICADO DE CONFIANZA Forma de Pago: Transferencia Teléfono: 81 2002 4556 Contacto: Oscar Herrera Email:compras@equiprestmx.com 1er Factura: 1951 | D52: Jessica Jasso - 81 2002 4556 Email:administracion@equiprestmx.com | E52: 3 | F52: JOSE LUIS | G52: =[1]DICIEMBRE!$BA$39 -> 9.094947e-13 | H52: =ENERO!BA52 -> 9.094947e-13 | I52: =FEBRERO!AX53 -> 9.094947e-13 | J52: =MARZO!BA53 -> 9.094947e-13 | S52: =(250*0.16+250)*E52 -> 870 | Y52: 870 | AZ52: =SUM(J52+S52+T52-U52-V52-W52-X52-Y52-Z52-AA52-AB52-AC52-AD52-AE52-AF52-AG52-AH52-AI52-AJ52-AK52-AL52-AM52-AN52-AO52-AP52-AQ52-AR52-AS52-AT52-AU52-AV52-AW52-AX52-AY52) -> 9.094947e-13
A53: 36 | B53: HECTOR ALVEAR AGUILAR - KARLA ALVEAR | C53: Nombre de la Empresa: HECTOR ALVEAR AGUILAR RFC. AEAH940117AV1 CFDI : Gastos en General C.P.:67250 Regimen Fiscal: R DE LAS PERSONAS FISICAS CON ACTIVIDADES EMPRESARIALES Y PROFESIONALES Forma de Pago: Transferencia Teléfono: 81 8050 5722 Contacto: Karla Vear Email: Hec_alvear@hotmail.com 1er Factura: 2068 | D53: Karla Alvear - 81 1800 0233 Email:Hec_alvear@hotmail.com | E53: 1 | F53: JOSE LUIS | G53: =[1]DICIEMBRE!$BA$67 -> 0 | H53: =ENERO!BA53 -> 0 | I53: =FEBRERO!AX54 -> 0 | J53: =MARZO!BA54 -> 0 | S53: =(300*0.16+300)*E53 -> 348 | AE53: 348 | AZ53: =SUM(J53+S53+T53-U53-V53-W53-X53-Y53-Z53-AA53-AB53-AC53-AD53-AE53-AF53-AG53-AH53-AI53-AJ53-AK53-AL53-AM53-AN53-AO53-AP53-AQ53-AR53-AS53-AT53-AU53-AV53-AW53-AX53-AY53) -> 0
A54: 37 | B54: INDUSTRIAL DE CARBON Y GRAFITO - CARBOGRAF | C54: Nombre de la Empresa: INDUSTRIAL DE CARBON Y GRAFITO, S.A. DE C.V. RFC: ICG 100106 UR0 CFDI: Gastos en general TEL: 16 42 2004 Contacto: Pablo Rodriguez Email: Elda@carbograf.com | D54: Daniela Cabello - 81 8273 6437 Email:julio.campos@carbograf.com marlene@carbograf.com | E54: 4 | F54: JOSE LUIS | G54: =[1]DICIEMBRE!$BA$26 -> 0.0032 | H54: =ENERO!BA54 -> 0.0032 | I54: =FEBRERO!AX55 -> 0.0032 | J54: =MARZO!BA55 -> 0.0032 | S54: =(349*0.16+349)*E54 -> 1619.36 | AE54: 1619.36 | AZ54: =SUM(J54+S54+T54-U54-V54-W54-X54-Y54-Z54-AA54-AB54-AC54-AD54-AE54-AF54-AG54-AH54-AI54-AJ54-AK54-AL54-AM54-AN54-AO54-AP54-AQ54-AR54-AS54-AT54-AU54-AV54-AW54-AX54-AY54) -> 0.0032
A55: 38 | B55: INDUSTRIAS PERSISTA LABORO S.A. DE C.V. (ERNESTO GOMEZ) | D55: COMODATO Ernesto Gómez - 81 2001 9256 ernesto.gomez@sanbox.com.mx | E55: 14 | F55: JOSE LUIS | G55: =[1]DICIEMBRE!$BA$58 -> 1525.0064 | H55: =ENERO!BA55 -> -0.0036 | I55: =FEBRERO!AX56 -> -0.0036 | J55: =MARZO!BA56 -> -0.0036 | S55: =(250*0.16+250)*E55 -> 4060 | T55: =(500*0.16+500)*2 -> 1160 | X55: 4350 | Y55: 870 | AZ55: =SUM(J55+S55+T55-U55-V55-W55-X55-Y55-Z55-AA55-AB55-AC55-AD55-AE55-AF55-AG55-AH55-AI55-AJ55-AK55-AL55-AM55-AN55-AO55-AP55-AQ55-AR55-AS55-AT55-AU55-AV55-AW55-AX55-AY55) -> -0.0036 | BA55: COB. ABR'25: 1 DES-INST. Y 1 RE-INST.
A56: 39 | B56: INVERSIONES QUINEXUS - PRESTACOCHE (FINANCIERA) | C56: Nombre de la Empresa: PRESTACOCHE Contacto: Rosy / Talía Carrizales Email: rosa.sr@quinexus.mx; talia.ci@quinexus.mx; Teléfono: 811 499 1431 / 812 147 3082 | D56: Rosy - 812 354 1373 Email:rosa.sr@quinexus.mx; | E56: 8 | F56: JOSE LUIS | G56: =[1]DICIEMBRE!$BA$85 -> 0.0048 | H56: =ENERO!BA56 -> 0.0048 | I56: =FEBRERO!AX57 -> 0.0048 | J56: =MARZO!BA57 -> 0.0048 | S56: =(220*0.16+220)*E56 -> 2041.6 | T56: =5200*0.16+5200 -> 6032 | Y56: 8073.6 | AZ56: =SUM(J56+S56+T56-U56-V56-W56-X56-Y56-Z56-AA56-AB56-AC56-AD56-AE56-AF56-AG56-AH56-AI56-AJ56-AK56-AL56-AM56-AN56-AO56-AP56-AQ56-AR56-AS56-AT56-AU56-AV56-AW56-AX56-AY56) -> 0.0048 | BA56: COB. ABR'25: 7 DES-INST. Y 1 REVISION
A57: 40 | B57: JAVIER ANGEL VELAZQUEZ SANCHEZ | C57: Nombre de la Empresa: JAVIER ANGEL VELAZQUEZ SANCHEZ RFC. VESJ4910026E3 CFDI: Comunicaciones satelitales Forma de Pago: Transferencia Teléfono: 812 032 0493 Contacto: Javier Ángel Velázquez Sánchez (FLETES ANGEL VELAZQUEZ) Email: fletesangelvelazquez@gmail.com | D57: Javier Velazquez - 812 032 0493 Email:fletesangelvelazquez@gmail.com | E57: 4 | F57: JOSE LUIS | G57: =[1]DICIEMBRE!$BA$60 -> -0.0048 | H57: =ENERO!BA57 -> -0.0048 | I57: =FEBRERO!AX58 -> -0.0048 | J57: =MARZO!BA58 -> -0.0048 | S57: =(330*0.16+330)*E57 -> 1531.2 | X57: 1531.2 | AZ57: =SUM(J57+S57+T57-U57-V57-W57-X57-Y57-Z57-AA57-AB57-AC57-AD57-AE57-AF57-AG57-AH57-AI57-AJ57-AK57-AL57-AM57-AN57-AO57-AP57-AQ57-AR57-AS57-AT57-AU57-AV57-AW57-AX57-AY57) -> -0.0048
A58: 41 | B58: JAVIER ARMENTA MARROQUIN | D58: Javier Armenta - 667 348 6917 | E58: 1 | F58: JOSE LUIS | J58: =MARZO!BA59 -> 0 | S58: =(799*0.16+799)*E58 -> 926.84 | T58: =481*0.16+481 -> 557.96 | Y58: 1484.8 | AZ58: =SUM(J58+S58+T58-U58-V58-W58-X58-Y58-Z58-AA58-AB58-AC58-AD58-AE58-AF58-AG58-AH58-AI58-AJ58-AK58-AL58-AM58-AN58-AO58-AP58-AQ58-AR58-AS58-AT58-AU58-AV58-AW58-AX58-AY58) -> 2.2737368e-13 | BA58: COB. ABR'25: 1 FINANCIAMIENTO DE DASH CAM MENS. 1/11
A59: 42 | B59: JESUS ALEJANDRO LOZANO LOZANO - TRANSPORTES TM | D59: ventas@autotransportes-jl.com administracion@autotransportes-jl.com | E59: 1 | F59: JOSE LUIS | G59: =[1]DICIEMBRE!$BA$100 -> 0 | H59: =ENERO!BA58 -> 0 | I59: =FEBRERO!AX59 -> 0 | J59: =MARZO!BA60 -> 0 | S59: =300*0.16+300 -> 348 | AZ59: =SUM(J59+S59+T59-U59-V59-W59-X59-Y59-Z59-AA59-AB59-AC59-AD59-AE59-AF59-AG59-AH59-AI59-AJ59-AK59-AL59-AM59-AN59-AO59-AP59-AQ59-AR59-AS59-AT59-AU59-AV59-AW59-AX59-AY59) -> 348
A60: 43 | B60: JOSE ANGEL MENDEZ ARRIAGA - TRANSPORTES 2M | C60: Nombre de la Empresa: TRANSPORTES 2M Contacto: José Ángel Méndez Arriaga Teléfono: 812 600 8976 Email: jama_ca@hotmail.com | D60: Jose Angel Mendez Arriaga - 812 600 8976 Email:jama_ca@hotmail.com | E60: 4 | F60: JOSE LUIS | G60: =[1]DICIEMBRE!$BA$98 -> -6 | H60: =ENERO!BA59 -> -6 | I60: =FEBRERO!AX60 -> 0 | J60: =MARZO!BA61 -> 0 | S60: =(300*0.16+300)*E60 -> 1392 | AA60: 1392 | AZ60: =SUM(J60+S60+T60-U60-V60-W60-X60-Y60-Z60-AA60-AB60-AC60-AD60-AE60-AF60-AG60-AH60-AI60-AJ60-AK60-AL60-AM60-AN60-AO60-AP60-AQ60-AR60-AS60-AT60-AU60-AV60-AW60-AX60-AY60) -> 0
A61: 44 | B61: JOSE MELQUIADES TOLEDO GARCIA DE LEON | D61: Jose Toledo - 81 1015 9453 Email:j.garcia@grupotranstech.com | E61: 2 | F61: JOSE LUIS | G61: =[1]DICIEMBRE!$BA$63 -> 2.2737368e-13 | H61: =ENERO!BA60 -> 2.2737368e-13 | I61: =FEBRERO!AX61 -> 2.2737368e-13 | J61: =MARZO!BA62 -> 2.2737368e-13 | S61: =(330*0.16+330)*E61 -> 765.6 | W61: 765.6 | AZ61: =SUM(J61+S61+T61-U61-V61-W61-X61-Y61-Z61-AA61-AB61-AC61-AD61-AE61-AF61-AG61-AH61-AI61-AJ61-AK61-AL61-AM61-AN61-AO61-AP61-AQ61-AR61-AS61-AT61-AU61-AV61-AW61-AX61-AY61) -> 2.2737368e-13
A62: 45 | B62: JUAN ANTONIO DE JESUS GARCIA RAMIREZ - TRANSPORTES GARCÍA | C62: Nombre de la Empresa: JUAN ANTONIO DE JESUS GARCIA RAMIREZ RFC. GARJ810921FM4 CFDI : Por Definir Forma de Pago: Transferencia Teléfono: 811 155 2769 Contacto: Antonio García Email: antoniotransgar@hotmail.es | D62: COMODATO Rosario Sanchez - 81 2161 6793 Antonio García - 81 1155 2769 Email:antoniotransgar@hotmail.es | E62: 14 | F62: JOSE LUIS | G62: =[1]DICIEMBRE!$BA$99 -> 0.004 | H62: =ENERO!BA61 -> 4693.364 | I62: =FEBRERO!AX62 -> 0.004 | J62: =MARZO!BA63 -> 4693.364 | S62: =(289*0.16+289)*E62 -> 4693.36 | AR62: 9386.72 | AZ62: =SUM(J62+S62+T62-U62-V62-W62-X62-Y62-Z62-AA62-AB62-AC62-AD62-AE62-AF62-AG62-AH62-AI62-AJ62-AK62-AL62-AM62-AN62-AO62-AP62-AQ62-AR62-AS62-AT62-AU62-AV62-AW62-AX62-AY62) -> 0.004
A63: 46 | B63: JUAN JAVIER CABRIALES CEDILLO (TRANSPORTES RCD) | D63: Juan Cabriales - 81 2947 2650 Email:transportes.rcd.diaz@gmail.com | E63: 4 | F63: JOSE LUIS | G63: =[1]DICIEMBRE!$BA$65 -> -0.0004 | H63: =ENERO!BA63 -> -0.0004 | I63: =FEBRERO!AX63 -> -0.0004 | J63: =MARZO!BA64 -> -0.0004 | S63: =(300*0.16+300)*E63 -> 1392 | W63: 1392 | AZ63: =SUM(J63+S63+T63-U63-V63-W63-X63-Y63-Z63-AA63-AB63-AC63-AD63-AE63-AF63-AG63-AH63-AI63-AJ63-AK63-AL63-AM63-AN63-AO63-AP63-AQ63-AR63-AS63-AT63-AU63-AV63-AW63-AX63-AY63) -> -0.0004
A64: 47 | B64: JUAN MEJIA HERNANDEZ | D64: Juan Mejia - 44 2160 1772 mejiahj@hotmail.com | E64: 1 | F64: JOSE LUIS | G64: =[1]DICIEMBRE!$BA$66 -> 0 | H64: =ENERO!BA64 -> 0 | I64: =FEBRERO!AX64 -> 0 | J64: =MARZO!BA65 -> 0 | S64: =(200*0.16+200)*E64 -> 232 | W64: 232 | AZ64: =SUM(J64+S64+T64-U64-V64-W64-X64-Y64-Z64-AA64-AB64-AC64-AD64-AE64-AF64-AG64-AH64-AI64-AJ64-AK64-AL64-AM64-AN64-AO64-AP64-AQ64-AR64-AS64-AT64-AU64-AV64-AW64-AX64-AY64) -> 0
A65: 48 | B65: K3 SOLUCIONES A LA INDUSTRIA ALIMENTICIA | D65: Susana Calvo - 81 1695 4703 proyectos3@serviciosk3.mx | E65: 1 | F65: JOSE LUIS | G65: =[1]DICIEMBRE!$BA$68 -> 0 | H65: =ENERO!BA65 -> 0 | I65: =FEBRERO!AX65 -> 0 | J65: =MARZO!BA66 -> 0 | S65: =(300*0.16+300)*E65 -> 348 | AC65: 348 | AZ65: =SUM(J65+S65+T65-U65-V65-W65-X65-Y65-Z65-AA65-AB65-AC65-AD65-AE65-AF65-AG65-AH65-AI65-AJ65-AK65-AL65-AM65-AN65-AO65-AP65-AQ65-AR65-AS65-AT65-AU65-AV65-AW65-AX65-AY65) -> 0
A66: 49 | B66: KARLA ZEBETH CLEMENTINA PEÑA MACIAS (EDUARDO ALMAGUER) | D66: Eduardo Almaguer - 81 2920 4044 abelardoalmaguer1991@gmail.com | E66: 1 | F66: JOSE LUIS | G66: =[1]DICIEMBRE!$BA$69 -> 0 | H66: =ENERO!BA66 -> 0 | I66: =FEBRERO!AX66 -> 0 | J66: =MARZO!BA67 -> 0 | S66: =(250*0.16+250)*E66 -> 290 | AW66: 290 | AZ66: =SUM(J66+S66+T66-U66-V66-W66-X66-Y66-Z66-AA66-AB66-AC66-AD66-AE66-AF66-AG66-AH66-AI66-AJ66-AK66-AL66-AM66-AN66-AO66-AP66-AQ66-AR66-AS66-AT66-AU66-AV66-AW66-AX66-AY66) -> 0
A67: 50 | B67: KROHNE DE MEXICO | C67: Nombre de la Empresa: KROHNE DE MEXICO RFC. KME091130LY6 CFDI : Gastos en General C.P.89110 Regimen Fiscal: R GENERAL DE LEY PERSONAS MORALES Forma de Pago: Transferencia Teléfono: (833) 217-3830 Contacto: Email: Pamela@KROHNEMEXICO.com 'erika@krohnemexico.com'; 'israel@krohnemexico.com'; 'maricela@krohnemexico.com' 1er Factura: 2070 | D67: (833) 217-3830 Ext. 101 Email:Pamela@KROHNEMEXICO.com 'erika@krohnemexico.com'; 'israel@krohnemexico.com'; 'maricela@krohnemexico.com' | E67: 17 | F67: JOSE LUIS | G67: =[1]DICIEMBRE!$BA$70 -> 0.002 | H67: =ENERO!BA67 -> 0.002 | I67: =FEBRERO!AX67 -> 0.002 | J67: =MARZO!BA68 -> 0.002 | S67: =(249*0.16+249)*E67 -> 4910.28 | Y67: 4910.28 | AZ67: =SUM(J67+S67+T67-U67-V67-W67-X67-Y67-Z67-AA67-AB67-AC67-AD67-AE67-AF67-AG67-AH67-AI67-AJ67-AK67-AL67-AM67-AN67-AO67-AP67-AQ67-AR67-AS67-AT67-AU67-AV67-AW67-AX67-AY67) -> 0.002 | BA67: BAJA DE CLIENTE 30-ABRIL-2025 COB. ABR'25: 2 BAJAS
A68: 51 | B68: LACAR ENERGY LOGISTIC - CARLOS MORENO | D68: Aylin Villanueva - 81 1240 3361 | E68: 4 | F68: JOSE LUIS | G68: =[1]DICIEMBRE!$BA$71 -> 0 | H68: =ENERO!BA68 -> 0 | I68: =FEBRERO!AX68 -> 0 | J68: =MARZO!BA69 -> 0 | S68: =(300*0.16+300)*E68 -> 1392 | T68: =2060*0.16+2060 -> 2389.6 | Y68: 1392 | AQ68: 2389.6 | AZ68: =SUM(J68+S68+T68-U68-V68-W68-X68-Y68-Z68-AA68-AB68-AC68-AD68-AE68-AF68-AG68-AH68-AI68-AJ68-AK68-AL68-AM68-AN68-AO68-AP68-AQ68-AR68-AS68-AT68-AU68-AV68-AW68-AX68-AY68) -> 0 | BA68: COB. ABR'25: 1 EQP. E INST. NUEVA Y 1 MENS. PROP. COBRAR EN MAYO MENS. COMPL.
A69: 52 | B69: LAMBI | C69: Nombre de la Empresa: LAMBI S.A. DE C.V. RFC. LAM9109013H1 CFDI : Gastos en General C.P.66062 Regimen Fiscal: R GENERAL DE LEY PERSONAS MORALES Forma de Pago: Transferencia Teléfono: 81 1908 0591 Contacto: Ericka Ortega Email: eortega@lambi.com.mx 1er Factura: 2008 | D69: Ericka Ortega (Compras) - 81 1908 0591 Email:trafico@lambi.com.mx jrojas@lambi.com.mx dquijas@lambi.com.mx | E69: 2 | F69: JOSE LUIS | G69: =[1]DICIEMBRE!$BA$72 -> -0.008 | H69: =ENERO!BA69 -> -0.008 | I69: =FEBRERO!AX69 -> 0.002 | J69: =MARZO!BA70 -> 0.002 | S69: =(249*0.16+249)*E69 -> 577.68 | AE69: 577.68 | AZ69: =SUM(J69+S69+T69-U69-V69-W69-X69-Y69-Z69-AA69-AB69-AC69-AD69-AE69-AF69-AG69-AH69-AI69-AJ69-AK69-AL69-AM69-AN69-AO69-AP69-AQ69-AR69-AS69-AT69-AU69-AV69-AW69-AX69-AY69) -> 0.002
A70: 53 | B70: LEMURA VIVIENDA | C70: Nombre de la Empresa: LEMURA VIVIENDA S.A. DE C.V. RFC. LVI170630MEA CFDI: Gastos en general Forma de Pago: Transferencia Teléfono: 81 1624 4288 Contacto: Ignacio Gaxiola Email: igaxiola@lemura.com.mx | D70: Ignacio Gaxiola - 81 1624 4288 Email:igaxiola@lemura.com.mx | E70: 1 | F70: JOSE LUIS | G70: =[1]DICIEMBRE!$BA$73 -> -866.52 | H70: =ENERO!BA70 -> -577.68 | I70: =FEBRERO!AX70 -> -288.84 | J70: =MARZO!BA71 -> 2.2737368e-12 | S70: =(249*0.16+249)*E70 -> 288.84 | AE70: 1733.04 | AZ70: =SUM(J70+S70+T70-U70-V70-W70-X70-Y70-Z70-AA70-AB70-AC70-AD70-AE70-AF70-AG70-AH70-AI70-AJ70-AK70-AL70-AM70-AN70-AO70-AP70-AQ70-AR70-AS70-AT70-AU70-AV70-AW70-AX70-AY70) -> -1444.2 | BA70: PAGO 6 MENSUALIDADES ADELANTADAS COBRAR HASTA SEPTIEMBRE 2025
A71: 54 | B71: LUIS ALBERTO DAVILA SALAZAR | C71: Nombre de la Empresa: LUIS ALBERTO DÁVILA SALAZAR RFC. DASL701219TM3 CFDI: Gastos en general Forma de Pago: Transferencia Teléfono: 813 074 5638 Contacto: Luis Dávila Email: luisdavila1970@gmail.com; luis.davila@alsglobal.com | D71: Luis Davila - 813 074 5638 Email:luisdavila1970@gmail.com | E71: 1 | F71: JOSE LUIS | G71: =[1]DICIEMBRE!$BA$74 -> 0 | H71: =ENERO!BA71 -> 0 | I71: =FEBRERO!AX71 -> 0 | J71: =MARZO!BA72 -> 0 | S71: 348 | AB71: 348 | AZ71: =SUM(J71+S71+T71-U71-V71-W71-X71-Y71-Z71-AA71-AB71-AC71-AD71-AE71-AF71-AG71-AH71-AI71-AJ71-AK71-AL71-AM71-AN71-AO71-AP71-AQ71-AR71-AS71-AT71-AU71-AV71-AW71-AX71-AY71) -> 0
A72: 55 | B72: LUIS JAVIER GONZALEZ PEREZ | C72: Nombre de la Empresa: LUIS JAVIER GONZALEZ PEREZ RFC. GOPL9105308A6 CFDI: Gastos en general Forma de Pago: Transferencia Teléfono: 811 907 9148 Contacto: Luis Javier Gonzalez Email: ljgonzalez3591@gmail.com | D72: Luis Javier Gonzalez Perez - 811 907 9148 Email:ljgonzalez3591@gmail.com | E72: 1 | F72: JOSE LUIS | G72: =[1]DICIEMBRE!$BA$76 -> 0 | H72: =ENERO!BA72 -> 0 | I72: =FEBRERO!AX72 -> 0 | J72: =MARZO!BA73 -> 0 | S72: =(300*0.16+300)*E72 -> 348 | AB72: 348 | AZ72: =SUM(J72+S72+T72-U72-V72-W72-X72-Y72-Z72-AA72-AB72-AC72-AD72-AE72-AF72-AG72-AH72-AI72-AJ72-AK72-AL72-AM72-AN72-AO72-AP72-AQ72-AR72-AS72-AT72-AU72-AV72-AW72-AX72-AY72) -> 0
A73: 56 | B73: MARINE DEL VALLE MENDOZA PEREZ - EDUARDO VENTURA MENDOZA | D73: Marine Mexico - 81 1994 9256 Eduardo Ventura - 81 3090 4628 Email:mendozael2003@yahoo.com | E73: 11 | F73: JOSE LUIS | G73: =[1]DICIEMBRE!$BA$36 -> 0.0012 | H73: =ENERO!BA73 -> -0.0076 | I73: =FEBRERO!AX73 -> 0.0024 | J73: =MARZO!BA74 -> 0.0024 | S73: =(250*0.16+250)*E73 -> 3190 | Y73: 3190 | AZ73: =SUM(J73+S73+T73-U73-V73-W73-X73-Y73-Z73-AA73-AB73-AC73-AD73-AE73-AF73-AG73-AH73-AI73-AJ73-AK73-AL73-AM73-AN73-AO73-AP73-AQ73-AR73-AS73-AT73-AU73-AV73-AW73-AX73-AY73) -> 0.0024
A74: 57 | B74: MARIO ALBERTO CABALLERO GARZA | D74: Mario Caballero - 81 1213 3136 | E74: 3 | F74: JOSE LUIS | G74: =[1]DICIEMBRE!$BA$78 -> 0.0012 | H74: =ENERO!BA74 -> 0.0012 | I74: =FEBRERO!AX74 -> 0.0012 | J74: =MARZO!BA75 -> 0.0012 | S74: =(250*0.16+250)*E74 -> 870 | Y74: 870 | AZ74: =SUM(J74+S74+T74-U74-V74-W74-X74-Y74-Z74-AA74-AB74-AC74-AD74-AE74-AF74-AG74-AH74-AI74-AJ74-AK74-AL74-AM74-AN74-AO74-AP74-AQ74-AR74-AS74-AT74-AU74-AV74-AW74-AX74-AY74) -> 0.0012
A75: 58 | B75: MARMOL Y GRANITO RIO - GERARDO NIETO | D75: Gerardo Nieto - 81 1184 1231 Email:fizz98@hotmail.com consueloer@marmolemperador.com | E75: 5 | F75: JOSE LUIS | G75: =[1]DICIEMBRE!$BA$51 -> 0 | H75: =ENERO!BA75 -> 0 | I75: =FEBRERO!AX75 -> 0 | J75: =MARZO!BA76 -> 0 | S75: =(300*0.16+300)*E75 -> 1740 | AE75: 1740 | AZ75: =SUM(J75+S75+T75-U75-V75-W75-X75-Y75-Z75-AA75-AB75-AC75-AD75-AE75-AF75-AG75-AH75-AI75-AJ75-AK75-AL75-AM75-AN75-AO75-AP75-AQ75-AR75-AS75-AT75-AU75-AV75-AW75-AX75-AY75) -> 0
A76: 59 | B76: MARTINEZ & DE LA ROSA CONSTRUCCIONES - ANTONIO MARTINEZ | D76: COMODATO Brenda Araujo - 81 3421 7089 Ing. Antonio Martínez -81 1537 7636 Email:facturas@myrconsa.mx catalinac@myrconsa.mx antoniomtz@myrconsa.mx | E76: 15 | F76: JOSE LUIS | G76: =[1]DICIEMBRE!$BA$22 -> -1.8189894e-12 | H76: =ENERO!BA76 -> -0.002 | I76: =FEBRERO!AX76 -> -0.002 | J76: =MARZO!BA77 -> -0.002 | S76: =(279*0.16+279)*E76 -> 4854.6 | AT76: 4854.6 | AZ76: =SUM(J76+S76+T76-U76-V76-W76-X76-Y76-Z76-AA76-AB76-AC76-AD76-AE76-AF76-AG76-AH76-AI76-AJ76-AK76-AL76-AM76-AN76-AO76-AP76-AQ76-AR76-AS76-AT76-AU76-AV76-AW76-AX76-AY76) -> -0.002
A77: 60 | B77: MCJ CHILLER - EVERARDO NUNCIO CUELLAR | D77: COMODATO Everardo Nuncio - 81 1823 3384 Pagos Brenda Ocañas - 81 7654 2904/81 18 72 2728 Email:oficina@mcjchillerservice.com | E77: 8 | F77: JOSE LUIS | G77: =[1]DICIEMBRE!$BA$40 -> 0.0004 | H77: =ENERO!BA77 -> 0.0004 | I77: =FEBRERO!AX77 -> 0.0004 | J77: =MARZO!BA78 -> 0.0004 | S77: =(269*0.16+269)*E77 -> 2496.32 | T77: =450*0.16+450 -> 522 | AB77: 3018.32 | AZ77: =SUM(J77+S77+T77-U77-V77-W77-X77-Y77-Z77-AA77-AB77-AC77-AD77-AE77-AF77-AG77-AH77-AI77-AJ77-AK77-AL77-AM77-AN77-AO77-AP77-AQ77-AR77-AS77-AT77-AU77-AV77-AW77-AX77-AY77) -> 0.0004 | BA77: COB. ABR'25: 1 REVISION
A78: 61 | B78: MIGUEL EDUARDO CASAS ARIZMENDI - MIGUEL ANGEL CASAS | C78: Nombre de la Empresa: MIGUEL EDUARDO CASAS ARIZMENDI RFC.: CAAM980824PA1 CFDI: Por Definir Forma de Pago: TransferenciaTeléfono: 811 418 8880 Contacto: Nidia Arizmendi Email: mactransportacion@gmail.com | D78: COMODATO Miguel Angel Casas - 811 566 5492 Email:mactransportacion@gmail.com | E78: 17 | F78: JOSE LUIS | H78: =ENERO!BA78 -> 0 | I78: =FEBRERO!AX78 -> -0.0024 | J78: =MARZO!BA79 -> -0.0024 | S78: =(289*0.16+289)*E78 -> 5699.08 | AU78: 5699.08 | AZ78: =SUM(J78+S78+T78-U78-V78-W78-X78-Y78-Z78-AA78-AB78-AC78-AD78-AE78-AF78-AG78-AH78-AI78-AJ78-AK78-AL78-AM78-AN78-AO78-AP78-AQ78-AR78-AS78-AT78-AU78-AV78-AW78-AX78-AY78) -> -0.0024
A79: 62 | B79: MYA TRANSPORTES, S.A. DE C.V. (MOLIENDAS Y ALIMENTOS) | C79: Nombre de la Empresa: MYA TRANSPORTES S.A. DE C.V. RFC. MTR0705245M3 CFDI: Por definir Forma de Pago: Cheque Bancario Teléfono: 81 8351 8283 Contacto: Srta. Elizabeth Garza / Sr. (s) Eduardo Garza / Emeterio Vargas. Email: administracion@myatsa.com; evargas@moliendas.com; egarza@moliendas.com; garzacavazos@hotmail.com, | D79: COMODATO Elizabeth Garza - 81 8351 8283 ext.126 Eduardo Garza / Emeterio Vargas Email:administracion@myatsa.com; evargas@moliendas.com; egarza@moliendas.com; garzacavazos@hotmail.com | E79: 16 | F79: DANIEL ESTRADA | G79: =[1]DICIEMBRE!$BA$81 -> -0.0012 | H79: =ENERO!BA79 -> -0.0012 | I79: =FEBRERO!AX79 -> -0.0012 | J79: =MARZO!BA80 -> -0.0012 | S79: =(5250+300)*0.16+5250+300 -> 6438 | AZ79: =SUM(J79+S79+T79-U79-V79-W79-X79-Y79-Z79-AA79-AB79-AC79-AD79-AE79-AF79-AG79-AH79-AI79-AJ79-AK79-AL79-AM79-AN79-AO79-AP79-AQ79-AR79-AS79-AT79-AU79-AV79-AW79-AX79-AY79) -> 6437.9988
A80: 63 | B80: NORMA LETICIA GONZALEZ VAZQUEZ (AARON ARRATIA AGUILAR) | D80: COMODATO Aaron Arratia Aguilar - 81 2339 0793 aaronarratiaaguilarisamel12@gmail.com | E80: 5 | F80: JOSE LUIS | G80: =[1]DICIEMBRE!$BA$119 -> -0.02 | H80: =ENERO!BA123 -> -0.02 | I80: =FEBRERO!AX80 -> 0 | J80: =MARZO!BA81 -> 0 | S80: =(300*0.16+300)*E80 -> 1740 | AF80: 1740 | AZ80: =SUM(J80+S80+T80-U80-V80-W80-X80-Y80-Z80-AA80-AB80-AC80-AD80-AE80-AF80-AG80-AH80-AI80-AJ80-AK80-AL80-AM80-AN80-AO80-AP80-AQ80-AR80-AS80-AT80-AU80-AV80-AW80-AX80-AY80) -> 0
A81: 64 | B81: PABLO EMILIANO RODRIGUEZ DURAN | D81: COMODATO Pablo Rodriguez - 81 2010 3744 pablordzmasper@hotmail.com | E81: 3 | F81: JOSE LUIS | G81: =[1]DICIEMBRE!$BA$83 -> 0 | H81: =ENERO!BA80 -> 0 | I81: =FEBRERO!AX81 -> 0 | J81: =MARZO!BA82 -> 0 | S81: =(300*0.16+300)*E81 -> 1044 | T81: =589*0.16+589 -> 683.24 | AS81: 1727.24 | AZ81: =SUM(J81+S81+T81-U81-V81-W81-X81-Y81-Z81-AA81-AB81-AC81-AD81-AE81-AF81-AG81-AH81-AI81-AJ81-AK81-AL81-AM81-AN81-AO81-AP81-AQ81-AR81-AS81-AT81-AU81-AV81-AW81-AX81-AY81) -> 0 | BA81: COB. ABR'25: 1 INST. NUEVA Y 1 MENS. PROP. 4 DIAS | BB81: PAGA A JOSE LUIS CON COMIDA PARA LUNA
A82: 65 | B82: PACKET CAR DE MONTERREY - PABLO ERNESTO CADENA ACEVEDO | C82: Nombre de la Empresa: PACKET CAR DE MONTERREY S.A. DE C.V. RFC. PCM200703M63 CFDI: Por definir Forma de Pago: Transferencia Teléfono: 811 722 2636 Contacto: Pablo Ernesto Cadena Acevedo Email: docrem@hotmail.com | D82: Pablo E. Cadena Acevedo - 811 722 2636 Email:docrem@hotmail.com | E82: 8 | F82: JOSE LUIS | G82: =[1]DICIEMBRE!$BA$82 -> 2784.0048 | H82: =ENERO!BA81 -> 0.0048 | I82: =FEBRERO!AX82 -> 0.0048 | J82: =MARZO!BA83 -> 0.0048 | S82: =(300*0.16+300)*E82 -> 2784 | Y82: 2784 | AZ82: =SUM(J82+S82+T82-U82-V82-W82-X82-Y82-Z82-AA82-AB82-AC82-AD82-AE82-AF82-AG82-AH82-AI82-AJ82-AK82-AL82-AM82-AN82-AO82-AP82-AQ82-AR82-AS82-AT82-AU82-AV82-AW82-AX82-AY82) -> 0.0048
A83: 66 | B83: PREFOM | D83: COMODATO Hugo Díaz - 81 1290 4608 admin@bloquerafbk.com | E83: 4 | F83: JOSE LUIS | G83: =[1]DICIEMBRE!$BA$84 -> 0 | H83: =ENERO!BA82 -> 0 | I83: =FEBRERO!AX83 -> 0 | J83: =MARZO!BA84 -> 0 | S83: =(220*0.16+220)*E83 -> 1020.8 | X83: 1020.8 | AZ83: =SUM(J83+S83+T83-U83-V83-W83-X83-Y83-Z83-AA83-AB83-AC83-AD83-AE83-AF83-AG83-AH83-AI83-AJ83-AK83-AL83-AM83-AN83-AO83-AP83-AQ83-AR83-AS83-AT83-AU83-AV83-AW83-AX83-AY83) -> 0
